Workbook

Sheet README — How to Use
A1: RAG SCREENING SHEET WORKBOOK | ESADE MSc Finance | Sustainable Finance | May 2026 Academic Prototype — Not Investment Advice — Not a Regulated ESG Product
A2: NINE-STEP WORKFLOW
A3: Step 1 | B3: Paste company identifiers | C3: Universe Tracker sheet → paste Company Name, Ticker, ISIN, Country, BICS Sector. One row per company. Row ID is calculated automatically.
A4: Step 2 | B4: Assign review priority | C4: Universe Tracker → Review Priority column. Deep Review = 10–12 companies for full Claude Project extraction. Light Screen = remaining 38–40.
A5: Step 3 | B5: Collect source documents | C5: For each Deep Review company: sustainability report PDF, annual report (if ESG-relevant), TCFD report, assurance statement. Log all in Source Register sheet.
A6: Step 4 | B6: Run RAG extraction in Claude Project | C6: Create one Claude Project per Deep Review company. Upload PDFs. Paste system prompt from 8-Test Greenwashing sheet. Run extraction. Save JSON output.
A7: Step 5 | B7: Paste outputs into RAG Screening Sheet | C7: Copy extracted evidence into relevant columns. Mark each cell with its source document and page reference. Use evidence confidence dropdowns.
A8: Step 6 | B8: Verify source evidence manually | C8: Verify ≥30% of all extractions against source PDF. 100% verification for any Watchlist or Exclusion flag. Record in Verification Log sheet.
A9: Step 7 | B9: Review scores and flags | C9: Check auto-calculated columns (G12–G15, G21, G22, H10–H12, I6, I7). Review any triggered flags. Note: C19, D12, E13, F11 require manual formula implementation — see Scoring Logic sheet.
A10: Step 8 | B10: Assign final RAG verdict | C10: Review I7 auto-verdict. Override in I8 if human judgement requires it. Document rationale in I10. Never leave I10 blank for Watchlist or Exclusion verdicts.
A11: Step 9 | B11: Handoff | C11: Pipeline Operator → JSON schema from JSON Output Schema sheet. ESG Specialist → indicator columns + Verification Log. Captain → Watchlist & Exclusion Summary sheet.
A13: COLOUR CODING
A14: Green fill | B14: Strong evidence / PASS | C14: Apply manually to cells with strong supporting evidence
A15: Amber fill | B15: Partial evidence / PARTIAL / see note | C15: Used automatically for C19/D12/E13/F11 placeholder cells (requires formula implementation)
A16: Red fill | B16: Failed test / hard exclusion trigger | C16: Apply manually to cells triggering hard exclusion
A17: Grey fill | B17: MISSING — evidence not found | C17: Apply manually when evidence is absent
A18: Yellow fill | B18: Unverified — human check required | C18: Apply when verification is pending
A20: IMPORTANT CONSTRAINTS
A21: Missing ≠ Good | B21: Absence of evidence is a risk signal, not positive evidence | C21: A company that does not disclose a metric receives no positive score for it
A22: Disclosure ≠ Performance | B22: Disclosing Scope 3 data ≠ performing well on Scope 3 | C22: Only the actual figures determine the climate score
A23: Eligibility ≠ Alignment | B23: EU Taxonomy eligible revenue ≠ aligned revenue | C23: Do not use eligibility to meet the ≥50% alignment mandate target
A24: Score ≠ Truth | B24: This model produces signals, not verdicts | C24: Human review required at all Watchlist and Exclusion decisions
A25: AI flags. Humans decide. Everything is logged. | B25: Core operating principle of this workbook | C25: All verdicts are subject to Captain and ESG Specialist confirmation
A27: SHEET DIRECTORY
A28: Sheet | B28: Purpose | C28: Owned By
A29: RAG Screening Sheet | B29: Main working sheet — one row per company, all groups A–I | C29: RAG Operator
A30: Universe Tracker | B30: 50-company master list with review priority and status | C30: RAG Operator / Data Engineer
A31: Watchlist & Exclusion Summary | B31: Decision-ready flags for Captain and ESG Specialist | C31: RAG Operator
A32: 8-Test Greenwashing | B32: Test definitions, pass/fail criteria, Claude Project system prompt | C32: RAG Operator
A33: Scoring Logic | B33: All formulas, weights, override rules, scoring point tables | C33: RAG Operator
A34: Biodiversity Framework | B34: ENCORE / WWF / Aqueduct / TNFD methodology reference | C34: RAG Operator
A35: Verification Log | B35: Manual verification records — 30% sample minimum | C35: RAG Operator
A36: Source Register | B36: All documents reviewed with URL and citation format | C36: RAG Operator
A37: Factor Definitions | B37: Academic rationale for every screening dimension | C37: RAG Operator
A38: Data Dictionary | B38: Glossary of all terms and abbreviations | C38: RAG Operator
A39: JSON Output Schema | B39: JSON structure for Pipeline Operator handoff | C39: RAG Operator / Pipeline Operator
A40: Disclaimer & Limitations | B40: Anti-overclaiming language — extract for Section 11 | C40: RAG Operator

Sheet RAG Screening Sheet
A1: RAG SCREENING SHEET | ESADE Sustainable Finance | Academic Prototype — Not Investment Advice | v1.0
A2: A — COMPANY IDENTIFIERS | K2: B — DOCUMENT COVERAGE | Z2: C — CLIMATE CLAIM CREDIBILITY | AT2: D — ESG SAFEGUARDS | BG2: E — BIODIVERSITY / NATURE-RISK | BU2: F — EU REGULATION / TAXONOMY | CG2: G — CONTROVERSY & GREENWASHING (8-TEST) | DC2: H — EVIDENCE QUALITY & VERIFICATION | DO2: I — FINAL RAG OUTPUT | EB2: J — SUMMARY TAB
A3: A | B3: A | C3: A | D3: A | E3: A | F3: A | G3: A | H3: A | I3: A | J3: A | K3: B | L3: B | M3: B | N3: B | O3: B | P3: B | Q3: B | R3: B | S3: B | T3: B | U3: B | V3: B | W3: B | X3: B | Y3: B | Z3: C | AA3: C | AB3: C | AC3: C | AD3: C | AE3: C | AF3: C | AG3: C | AH3: C | AI3: C | AJ3: C | AK3: C | AL3: C | AM3: C | AN3: C | AO3: C | AP3: C | AQ3: C | AR3: C | AS3: C | AT3: D | AU3: D | AV3: D | AW3: D | AX3: D | AY3: D | AZ3: D | BA3: D | BB3: D | BC3: D | BD3: D | BE3: D | BF3: D | BG3: E | BH3: E | BI3: E | BJ3: E | BK3: E | BL3: E | BM3: E | BN3: E | BO3: E | BP3: E | BQ3: E | BR3: E | BS3: E | BT3: E | BU3: F | BV3: F | BW3: F | BX3: F | BY3: F | BZ3: F | CA3: F | CB3: F | CC3: F | CD3: F | CE3: F | CF3: F | CG3: G | CH3: G | CI3: G | CJ3: G | CK3: G | CL3: G | CM3: G | CN3: G | CO3: G | CP3: G | CQ3: G | CR3: G | CS3: G | CT3: G | CU3: G | CV3: G | CW3: G | CX3: G | CY3: G | CZ3: G | DA3: G | DB3: G | DC3: H | DD3: H | DE3: H | DF3: H | DG3: H | DH3: H | DI3: H | DJ3: H | DK3: H | DL3: H | DM3: H | DN3: H | DO3: I | DP3: I | DQ3: I | DR3: I | DS3: I | DT3: I | DU3: I | DV3: I | DW3: I | DX3: I | DY3: I | DZ3: I | EA3: I | EB3: J | EC3: J | ED3: J | EE3: J | EF3: J
A4: 1 | B4: =A4+1 | C4: =B4+1 | D4: =C4+1 | E4: =D4+1 | F4: =E4+1 | G4: =F4+1 | H4: =G4+1 | I4: =H4+1 | ... EF4: =EE4+1
A5: =CONCATENATE(A3,A4) | B5: =CONCATENATE(B3,B4) | C5: =CONCATENATE(C3,C4) | D5: =CONCATENATE(D3,D4) | E5: =CONCATENATE(E3,E4) | F5: =CONCATENATE(F3,F4) | G5: =CONCATENATE(G3,G4) | H5: =CONCATENATE(H3,H4) | ... EF5: =CONCATENATE(EF3,EF4)
A6: Company Name | B6: Ticker | C6: ISIN | D6: Country (Incorporation) | E6: Country (Domicile) | F6: BICS Sector | G6: BICS Industry | H6: Universe Status | I6: Review Priority | J6: Row ID [auto] | K6: Annual Report Available? | L6: Sustainability Report Available? | M6: TCFD Report Available? | N6: CSRD / ESRS Disclosure? | O6: SBTi Database Checked? | P6: TPI Checked? | Q6: CA100+ Checked? | R6: ENCORE Checked? | S6: WWF BRF Checked? | T6: WRI Aqueduct Checked? | U6: Controversy Search Done? | V6: # Sources Reviewed | W6: Most Recent Report Year | X6: Data Vintage Note | Y6: Doc Coverage Flag [auto] | Z6: Net-Zero Target Claimed? | AA6: Net-Zero Target Year | AB6: Interim Target Stated? | AC6: Interim Target Year | AD6: Interim Target % Reduction | AE6: Interim Target Baseline Year | AF6: Scope 1+2 Coverage | AG6: Scope 3 Disclosed? | AH6: Scope 3 Categories Count (of 15) | AI6: Scope 3 Included in Target? | AJ6: SBTi Status | AK6: SBTi Approval Year | AL6: Transition Plan Disclosed? | AM6: Capex Alignment Evidence? | AN6: Capex Alignment Quote | AO6: Capex % Sustainable | AP6: Climate Governance Evidence | AQ6: Lobbying Consistency | AR6: Climate Credibility Score [auto] | AS6: Climate Red Flag | AT6: HR Policy Status | AU6: HR Policy Page Ref | AV6: UNGC Signatory? | AW6: UNGC Violation Evidence | AX6: OECD MNE Compliance | AY6: Supply Chain DD Evidence | AZ6: Labour / H&S Controversy | BA6: Board Sustainability Oversight | BB6: ESG-Linked Exec Pay | BC6: ESG Data Assurance | BD6: Assurance Provider | BE6: Safeguards Score [auto] | BF6: Safeguards Red Flag | BG6: Biodiversity Policy | BH6: Nature Dependency (ENCORE) | BI6: Nature Impact (ENCORE) | BJ6: Water Risk (WRI Aqueduct) | BK6: Land Use Exposure | BL6: Pollution / Waste Exposure | BM6: Biodiversity-Sensitive Sites | BN6: PAI 7 Relevance | BO6: PAI 7 % Revenue | BP6: Sector Nature Risk Class | BQ6: Mitigation Hierarchy Evidence | BR6: TNFD Alignment | BS6: Biodiversity Score [auto] | BT6: Nature-Risk Red Flag | BU6: Taxonomy Eligibility Source | BV6: Taxonomy Eligible Revenue % | BW6: Taxonomy Aligned Revenue % | BX6: Taxonomy Aligned Capex % | BY6: Alignment Company-Stated? | BZ6: DNSH Evidence | CA6: Minimum Safeguards Evidence | CB6: PAI Indicators Reported (of 18) | CC6: CSRD / ESRS Disclosure Quality | CD6: SFDR Fund Classification (self) | CE6: EU Reg Evidence Score [auto] | CF6: EU Reg Red Flag | CG6: Main Claim Tested | CH6: Claim Source Document | CI6: Claim Page / Section Ref | CJ6: 8-Test 1: Specificity | CK6: 8-Test 2: Metric | CL6: 8-Test 3: Baseline | CM6: 8-Test 4: Target | CN6: 8-Test 5: Time Horizon | CO6: 8-Test 6: Scope | CP6: 8-Test 7: Verification | CQ6: 8-Test 8: Consistency | CR6: # Tests FAILED [auto] | CS6: # Tests PARTIAL [auto] | CT6: # Tests MISSING [auto] | CU6: Greenwashing Risk Score [auto] | CV6: Worst Dimension | CW6: Controversy Severity | CX6: Controversy Description | CY6: Controversy Source | CZ6: Controversy Date | DA6: Watchlist Trigger [auto] | DB6: Exclusion Trigger [auto] | DC6: Key Evidence Quote | DD6: Key Evidence Source Doc | DE6: Key Evidence Page Ref | DF6: Evidence Confidence (1–5) | DG6: AI Extraction Confidence (1–5) | DH6: Verification Status | DI6: Verified By | DJ6: Verification Date | DK6: Verification Notes | DL6: Low-Confidence Flag [auto] | DM6: Human Review Required [auto] | DN6: Evidence Quality Score [auto] | DO6: Climate Verdict | DP6: Biodiversity Verdict | DQ6: Safeguards Verdict | DR6: Greenwashing Verdict | DS6: EU Reg Verdict | DT6: Overall RAG Score [auto] | DU6: Final RAG Verdict [auto] | DV6: Human Override | DW6: Recommended Action | DX6: Verdict Rationale | DY6: Open Questions | DZ6: Handoff Owner | EA6: Handoff Status | EB6: Missing Source Flag | EC6: Missing Page Reference Flag | ED6: Verified Evidence Count | EE6: Verification Completion Percentage | EF6: Companies Ready for Handoff
A7: Next PLC | B7: NXG | C7: =IF(ISBLANK('Universe Tracker'!D3),"",'Universe Tracker'!D3) | F7: =IF(ISBLANK('Universe Tracker'!F3),"",'Universe Tracker'!F3) | G7: =IF(ISBLANK('Universe Tracker'!G3),"",'Universe Tracker'!G3) | J7: =IF(ISBLANK(B7),"",B7&"_"&C7) | Y7: =IF(AND(V7>=2,K7="Yes",L7="Yes"),"Sufficient",IF(AND(V7>=1,OR(K7="Yes",L7="Yes")),"Thin","Insufficient")) | AR7: {=MIN(100, MAX(0, IFERROR(_xlfn.XLOOKUP(AJ7,'Lookup Tables'!$A$2:$A$7,'Lookup Tables'!$B$2:$B$7,0),0) + IF(Z7="Yes", IF(IFERROR(_xlfn.XLOOKUP(AJ7,'Lookup Tables'!$A$2:$A$7,'Lookup Tables'!$B$2:$B$7,0),0)<20, 5, 0), 0) + _xlfn.IFS(AB7="Yes", IF(ISNUMBER(AC7)*AND(AC7<=2030),15,10), AB7="Long-term Only", 5, AB7="No", 0, TRUE, 0) + _xlfn.IFS(AF7="Full",10, AF7="Partial",5, AF7="Scope 2 Only",3, TRUE,0) + _xlfn.IFS(AG7="Yes", IF(ISNUMBER(AH7)*AND(AH7>=5),10,6), AG7="Partial",4, TRUE,0) + _xlfn.IFS(AI7="Yes",5, AI7="Partial (material categories only)",3, TRUE,0) + _xlfn.IFS(AL7="Yes — Detailed",10, AL7="Yes — High Level",5, TRUE,0) + _xlfn.IFS(AM7="Yes — Quantified",15, AM7="Yes — Directional Only",7, TRUE,0) + _xlfn.IFS(AP7="Formal",5, AP7="Referenced",2, TRUE,0) + _xlfn.IFS(AQ7="No Issues Found",5, AQ7="Concern Identified",-5, AQ7="Severe Contradiction",-15, TRUE,0) + _xlfn.IFS(BC7="Reasonable Assurance",5, BC7="Limited Assurance",3, TRUE,0) - IF(AND(Z7="Yes", AI7="No"), 10, 0) - IF(AND(Z7="Yes", AM7="No"), 10, 0) ))} | BE7: {=MIN(100, MAX(0, IFERROR(_xlfn.XLOOKUP(AT7,'Lookup Tables'!$D$2:$D$6,'Lookup Tables'!$E$2:$E$6,0),0) + IFERROR(_xlfn.XLOOKUP(AV7,'Lookup Tables'!$G$2:$G$5,'Lookup Tables'!$H$2:$H$5,0),0) + IFERROR(_xlfn.XLOOKUP(AW7,'Lookup Tables'!$J$2:$J$5,'Lookup Tables'!$K$2:$K$5,0),0) + _xlfn.IFS(AX7="No Issues",10, AX7="Complaint Filed",3, AX7="Confirmed Breach",-15, TRUE,0) + IFERROR(_xlfn.XLOOKUP(AY7,'Lookup Tables'!$M$2:$M$6,'Lookup Tables'!$N$2:$N$6,0),0) + IFERROR(_xlfn.XLOOKUP(AZ7,'Lookup Tables'!$P$2:$P$6,'Lookup Tables'!$Q$2:$Q$6,0),0) + _xlfn.IFS(BA7="Formal Board Committee",5, BA7="Board Oversight Mentioned",2, TRUE,0) + _xlfn.IFS(BB7="Yes — Quantified Targets",5, BB7="Yes — Discretionary Only",2, TRUE,0) + _xlfn.IFS(BC7="Reasonable Assurance",5, BC7="Limited Assurance",3, BC7="Management Review Only",1, TRUE,0) ))} | BS7: {=MIN(100, MAX(0, IFERROR(_xlfn.XLOOKUP(BG7,'Lookup Tables'!$A$11:$A$16,'Lookup Tables'!$B$11:$B$16,0),0) + IFERROR(_xlfn.XLOOKUP(BR7,'Lookup Tables'!$M$11:$M$14,'Lookup Tables'!$N$11:$N$14,0),0) + IFERROR(_xlfn.XLOOKUP(BQ7,'Lookup Tables'!$J$11:$J$15,'Lookup Tables'!$K$11:$K$15,0),0) + IFERROR(_xlfn.XLOOKUP(BH7,'Lookup Tables'!$D$11:$D$15,'Lookup Tables'!$E$11:$E$15,0),0) + IFERROR(_xlfn.XLOOKUP(BJ7,'Lookup Tables'!$G$11:$G$16,'Lookup Tables'!$H$11:$H$16,0),0) + IFERROR(_xlfn.XLOOKUP(BN7,'Lookup Tables'!$P$11:$P$15,'Lookup Tables'!$Q$11:$Q$15,0),0) + _xlfn.IFS(BM7="No Evidence",10, BM7="Unknown",3, BM7="Likely",0, BM7="Confirmed",-10, TRUE,3) + IFERROR(_xlfn.XLOOKUP(BP7,'Lookup Tables'!$J$21:$J$24,'Lookup Tables'!$K$21:$K$24,0),0) ))} | CE7: {=MIN(100, MAX(0, IF(ISNUMBER(BV7)*AND(BV7>0), 10, 0) + _xlfn.IFS(BY7="Independently Verified",25, BY7="Yes",15, TRUE,0) + IFERROR(_xlfn.XLOOKUP(BZ7,'Lookup Tables'!$A$21:$A$24,'Lookup Tables'!$B$21:$B$24,0),0) + IFERROR(_xlfn.XLOOKUP(CA7,'Lookup Tables'!$D$21:$D$24,'Lookup Tables'!$E$21:$E$24,0),0) + _xlfn.IFS(ISNUMBER(CB7)*AND(CB7>=11),15, ISNUMBER(CB7)*AND(CB7>=6),10, ISNUMBER(CB7)*AND(CB7>=1),5, TRUE,0) + IFERROR(_xlfn.XLOOKUP(CC7,'Lookup Tables'!$G$21:$G$25,'Lookup Tables'!$H$21:$H$25,0),0) - IF(ISNUMBER(BW7)*AND(ISNUMBER(BV7))*AND(BW7>BV7), 20, 0) - IF(AND(BY7="Yes", ISNUMBER(BW7), BW7>60), 10, 0) ))} | CR7: =COUNTIF(CJ7:CQ7,"FAIL") | CS7: =COUNTIF(CJ7:CQ7,"PARTIAL") | CT7: =COUNTIF(CJ7:CQ7,"MISSING") | CU7: =MIN(100, CR7*15 + CS7*6 + CT7*3 + IFERROR(_xlfn.XLOOKUP(CW7,'Lookup Tables'!$M$21:$M$25,'Lookup Tables'!$N$21:$N$25,0),0) ) | CV7: =IFERROR( CHOOSE( MATCH("FAIL",CJ7:CQ7,0), "1-Specificity","2-Metric","3-Baseline","4-Target", "5-Time Horizon","6-Scope","7-Verification","8-Consistency" ), IFERROR( CHOOSE( MATCH("PARTIAL",CJ7:CQ7,0), "1-Specificity","2-Metric","3-Baseline","4-Target", "5-Time Horizon","6-Scope","7-Verification","8-Consistency" ), "No failures" ) ) | DA7: =IF(OR(CU7>=50,CW7="Material",CW7="Severe",AS7="Material",AS7="Severe",BF7="Material",BF7="Severe — Exclusion Trigger",AND(ISNUMBER(BS7),BS7<30)),"Yes","No") | DB7: =IF(OR(CR7>=6,AW7="Confirmed Violation",AX7="Confirmed Breach"),"Yes — Automatic",IF(CW7="Severe","Yes — Requires Captain Confirmation","No")) | DL7: =IF(OR(IFERROR(VALUE(LEFT(DF7,1)),99)<=2,IFERROR(VALUE(LEFT(DG7,1)),99)<=2),"Flagged","Clear") | DM7: =IF(OR(DA7="Yes",DB7<>"No",DH7="Unverified",DL7="Flagged"),"Yes","No") | DN7: {=MIN(100, IF(ISNUMBER(V7), _xlfn.IFS(V7>=3,25, V7=2,15, V7=1,5, TRUE,0), 0) + IFERROR(_xlfn.IFS(VALUE(LEFT(DF7,1))=5,25, VALUE(LEFT(DF7,1))=4,20, VALUE(LEFT(DF7,1))=3,15, VALUE(LEFT(DF7,1))=2,8, TRUE,0), 15) + IFERROR(_xlfn.IFS(VALUE(LEFT(DG7,1))=5,25, VALUE(LEFT(DG7,1))=4,20, VALUE(LEFT(DG7,1))=3,15, VALUE(LEFT(DG7,1))=2,8, TRUE,0), 15) + _xlfn.IFS(DH7="Fully Verified",25, DH7="Partially Verified",12, TRUE,0) )} | DO7: {=_xlfn.IFS( ISBLANK(AR7), "Insufficient Evidence", AND(AR7>=65, AJ7="Approved"), "Strong", AR7>=65, "Adequate", AR7>=40, "Adequate", AR7>=20, "Weak", TRUE, "Insufficient Evidence" )} | DP7: {=_xlfn.IFS( ISBLANK(BS7), "Insufficient Evidence", BS7>=65, "Strong", BS7>=40, "Adequate", BS7>=20, "Weak", TRUE, "Insufficient Evidence" )} | DQ7: {=_xlfn.IFS( ISBLANK(BE7), "Insufficient Evidence", OR(AW7="Confirmed Violation", AX7="Confirmed Breach"), "Severe — Hard Trigger", BE7>=65, "Strong", BE7>=40, "Adequate", BE7>=20, "Weak", TRUE, "Insufficient Evidence" )} | DR7: {=_xlfn.IFS( ISBLANK(CU7), "Insufficient Evidence", CU7<=20, "Low Risk", CU7<=50, "Moderate Risk", CU7<=75, "High Risk", TRUE, "Very High Risk" )} | DS7: {=_xlfn.IFS( ISBLANK(CE7), "Insufficient Evidence", AND(ISNUMBER(BW7),ISNUMBER(BV7),BW7>BV7), "Overclaiming Risk", CE7>=65, "Strong", CE7>=40, "Adequate", TRUE, "Weak" )} | DT7: =IF(DB7="Yes — Automatic",0,ROUND((IF(ISNUMBER(AR7),AR7,0)*0.3+IF(ISNUMBER(BS7),BS7,0)*0.2+IF(ISNUMBER(BE7),BE7,0)*0.2+IF(ISNUMBER(CE7),CE7,0)*0.15+(100-IF(ISNUMBER(CU7),CU7,50))*0.15)*IF(DN7>=75,1,IF(DN7>=50,0.9,IF(DN7>=25,0.75,0.6))),1)) | DU7: {=_xlfn.IFS( DV7="Upgraded to Clear", "Clear", DV7="Downgraded to Watchlist", "Watchlist", DV7="Downgraded to Exclusion", "Exclusion Risk", DB7="Yes — Automatic", "Exclusion Risk", OR(AW7="Confirmed Violation", AX7="Confirmed Breach"), "Exclusion Risk", OR(V7=0, ISBLANK(V7), DN7<20), "Insufficient Evidence", AND(DT7>=65, DA7="No", DB7="No"), "Clear", OR(DT7>=40, DA7="Yes"), "Watchlist", TRUE, "Exclusion Risk" )} | DW7: {=_xlfn.IFS( DU7="Exclusion Risk", "Exclude — Hard Trigger", DU7="Insufficient Evidence", "Watchlist — Further Evidence Needed", DU7="Watchlist", "Watchlist — Further Evidence Needed", AND(DU7="Clear", DT7>=80), "Include — No Conditions", DU7="Clear", "Include — Monitor", TRUE, "Watchlist — Further Evidence Needed" )} | EB7: =IF(OR(V7=0, ISBLANK(V7)), "MISSING — No sources reviewed", "") | EC7: =IF(AND(NOT(ISBLANK(DC7)), ISBLANK(DE7)), "PAGE REF MISSING", "") | ED7: =COUNTIF(DH7:DH56,"Fully Verified") | EE7: =IFERROR(COUNTIF(DH7:DH56,"Fully Verified")/COUNTA(B7:B56),0) | EF7: =COUNTIFS(DU7:DU56,"Clear",DH7:DH56,"Fully Verified")
A8: SBM Offshore NV | B8: IHCB | C8: NL0000360618 | F8: =IF(ISBLANK('Universe Tracker'!F4),"",'Universe Tracker'!F4) | G8: =IF(ISBLANK('Universe Tracker'!G4),"",'Universe Tracker'!G4) | J8: =IF(ISBLANK(B8),"",B8&"_"&C8) | O8: Yes | P8: Yes | Y8: =IF(AND(V8>=2,K8="Yes",L8="Yes"),"Sufficient",IF(AND(V8>=1,OR(K8="Yes",L8="Yes")),"Thin","Insufficient")) | AJ8: Not in SBTi database (checked 2026-05-21) | AR8: {=MIN(100, MAX(0, IFERROR(_xlfn.XLOOKUP(AJ8,'Lookup Tables'!$A$2:$A$7,'Lookup Tables'!$B$2:$B$7,0),0) + IF(Z8="Yes", IF(IFERROR(_xlfn.XLOOKUP(AJ8,'Lookup Tables'!$A$2:$A$7,'Lookup Tables'!$B$2:$B$7,0),0)<20, 5, 0), 0) + _xlfn.IFS(AB8="Yes", IF(ISNUMBER(AC8)*AND(AC8<=2030),15,10), AB8="Long-term Only", 5, AB8="No", 0, TRUE, 0) + _xlfn.IFS(AF8="Full",10, AF8="Partial",5, AF8="Scope 2 Only",3, TRUE,0) + _xlfn.IFS(AG8="Yes", IF(ISNUMBER(AH8)*AND(AH8>=5),10,6), AG8="Partial",4, TRUE,0) + _xlfn.IFS(AI8="Yes",5, AI8="Partial (material categories only)",3, TRUE,0) + _xlfn.IFS(AL8="Yes — Detailed",10, AL8="Yes — High Level",5, TRUE,0) + _xlfn.IFS(AM8="Yes — Quantified",15, AM8="Yes — Directional Only",7, TRUE,0) + _xlfn.IFS(AP8="Formal",5, AP8="Referenced",2, TRUE,0) + _xlfn.IFS(AQ8="No Issues Found",5, AQ8="Concern Identified",-5, AQ8="Severe Contradiction",-15, TRUE,0) + _xlfn.IFS(BC8="Reasonable Assurance",5, BC8="Limited Assurance",3, TRUE,0) - IF(AND(Z8="Yes", AI8="No"), 10, 0) - IF(AND(Z8="Yes", AM8="No"), 10, 0) ))} | BE8: {=MIN(100, MAX(0, IFERROR(_xlfn.XLOOKUP(AT8,'Lookup Tables'!$D$2:$D$6,'Lookup Tables'!$E$2:$E$6,0),0) + IFERROR(_xlfn.XLOOKUP(AV8,'Lookup Tables'!$G$2:$G$5,'Lookup Tables'!$H$2:$H$5,0),0) + IFERROR(_xlfn.XLOOKUP(AW8,'Lookup Tables'!$J$2:$J$5,'Lookup Tables'!$K$2:$K$5,0),0) + _xlfn.IFS(AX8="No Issues",10, AX8="Complaint Filed",3, AX8="Confirmed Breach",-15, TRUE,0) + IFERROR(_xlfn.XLOOKUP(AY8,'Lookup Tables'!$M$2:$M$6,'Lookup Tables'!$N$2:$N$6,0),0) + IFERROR(_xlfn.XLOOKUP(AZ8,'Lookup Tables'!$P$2:$P$6,'Lookup Tables'!$Q$2:$Q$6,0),0) + _xlfn.IFS(BA8="Formal Board Committee",5, BA8="Board Oversight Mentioned",2, TRUE,0) + _xlfn.IFS(BB8="Yes — Quantified Targets",5, BB8="Yes — Discretionary Only",2, TRUE,0) + _xlfn.IFS(BC8="Reasonable Assurance",5, BC8="Limited Assurance",3, BC8="Management Review Only",1, TRUE,0) ))} | BS8: {=MIN(100, MAX(0, IFERROR(_xlfn.XLOOKUP(BG8,'Lookup Tables'!$A$11:$A$16,'Lookup Tables'!$B$11:$B$16,0),0) + IFERROR(_xlfn.XLOOKUP(BR8,'Lookup Tables'!$M$11:$M$14,'Lookup Tables'!$N$11:$N$14,0),0) + IFERROR(_xlfn.XLOOKUP(BQ8,'Lookup Tables'!$J$11:$J$15,'Lookup Tables'!$K$11:$K$15,0),0) + IFERROR(_xlfn.XLOOKUP(BH8,'Lookup Tables'!$D$11:$D$15,'Lookup Tables'!$E$11:$E$15,0),0) + IFERROR(_xlfn.XLOOKUP(BJ8,'Lookup Tables'!$G$11:$G$16,'Lookup Tables'!$H$11:$H$16,0),0) + IFERROR(_xlfn.XLOOKUP(BN8,'Lookup Tables'!$P$11:$P$15,'Lookup Tables'!$Q$11:$Q$15,0),0) + _xlfn.IFS(BM8="No Evidence",10, BM8="Unknown",3, BM8="Likely",0, BM8="Confirmed",-10, TRUE,3) + IFERROR(_xlfn.XLOOKUP(BP8,'Lookup Tables'!$J$21:$J$24,'Lookup Tables'!$K$21:$K$24,0),0) ))} | CE8: {=MIN(100, MAX(0, IF(ISNUMBER(BV8)*AND(BV8>0), 10, 0) + _xlfn.IFS(BY8="Independently Verified",25, BY8="Yes",15, TRUE,0) + IFERROR(_xlfn.XLOOKUP(BZ8,'Lookup Tables'!$A$21:$A$24,'Lookup Tables'!$B$21:$B$24,0),0) + IFERROR(_xlfn.XLOOKUP(CA8,'Lookup Tables'!$D$21:$D$24,'Lookup Tables'!$E$21:$E$24,0),0) + _xlfn.IFS(ISNUMBER(CB8)*AND(CB8>=11),15, ISNUMBER(CB8)*AND(CB8>=6),10, ISNUMBER(CB8)*AND(CB8>=1),5, TRUE,0) + IFERROR(_xlfn.XLOOKUP(CC8,'Lookup Tables'!$G$21:$G$25,'Lookup Tables'!$H$21:$H$25,0),0) - IF(ISNUMBER(BW8)*AND(ISNUMBER(BV8))*AND(BW8>BV8), 20, 0) - IF(AND(BY8="Yes", ISNUMBER(BW8), BW8>60), 10, 0) ))} | CG8: Including the use of certified climate projects to compensate any residual scope 1 and 2 emissions | CH8: SBM-Offshore-Annual-Report-2025.pdf | CI8: 12 | CJ8: PARTIAL | CK8: PASS | CL8: PASS | CM8: PARTIAL | CN8: PASS | CO8: PASS | CP8: PARTIAL | CQ8: PARTIAL | CR8: =COUNTIF(CJ8:CQ8,"FAIL") | CS8: =COUNTIF(CJ8:CQ8,"PARTIAL") | CT8: =COUNTIF(CJ8:CQ8,"MISSING") | CU8: =MIN(100, CR8*15 + CS8*6 + CT8*3 + IFERROR(_xlfn.XLOOKUP(CW8,'Lookup Tables'!$M$21:$M$25,'Lookup Tables'!$N$21:$N$25,0),0) ) | CV8: =IFERROR( CHOOSE( MATCH("FAIL",CJ8:CQ8,0), "1-Specificity","2-Metric","3-Baseline","4-Target", "5-Time Horizon","6-Scope","7-Verification","8-Consistency" ), IFERROR( CHOOSE( MATCH("PARTIAL",CJ8:CQ8,0), "1-Specificity","2-Metric","3-Baseline","4-Target", "5-Time Horizon","6-Scope","7-Verification","8-Consistency" ), "No failures" ) ) | DA8: =IF(OR(CU8>=50,CW8="Material",CW8="Severe",AS8="Material",AS8="Severe",BF8="Material",BF8="Severe — Exclusion Trigger",AND(ISNUMBER(BS8),BS8<30)),"Yes","No") | DB8: =IF(OR(CR8>=6,AW8="Confirmed Violation",AX8="Confirmed Breach"),"Yes — Automatic",IF(CW8="Severe","Yes — Requires Captain Confirmation","No")) | DC8: Including the use of certified climate projects to compensate any residual scope 1 and 2 emissions | DD8: SBM-Offshore-Annual-Report-2025.pdf | DE8: 12 | DF8: 4 | DG8: 4 | DH8: PENDING | DL8: =IF(OR(IFERROR(VALUE(LEFT(DF8,1)),99)<=2,IFERROR(VALUE(LEFT(DG8,1)),99)<=2),"Flagged","Clear") | DM8: =IF(OR(DA8="Yes",DB8<>"No",DH8="Unverified",DL8="Flagged"),"Yes","No") | DN8: {=MIN(100, IF(ISNUMBER(V8), _xlfn.IFS(V8>=3,25, V8=2,15, V8=1,5, TRUE,0), 0) + IFERROR(_xlfn.IFS(VALUE(LEFT(DF8,1))=5,25, VALUE(LEFT(DF8,1))=4,20, VALUE(LEFT(DF8,1))=3,15, VALUE(LEFT(DF8,1))=2,8, TRUE,0), 15) + IFERROR(_xlfn.IFS(VALUE(LEFT(DG8,1))=5,25, VALUE(LEFT(DG8,1))=4,20, VALUE(LEFT(DG8,1))=3,15, VALUE(LEFT(DG8,1))=2,8, TRUE,0), 15) + _xlfn.IFS(DH8="Fully Verified",25, DH8="Partially Verified",12, TRUE,0) )} | DO8: {=_xlfn.IFS( ISBLANK(AR8), "Insufficient Evidence", AND(AR8>=65, AJ8="Approved"), "Strong", AR8>=65, "Adequate", AR8>=40, "Adequate", AR8>=20, "Weak", TRUE, "Insufficient Evidence" )} | DP8: {=_xlfn.IFS( ISBLANK(BS8), "Insufficient Evidence", BS8>=65, "Strong", BS8>=40, "Adequate", BS8>=20, "Weak", TRUE, "Insufficient Evidence" )} | DQ8: {=_xlfn.IFS( ISBLANK(BE8), "Insufficient Evidence", OR(AW8="Confirmed Violation", AX8="Confirmed Breach"), "Severe — Hard Trigger", BE8>=65, "Strong", BE8>=40, "Adequate", BE8>=20, "Weak", TRUE, "Insufficient Evidence" )} | DR8: {=_xlfn.IFS( ISBLANK(CU8), "Insufficient Evidence", CU8<=20, "Low Risk", CU8<=50, "Moderate Risk", CU8<=75, "High Risk", TRUE, "Very High Risk" )} | DS8: {=_xlfn.IFS( ISBLANK(CE8), "Insufficient Evidence", AND(ISNUMBER(BW8),ISNUMBER(BV8),BW8>BV8), "Overclaiming Risk", CE8>=65, "Strong", CE8>=40, "Adequate", TRUE, "Weak" )} | DT8: =IF(DB8="Yes — Automatic",0,ROUND((IF(ISNUMBER(AR8),AR8,0)*0.3+IF(ISNUMBER(BS8),BS8,0)*0.2+IF(ISNUMBER(BE8),BE8,0)*0.2+IF(ISNUMBER(CE8),CE8,0)*0.15+(100-IF(ISNUMBER(CU8),CU8,50))*0.15)*IF(DN8>=75,1,IF(DN8>=50,0.9,IF(DN8>=25,0.75,0.6))),1)) | DU8: {=_xlfn.IFS( DV8="Upgraded to Clear", "Clear", DV8="Downgraded to Watchlist", "Watchlist", DV8="Downgraded to Exclusion", "Exclusion Risk", DB8="Yes — Automatic", "Exclusion Risk", OR(AW8="Confirmed Violation", AX8="Confirmed Breach"), "Exclusion Risk", OR(V8=0, ISBLANK(V8), DN8<20), "Insufficient Evidence", AND(DT8>=65, DA8="No", DB8="No"), "Clear", OR(DT8>=40, DA8="Yes"), "Watchlist", TRUE, "Exclusion Risk" )} | DW8: {=_xlfn.IFS( DU8="Exclusion Risk", "Exclude — Hard Trigger", DU8="Insufficient Evidence", "Watchlist — Further Evidence Needed", DU8="Watchlist", "Watchlist — Further Evidence Needed", AND(DU8="Clear", DT8>=80), "Include — No Conditions", DU8="Clear", "Include — Monitor", TRUE, "Watchlist — Further Evidence Needed" )} | DX8: Main claim: "Including the use of certified climate projects to compensate any residual scope 1 and 2 emissions" (SBM-Offshore-Annual-Report-2025.pdf, p12). SBTi: no validated target in the SBTi database. 8-Test: 4 PARTIAL, 0 FAIL, 0 MISSING -> PASS. Offshore-energy contractor. Disclosure is structured (2016 base year, intermediary 2030 targets, ISAE limited assurance) but four MED flags reflect an offset-reliant near-term 'climate neutral' claim, SBTi-guideline-based (not... | EB8: =IF(OR(V8=0, ISBLANK(V8)), "MISSING — No sources reviewed", "") | EC8: =IF(AND(NOT(ISBLANK(DC8)), ISBLANK(DE8)), "PAGE REF MISSING", "")
A9: Drax Group PLC | B9: D9F2 | C9: =IF(ISBLANK('Universe Tracker'!D5),"",'Universe Tracker'!D5) | F9: =IF(ISBLANK('Universe Tracker'!F5),"",'Universe Tracker'!F5) | G9: =IF(ISBLANK('Universe Tracker'!G5),"",'Universe Tracker'!G5) | J9: =IF(ISBLANK(B9),"",B9&"_"&C9) | Y9: =IF(AND(V9>=2,K9="Yes",L9="Yes"),"Sufficient",IF(AND(V9>=1,OR(K9="Yes",L9="Yes")),"Thin","Insufficient")) | AR9: {=MIN(100, MAX(0, IFERROR(_xlfn.XLOOKUP(AJ9,'Lookup Tables'!$A$2:$A$7,'Lookup Tables'!$B$2:$B$7,0),0) + IF(Z9="Yes", IF(IFERROR(_xlfn.XLOOKUP(AJ9,'Lookup Tables'!$A$2:$A$7,'Lookup Tables'!$B$2:$B$7,0),0)<20, 5, 0), 0) + _xlfn.IFS(AB9="Yes", IF(ISNUMBER(AC9)*AND(AC9<=2030),15,10), AB9="Long-term Only", 5, AB9="No", 0, TRUE, 0) + _xlfn.IFS(AF9="Full",10, AF9="Partial",5, AF9="Scope 2 Only",3, TRUE,0) + _xlfn.IFS(AG9="Yes", IF(ISNUMBER(AH9)*AND(AH9>=5),10,6), AG9="Partial",4, TRUE,0) + _xlfn.IFS(AI9="Yes",5, AI9="Partial (material categories only)",3, TRUE,0) + _xlfn.IFS(AL9="Yes — Detailed",10, AL9="Yes — High Level",5, TRUE,0) + _xlfn.IFS(AM9="Yes — Quantified",15, AM9="Yes — Directional Only",7, TRUE,0) + _xlfn.IFS(AP9="Formal",5, AP9="Referenced",2, TRUE,0) + _xlfn.IFS(AQ9="No Issues Found",5, AQ9="Concern Identified",-5, AQ9="Severe Contradiction",-15, TRUE,0) + _xlfn.IFS(BC9="Reasonable Assurance",5, BC9="Limited Assurance",3, TRUE,0) - IF(AND(Z9="Yes", AI9="No"), 10, 0) - IF(AND(Z9="Yes", AM9="No"), 10, 0) ))} | BE9: {=MIN(100, MAX(0, IFERROR(_xlfn.XLOOKUP(AT9,'Lookup Tables'!$D$2:$D$6,'Lookup Tables'!$E$2:$E$6,0),0) + IFERROR(_xlfn.XLOOKUP(AV9,'Lookup Tables'!$G$2:$G$5,'Lookup Tables'!$H$2:$H$5,0),0) + IFERROR(_xlfn.XLOOKUP(AW9,'Lookup Tables'!$J$2:$J$5,'Lookup Tables'!$K$2:$K$5,0),0) + _xlfn.IFS(AX9="No Issues",10, AX9="Complaint Filed",3, AX9="Confirmed Breach",-15, TRUE,0) + IFERROR(_xlfn.XLOOKUP(AY9,'Lookup Tables'!$M$2:$M$6,'Lookup Tables'!$N$2:$N$6,0),0) + IFERROR(_xlfn.XLOOKUP(AZ9,'Lookup Tables'!$P$2:$P$6,'Lookup Tables'!$Q$2:$Q$6,0),0) + _xlfn.IFS(BA9="Formal Board Committee",5, BA9="Board Oversight Mentioned",2, TRUE,0) + _xlfn.IFS(BB9="Yes — Quantified Targets",5, BB9="Yes — Discretionary Only",2, TRUE,0) + _xlfn.IFS(BC9="Reasonable Assurance",5, BC9="Limited Assurance",3, BC9="Management Review Only",1, TRUE,0) ))} | BS9: {=MIN(100, MAX(0, IFERROR(_xlfn.XLOOKUP(BG9,'Lookup Tables'!$A$11:$A$16,'Lookup Tables'!$B$11:$B$16,0),0) + IFERROR(_xlfn.XLOOKUP(BR9,'Lookup Tables'!$M$11:$M$14,'Lookup Tables'!$N$11:$N$14,0),0) + IFERROR(_xlfn.XLOOKUP(BQ9,'Lookup Tables'!$J$11:$J$15,'Lookup Tables'!$K$11:$K$15,0),0) + IFERROR(_xlfn.XLOOKUP(BH9,'Lookup Tables'!$D$11:$D$15,'Lookup Tables'!$E$11:$E$15,0),0) + IFERROR(_xlfn.XLOOKUP(BJ9,'Lookup Tables'!$G$11:$G$16,'Lookup Tables'!$H$11:$H$16,0),0) + IFERROR(_xlfn.XLOOKUP(BN9,'Lookup Tables'!$P$11:$P$15,'Lookup Tables'!$Q$11:$Q$15,0),0) + _xlfn.IFS(BM9="No Evidence",10, BM9="Unknown",3, BM9="Likely",0, BM9="Confirmed",-10, TRUE,3) + IFERROR(_xlfn.XLOOKUP(BP9,'Lookup Tables'!$J$21:$J$24,'Lookup Tables'!$K$21:$K$24,0),0) ))} | CE9: {=MIN(100, MAX(0, IF(ISNUMBER(BV9)*AND(BV9>0), 10, 0) + _xlfn.IFS(BY9="Independently Verified",25, BY9="Yes",15, TRUE,0) + IFERROR(_xlfn.XLOOKUP(BZ9,'Lookup Tables'!$A$21:$A$24,'Lookup Tables'!$B$21:$B$24,0),0) + IFERROR(_xlfn.XLOOKUP(CA9,'Lookup Tables'!$D$21:$D$24,'Lookup Tables'!$E$21:$E$24,0),0) + _xlfn.IFS(ISNUMBER(CB9)*AND(CB9>=11),15, ISNUMBER(CB9)*AND(CB9>=6),10, ISNUMBER(CB9)*AND(CB9>=1),5, TRUE,0) + IFERROR(_xlfn.XLOOKUP(CC9,'Lookup Tables'!$G$21:$G$25,'Lookup Tables'!$H$21:$H$25,0),0) - IF(ISNUMBER(BW9)*AND(ISNUMBER(BV9))*AND(BW9>BV9), 20, 0) - IF(AND(BY9="Yes", ISNUMBER(BW9), BW9>60), 10, 0) ))} | CR9: =COUNTIF(CJ9:CQ9,"FAIL") | CS9: =COUNTIF(CJ9:CQ9,"PARTIAL") | CT9: =COUNTIF(CJ9:CQ9,"MISSING") | CU9: =MIN(100, CR9*15 + CS9*6 + CT9*3 + IFERROR(_xlfn.XLOOKUP(CW9,'Lookup Tables'!$M$21:$M$25,'Lookup Tables'!$N$21:$N$25,0),0) ) | CV9: =IFERROR( CHOOSE( MATCH("FAIL",CJ9:CQ9,0), "1-Specificity","2-Metric","3-Baseline","4-Target", "5-Time Horizon","6-Scope","7-Verification","8-Consistency" ), IFERROR( CHOOSE( MATCH("PARTIAL",CJ9:CQ9,0), "1-Specificity","2-Metric","3-Baseline","4-Target", "5-Time Horizon","6-Scope","7-Verification","8-Consistency" ), "No failures" ) ) | DA9: =IF(OR(CU9>=50,CW9="Material",CW9="Severe",AS9="Material",AS9="Severe",BF9="Material",BF9="Severe — Exclusion Trigger",AND(ISNUMBER(BS9),BS9<30)),"Yes","No") | DB9: =IF(OR(CR9>=6,AW9="Confirmed Violation",AX9="Confirmed Breach"),"Yes — Automatic",IF(CW9="Severe","Yes — Requires Captain Confirmation","No")) | DL9: =IF(OR(IFERROR(VALUE(LEFT(DF9,1)),99)<=2,IFERROR(VALUE(LEFT(DG9,1)),99)<=2),"Flagged","Clear") | DM9: =IF(OR(DA9="Yes",DB9<>"No",DH9="Unverified",DL9="Flagged"),"Yes","No") | DN9: {=MIN(100, IF(ISNUMBER(V9), _xlfn.IFS(V9>=3,25, V9=2,15, V9=1,5, TRUE,0), 0) + IFERROR(_xlfn.IFS(VALUE(LEFT(DF9,1))=5,25, VALUE(LEFT(DF9,1))=4,20, VALUE(LEFT(DF9,1))=3,15, VALUE(LEFT(DF9,1))=2,8, TRUE,0), 15) + IFERROR(_xlfn.IFS(VALUE(LEFT(DG9,1))=5,25, VALUE(LEFT(DG9,1))=4,20, VALUE(LEFT(DG9,1))=3,15, VALUE(LEFT(DG9,1))=2,8, TRUE,0), 15) + _xlfn.IFS(DH9="Fully Verified",25, DH9="Partially Verified",12, TRUE,0) )} | DO9: {=_xlfn.IFS( ISBLANK(AR9), "Insufficient Evidence", AND(AR9>=65, AJ9="Approved"), "Strong", AR9>=65, "Adequate", AR9>=40, "Adequate", AR9>=20, "Weak", TRUE, "Insufficient Evidence" )} | DP9: {=_xlfn.IFS( ISBLANK(BS9), "Insufficient Evidence", BS9>=65, "Strong", BS9>=40, "Adequate", BS9>=20, "Weak", TRUE, "Insufficient Evidence" )} | DQ9: {=_xlfn.IFS( ISBLANK(BE9), "Insufficient Evidence", OR(AW9="Confirmed Violation", AX9="Confirmed Breach"), "Severe — Hard Trigger", BE9>=65, "Strong", BE9>=40, "Adequate", BE9>=20, "Weak", TRUE, "Insufficient Evidence" )} | DR9: {=_xlfn.IFS( ISBLANK(CU9), "Insufficient Evidence", CU9<=20, "Low Risk", CU9<=50, "Moderate Risk", CU9<=75, "High Risk", TRUE, "Very High Risk" )} | DS9: {=_xlfn.IFS( ISBLANK(CE9), "Insufficient Evidence", AND(ISNUMBER(BW9),ISNUMBER(BV9),BW9>BV9), "Overclaiming Risk", CE9>=65, "Strong", CE9>=40, "Adequate", TRUE, "Weak" )} | DT9: =IF(DB9="Yes — Automatic",0,ROUND((IF(ISNUMBER(AR9),AR9,0)*0.3+IF(ISNUMBER(BS9),BS9,0)*0.2+IF(ISNUMBER(BE9),BE9,0)*0.2+IF(ISNUMBER(CE9),CE9,0)*0.15+(100-IF(ISNUMBER(CU9),CU9,50))*0.15)*IF(DN9>=75,1,IF(DN9>=50,0.9,IF(DN9>=25,0.75,0.6))),1)) | DU9: {=_xlfn.IFS( DV9="Upgraded to Clear", "Clear", DV9="Downgraded to Watchlist", "Watchlist", DV9="Downgraded to Exclusion", "Exclusion Risk", DB9="Yes — Automatic", "Exclusion Risk", OR(AW9="Confirmed Violation", AX9="Confirmed Breach"), "Exclusion Risk", OR(V9=0, ISBLANK(V9), DN9<20), "Insufficient Evidence", AND(DT9>=65, DA9="No", DB9="No"), "Clear", OR(DT9>=40, DA9="Yes"), "Watchlist", TRUE, "Exclusion Risk" )} | DW9: {=_xlfn.IFS( DU9="Exclusion Risk", "Exclude — Hard Trigger", DU9="Insufficient Evidence", "Watchlist — Further Evidence Needed", DU9="Watchlist", "Watchlist — Further Evidence Needed", AND(DU9="Clear", DT9>=80), "Include — No Conditions", DU9="Clear", "Include — Monitor", TRUE, "Watchlist — Further Evidence Needed" )} | EB9: =IF(OR(V9=0, ISBLANK(V9)), "MISSING — No sources reviewed", "") | EC9: =IF(AND(NOT(ISBLANK(DC9)), ISBLANK(DE9)), "PAGE REF MISSING", "")
A10: SSAB AB | B10: SKWA | C10: =IF(ISBLANK('Universe Tracker'!D6),"",'Universe Tracker'!D6) | F10: =IF(ISBLANK('Universe Tracker'!F6),"",'Universe Tracker'!F6) | G10: =IF(ISBLANK('Universe Tracker'!G6),"",'Universe Tracker'!G6) | J10: =IF(ISBLANK(B10),"",B10&"_"&C10) | Y10: =IF(AND(V10>=2,K10="Yes",L10="Yes"),"Sufficient",IF(AND(V10>=1,OR(K10="Yes",L10="Yes")),"Thin","Insufficient")) | AR10: {=MIN(100, MAX(0, IFERROR(_xlfn.XLOOKUP(AJ10,'Lookup Tables'!$A$2:$A$7,'Lookup Tables'!$B$2:$B$7,0),0) + IF(Z10="Yes", IF(IFERROR(_xlfn.XLOOKUP(AJ10,'Lookup Tables'!$A$2:$A$7,'Lookup Tables'!$B$2:$B$7,0),0)<20, 5, 0), 0) + _xlfn.IFS(AB10="Yes", IF(ISNUMBER(AC10)*AND(AC10<=2030),15,10), AB10="Long-term Only", 5, AB10="No", 0, TRUE, 0) + _xlfn.IFS(AF10="Full",10, AF10="Partial",5, AF10="Scope 2 Only",3, TRUE,0) + _xlfn.IFS(AG10="Yes", IF(ISNUMBER(AH10)*AND(AH10>=5),10,6), AG10="Partial",4, TRUE,0) + _xlfn.IFS(AI10="Yes",5, AI10="Partial (material categories only)",3, TRUE,0) + _xlfn.IFS(AL10="Yes — Detailed",10, AL10="Yes — High Level",5, TRUE,0) + _xlfn.IFS(AM10="Yes — Quantified",15, AM10="Yes — Directional Only",7, TRUE,0) + _xlfn.IFS(AP10="Formal",5, AP10="Referenced",2, TRUE,0) + _xlfn.IFS(AQ10="No Issues Found",5, AQ10="Concern Identified",-5, AQ10="Severe Contradiction",-15, TRUE,0) + _xlfn.IFS(BC10="Reasonable Assurance",5, BC10="Limited Assurance",3, TRUE,0) - IF(AND(Z10="Yes", AI10="No"), 10, 0) - IF(AND(Z10="Yes", AM10="No"), 10, 0) ))} | BE10: {=MIN(100, MAX(0, IFERROR(_xlfn.XLOOKUP(AT10,'Lookup Tables'!$D$2:$D$6,'Lookup Tables'!$E$2:$E$6,0),0) + IFERROR(_xlfn.XLOOKUP(AV10,'Lookup Tables'!$G$2:$G$5,'Lookup Tables'!$H$2:$H$5,0),0) + IFERROR(_xlfn.XLOOKUP(AW10,'Lookup Tables'!$J$2:$J$5,'Lookup Tables'!$K$2:$K$5,0),0) + _xlfn.IFS(AX10="No Issues",10, AX10="Complaint Filed",3, AX10="Confirmed Breach",-15, TRUE,0) + IFERROR(_xlfn.XLOOKUP(AY10,'Lookup Tables'!$M$2:$M$6,'Lookup Tables'!$N$2:$N$6,0),0) + IFERROR(_xlfn.XLOOKUP(AZ10,'Lookup Tables'!$P$2:$P$6,'Lookup Tables'!$Q$2:$Q$6,0),0) + _xlfn.IFS(BA10="Formal Board Committee",5, BA10="Board Oversight Mentioned",2, TRUE,0) + _xlfn.IFS(BB10="Yes — Quantified Targets",5, BB10="Yes — Discretionary Only",2, TRUE,0) + _xlfn.IFS(BC10="Reasonable Assurance",5, BC10="Limited Assurance",3, BC10="Management Review Only",1, TRUE,0) ))} | BS10: {=MIN(100, MAX(0, IFERROR(_xlfn.XLOOKUP(BG10,'Lookup Tables'!$A$11:$A$16,'Lookup Tables'!$B$11:$B$16,0),0) + IFERROR(_xlfn.XLOOKUP(BR10,'Lookup Tables'!$M$11:$M$14,'Lookup Tables'!$N$11:$N$14,0),0) + IFERROR(_xlfn.XLOOKUP(BQ10,'Lookup Tables'!$J$11:$J$15,'Lookup Tables'!$K$11:$K$15,0),0) + IFERROR(_xlfn.XLOOKUP(BH10,'Lookup Tables'!$D$11:$D$15,'Lookup Tables'!$E$11:$E$15,0),0) + IFERROR(_xlfn.XLOOKUP(BJ10,'Lookup Tables'!$G$11:$G$16,'Lookup Tables'!$H$11:$H$16,0),0) + IFERROR(_xlfn.XLOOKUP(BN10,'Lookup Tables'!$P$11:$P$15,'Lookup Tables'!$Q$11:$Q$15,0),0) + _xlfn.IFS(BM10="No Evidence",10, BM10="Unknown",3, BM10="Likely",0, BM10="Confirmed",-10, TRUE,3) + IFERROR(_xlfn.XLOOKUP(BP10,'Lookup Tables'!$J$21:$J$24,'Lookup Tables'!$K$21:$K$24,0),0) ))} | CE10: {=MIN(100, MAX(0, IF(ISNUMBER(BV10)*AND(BV10>0), 10, 0) + _xlfn.IFS(BY10="Independently Verified",25, BY10="Yes",15, TRUE,0) + IFERROR(_xlfn.XLOOKUP(BZ10,'Lookup Tables'!$A$21:$A$24,'Lookup Tables'!$B$21:$B$24,0),0) + IFERROR(_xlfn.XLOOKUP(CA10,'Lookup Tables'!$D$21:$D$24,'Lookup Tables'!$E$21:$E$24,0),0) + _xlfn.IFS(ISNUMBER(CB10)*AND(CB10>=11),15, ISNUMBER(CB10)*AND(CB10>=6),10, ISNUMBER(CB10)*AND(CB10>=1),5, TRUE,0) + IFERROR(_xlfn.XLOOKUP(CC10,'Lookup Tables'!$G$21:$G$25,'Lookup Tables'!$H$21:$H$25,0),0) - IF(ISNUMBER(BW10)*AND(ISNUMBER(BV10))*AND(BW10>BV10), 20, 0) - IF(AND(BY10="Yes", ISNUMBER(BW10), BW10>60), 10, 0) ))} | CR10: =COUNTIF(CJ10:CQ10,"FAIL") | CS10: =COUNTIF(CJ10:CQ10,"PARTIAL") | CT10: =COUNTIF(CJ10:CQ10,"MISSING") | CU10: =MIN(100, CR10*15 + CS10*6 + CT10*3 + IFERROR(_xlfn.XLOOKUP(CW10,'Lookup Tables'!$M$21:$M$25,'Lookup Tables'!$N$21:$N$25,0),0) ) | CV10: =IFERROR( CHOOSE( MATCH("FAIL",CJ10:CQ10,0), "1-Specificity","2-Metric","3-Baseline","4-Target", "5-Time Horizon","6-Scope","7-Verification","8-Consistency" ), IFERROR( CHOOSE( MATCH("PARTIAL",CJ10:CQ10,0), "1-Specificity","2-Metric","3-Baseline","4-Target", "5-Time Horizon","6-Scope","7-Verification","8-Consistency" ), "No failures" ) ) | DA10: =IF(OR(CU10>=50,CW10="Material",CW10="Severe",AS10="Material",AS10="Severe",BF10="Material",BF10="Severe — Exclusion Trigger",AND(ISNUMBER(BS10),BS10<30)),"Yes","No") | DB10: =IF(OR(CR10>=6,AW10="Confirmed Violation",AX10="Confirmed Breach"),"Yes — Automatic",IF(CW10="Severe","Yes — Requires Captain Confirmation","No")) | DL10: =IF(OR(IFERROR(VALUE(LEFT(DF10,1)),99)<=2,IFERROR(VALUE(LEFT(DG10,1)),99)<=2),"Flagged","Clear") | DM10: =IF(OR(DA10="Yes",DB10<>"No",DH10="Unverified",DL10="Flagged"),"Yes","No") | DN10: {=MIN(100, IF(ISNUMBER(V10), _xlfn.IFS(V10>=3,25, V10=2,15, V10=1,5, TRUE,0), 0) + IFERROR(_xlfn.IFS(VALUE(LEFT(DF10,1))=5,25, VALUE(LEFT(DF10,1))=4,20, VALUE(LEFT(DF10,1))=3,15, VALUE(LEFT(DF10,1))=2,8, TRUE,0), 15) + IFERROR(_xlfn.IFS(VALUE(LEFT(DG10,1))=5,25, VALUE(LEFT(DG10,1))=4,20, VALUE(LEFT(DG10,1))=3,15, VALUE(LEFT(DG10,1))=2,8, TRUE,0), 15) + _xlfn.IFS(DH10="Fully Verified",25, DH10="Partially Verified",12, TRUE,0) )} | DO10: {=_xlfn.IFS( ISBLANK(AR10), "Insufficient Evidence", AND(AR10>=65, AJ10="Approved"), "Strong", AR10>=65, "Adequate", AR10>=40, "Adequate", AR10>=20, "Weak", TRUE, "Insufficient Evidence" )} | DP10: {=_xlfn.IFS( ISBLANK(BS10), "Insufficient Evidence", BS10>=65, "Strong", BS10>=40, "Adequate", BS10>=20, "Weak", TRUE, "Insufficient Evidence" )} | DQ10: {=_xlfn.IFS( ISBLANK(BE10), "Insufficient Evidence", OR(AW10="Confirmed Violation", AX10="Confirmed Breach"), "Severe — Hard Trigger", BE10>=65, "Strong", BE10>=40, "Adequate", BE10>=20, "Weak", TRUE, "Insufficient Evidence" )} | DR10: {=_xlfn.IFS( ISBLANK(CU10), "Insufficient Evidence", CU10<=20, "Low Risk", CU10<=50, "Moderate Risk", CU10<=75, "High Risk", TRUE, "Very High Risk" )} | DS10: {=_xlfn.IFS( ISBLANK(CE10), "Insufficient Evidence", AND(ISNUMBER(BW10),ISNUMBER(BV10),BW10>BV10), "Overclaiming Risk", CE10>=65, "Strong", CE10>=40, "Adequate", TRUE, "Weak" )} | DT10: =IF(DB10="Yes — Automatic",0,ROUND((IF(ISNUMBER(AR10),AR10,0)*0.3+IF(ISNUMBER(BS10),BS10,0)*0.2+IF(ISNUMBER(BE10),BE10,0)*0.2+IF(ISNUMBER(CE10),CE10,0)*0.15+(100-IF(ISNUMBER(CU10),CU10,50))*0.15)*IF(DN10>=75,1,IF(DN10>=50,0.9,IF(DN10>=25,0.75,0.6))),1)) | DU10: {=_xlfn.IFS( DV10="Upgraded to Clear", "Clear", DV10="Downgraded to Watchlist", "Watchlist", DV10="Downgraded to Exclusion", "Exclusion Risk", DB10="Yes — Automatic", "Exclusion Risk", OR(AW10="Confirmed Violation", AX10="Confirmed Breach"), "Exclusion Risk", OR(V10=0, ISBLANK(V10), DN10<20), "Insufficient Evidence", AND(DT10>=65, DA10="No", DB10="No"), "Clear", OR(DT10>=40, DA10="Yes"), "Watchlist", TRUE, "Exclusion Risk" )} | DW10: {=_xlfn.IFS( DU10="Exclusion Risk", "Exclude — Hard Trigger", DU10="Insufficient Evidence", "Watchlist — Further Evidence Needed", DU10="Watchlist", "Watchlist — Further Evidence Needed", AND(DU10="Clear", DT10>=80), "Include — No Conditions", DU10="Clear", "Include — Monitor", TRUE, "Watchlist — Further Evidence Needed" )} | EB10: =IF(OR(V10=0, ISBLANK(V10)), "MISSING — No sources reviewed", "") | EC10: =IF(AND(NOT(ISBLANK(DC10)), ISBLANK(DE10)), "PAGE REF MISSING", "")
A11: Tenaris SA | B11: TW11 | C11: =IF(ISBLANK('Universe Tracker'!D7),"",'Universe Tracker'!D7) | F11: =IF(ISBLANK('Universe Tracker'!F7),"",'Universe Tracker'!F7) | G11: =IF(ISBLANK('Universe Tracker'!G7),"",'Universe Tracker'!G7) | J11: =IF(ISBLANK(B11),"",B11&"_"&C11) | Y11: =IF(AND(V11>=2,K11="Yes",L11="Yes"),"Sufficient",IF(AND(V11>=1,OR(K11="Yes",L11="Yes")),"Thin","Insufficient")) | AR11: {=MIN(100, MAX(0, IFERROR(_xlfn.XLOOKUP(AJ11,'Lookup Tables'!$A$2:$A$7,'Lookup Tables'!$B$2:$B$7,0),0) + IF(Z11="Yes", IF(IFERROR(_xlfn.XLOOKUP(AJ11,'Lookup Tables'!$A$2:$A$7,'Lookup Tables'!$B$2:$B$7,0),0)<20, 5, 0), 0) + _xlfn.IFS(AB11="Yes", IF(ISNUMBER(AC11)*AND(AC11<=2030),15,10), AB11="Long-term Only", 5, AB11="No", 0, TRUE, 0) + _xlfn.IFS(AF11="Full",10, AF11="Partial",5, AF11="Scope 2 Only",3, TRUE,0) + _xlfn.IFS(AG11="Yes", IF(ISNUMBER(AH11)*AND(AH11>=5),10,6), AG11="Partial",4, TRUE,0) + _xlfn.IFS(AI11="Yes",5, AI11="Partial (material categories only)",3, TRUE,0) + _xlfn.IFS(AL11="Yes — Detailed",10, AL11="Yes — High Level",5, TRUE,0) + _xlfn.IFS(AM11="Yes — Quantified",15, AM11="Yes — Directional Only",7, TRUE,0) + _xlfn.IFS(AP11="Formal",5, AP11="Referenced",2, TRUE,0) + _xlfn.IFS(AQ11="No Issues Found",5, AQ11="Concern Identified",-5, AQ11="Severe Contradiction",-15, TRUE,0) + _xlfn.IFS(BC11="Reasonable Assurance",5, BC11="Limited Assurance",3, TRUE,0) - IF(AND(Z11="Yes", AI11="No"), 10, 0) - IF(AND(Z11="Yes", AM11="No"), 10, 0) ))} | BE11: {=MIN(100, MAX(0, IFERROR(_xlfn.XLOOKUP(AT11,'Lookup Tables'!$D$2:$D$6,'Lookup Tables'!$E$2:$E$6,0),0) + IFERROR(_xlfn.XLOOKUP(AV11,'Lookup Tables'!$G$2:$G$5,'Lookup Tables'!$H$2:$H$5,0),0) + IFERROR(_xlfn.XLOOKUP(AW11,'Lookup Tables'!$J$2:$J$5,'Lookup Tables'!$K$2:$K$5,0),0) + _xlfn.IFS(AX11="No Issues",10, AX11="Complaint Filed",3, AX11="Confirmed Breach",-15, TRUE,0) + IFERROR(_xlfn.XLOOKUP(AY11,'Lookup Tables'!$M$2:$M$6,'Lookup Tables'!$N$2:$N$6,0),0) + IFERROR(_xlfn.XLOOKUP(AZ11,'Lookup Tables'!$P$2:$P$6,'Lookup Tables'!$Q$2:$Q$6,0),0) + _xlfn.IFS(BA11="Formal Board Committee",5, BA11="Board Oversight Mentioned",2, TRUE,0) + _xlfn.IFS(BB11="Yes — Quantified Targets",5, BB11="Yes — Discretionary Only",2, TRUE,0) + _xlfn.IFS(BC11="Reasonable Assurance",5, BC11="Limited Assurance",3, BC11="Management Review Only",1, TRUE,0) ))} | BS11: {=MIN(100, MAX(0, IFERROR(_xlfn.XLOOKUP(BG11,'Lookup Tables'!$A$11:$A$16,'Lookup Tables'!$B$11:$B$16,0),0) + IFERROR(_xlfn.XLOOKUP(BR11,'Lookup Tables'!$M$11:$M$14,'Lookup Tables'!$N$11:$N$14,0),0) + IFERROR(_xlfn.XLOOKUP(BQ11,'Lookup Tables'!$J$11:$J$15,'Lookup Tables'!$K$11:$K$15,0),0) + IFERROR(_xlfn.XLOOKUP(BH11,'Lookup Tables'!$D$11:$D$15,'Lookup Tables'!$E$11:$E$15,0),0) + IFERROR(_xlfn.XLOOKUP(BJ11,'Lookup Tables'!$G$11:$G$16,'Lookup Tables'!$H$11:$H$16,0),0) + IFERROR(_xlfn.XLOOKUP(BN11,'Lookup Tables'!$P$11:$P$15,'Lookup Tables'!$Q$11:$Q$15,0),0) + _xlfn.IFS(BM11="No Evidence",10, BM11="Unknown",3, BM11="Likely",0, BM11="Confirmed",-10, TRUE,3) + IFERROR(_xlfn.XLOOKUP(BP11,'Lookup Tables'!$J$21:$J$24,'Lookup Tables'!$K$21:$K$24,0),0) ))} | CE11: {=MIN(100, MAX(0, IF(ISNUMBER(BV11)*AND(BV11>0), 10, 0) + _xlfn.IFS(BY11="Independently Verified",25, BY11="Yes",15, TRUE,0) + IFERROR(_xlfn.XLOOKUP(BZ11,'Lookup Tables'!$A$21:$A$24,'Lookup Tables'!$B$21:$B$24,0),0) + IFERROR(_xlfn.XLOOKUP(CA11,'Lookup Tables'!$D$21:$D$24,'Lookup Tables'!$E$21:$E$24,0),0) + _xlfn.IFS(ISNUMBER(CB11)*AND(CB11>=11),15, ISNUMBER(CB11)*AND(CB11>=6),10, ISNUMBER(CB11)*AND(CB11>=1),5, TRUE,0) + IFERROR(_xlfn.XLOOKUP(CC11,'Lookup Tables'!$G$21:$G$25,'Lookup Tables'!$H$21:$H$25,0),0) - IF(ISNUMBER(BW11)*AND(ISNUMBER(BV11))*AND(BW11>BV11), 20, 0) - IF(AND(BY11="Yes", ISNUMBER(BW11), BW11>60), 10, 0) ))} | CR11: =COUNTIF(CJ11:CQ11,"FAIL") | CS11: =COUNTIF(CJ11:CQ11,"PARTIAL") | CT11: =COUNTIF(CJ11:CQ11,"MISSING") | CU11: =MIN(100, CR11*15 + CS11*6 + CT11*3 + IFERROR(_xlfn.XLOOKUP(CW11,'Lookup Tables'!$M$21:$M$25,'Lookup Tables'!$N$21:$N$25,0),0) ) | CV11: =IFERROR( CHOOSE( MATCH("FAIL",CJ11:CQ11,0), "1-Specificity","2-Metric","3-Baseline","4-Target", "5-Time Horizon","6-Scope","7-Verification","8-Consistency" ), IFERROR( CHOOSE( MATCH("PARTIAL",CJ11:CQ11,0), "1-Specificity","2-Metric","3-Baseline","4-Target", "5-Time Horizon","6-Scope","7-Verification","8-Consistency" ), "No failures" ) ) | DA11: =IF(OR(CU11>=50,CW11="Material",CW11="Severe",AS11="Material",AS11="Severe",BF11="Material",BF11="Severe — Exclusion Trigger",AND(ISNUMBER(BS11),BS11<30)),"Yes","No") | DB11: =IF(OR(CR11>=6,AW11="Confirmed Violation",AX11="Confirmed Breach"),"Yes — Automatic",IF(CW11="Severe","Yes — Requires Captain Confirmation","No")) | DL11: =IF(OR(IFERROR(VALUE(LEFT(DF11,1)),99)<=2,IFERROR(VALUE(LEFT(DG11,1)),99)<=2),"Flagged","Clear") | DM11: =IF(OR(DA11="Yes",DB11<>"No",DH11="Unverified",DL11="Flagged"),"Yes","No") | DN11: {=MIN(100, IF(ISNUMBER(V11), _xlfn.IFS(V11>=3,25, V11=2,15, V11=1,5, TRUE,0), 0) + IFERROR(_xlfn.IFS(VALUE(LEFT(DF11,1))=5,25, VALUE(LEFT(DF11,1))=4,20, VALUE(LEFT(DF11,1))=3,15, VALUE(LEFT(DF11,1))=2,8, TRUE,0), 15) + IFERROR(_xlfn.IFS(VALUE(LEFT(DG11,1))=5,25, VALUE(LEFT(DG11,1))=4,20, VALUE(LEFT(DG11,1))=3,15, VALUE(LEFT(DG11,1))=2,8, TRUE,0), 15) + _xlfn.IFS(DH11="Fully Verified",25, DH11="Partially Verified",12, TRUE,0) )} | DO11: {=_xlfn.IFS( ISBLANK(AR11), "Insufficient Evidence", AND(AR11>=65, AJ11="Approved"), "Strong", AR11>=65, "Adequate", AR11>=40, "Adequate", AR11>=20, "Weak", TRUE, "Insufficient Evidence" )} | DP11: {=_xlfn.IFS( ISBLANK(BS11), "Insufficient Evidence", BS11>=65, "Strong", BS11>=40, "Adequate", BS11>=20, "Weak", TRUE, "Insufficient Evidence" )} | DQ11: {=_xlfn.IFS( ISBLANK(BE11), "Insufficient Evidence", OR(AW11="Confirmed Violation", AX11="Confirmed Breach"), "Severe — Hard Trigger", BE11>=65, "Strong", BE11>=40, "Adequate", BE11>=20, "Weak", TRUE, "Insufficient Evidence" )} | DR11: {=_xlfn.IFS( ISBLANK(CU11), "Insufficient Evidence", CU11<=20, "Low Risk", CU11<=50, "Moderate Risk", CU11<=75, "High Risk", TRUE, "Very High Risk" )} | DS11: {=_xlfn.IFS( ISBLANK(CE11), "Insufficient Evidence", AND(ISNUMBER(BW11),ISNUMBER(BV11),BW11>BV11), "Overclaiming Risk", CE11>=65, "Strong", CE11>=40, "Adequate", TRUE, "Weak" )} | DT11: =IF(DB11="Yes — Automatic",0,ROUND((IF(ISNUMBER(AR11),AR11,0)*0.3+IF(ISNUMBER(BS11),BS11,0)*0.2+IF(ISNUMBER(BE11),BE11,0)*0.2+IF(ISNUMBER(CE11),CE11,0)*0.15+(100-IF(ISNUMBER(CU11),CU11,50))*0.15)*IF(DN11>=75,1,IF(DN11>=50,0.9,IF(DN11>=25,0.75,0.6))),1)) | DU11: {=_xlfn.IFS( DV11="Upgraded to Clear", "Clear", DV11="Downgraded to Watchlist", "Watchlist", DV11="Downgraded to Exclusion", "Exclusion Risk", DB11="Yes — Automatic", "Exclusion Risk", OR(AW11="Confirmed Violation", AX11="Confirmed Breach"), "Exclusion Risk", OR(V11=0, ISBLANK(V11), DN11<20), "Insufficient Evidence", AND(DT11>=65, DA11="No", DB11="No"), "Clear", OR(DT11>=40, DA11="Yes"), "Watchlist", TRUE, "Exclusion Risk" )} | DW11: {=_xlfn.IFS( DU11="Exclusion Risk", "Exclude — Hard Trigger", DU11="Insufficient Evidence", "Watchlist — Further Evidence Needed", DU11="Watchlist", "Watchlist — Further Evidence Needed", AND(DU11="Clear", DT11>=80), "Include — No Conditions", DU11="Clear", "Include — Monitor", TRUE, "Watchlist — Further Evidence Needed" )} | EB11: =IF(OR(V11=0, ISBLANK(V11)), "MISSING — No sources reviewed", "") | EC11: =IF(AND(NOT(ISBLANK(DC11)), ISBLANK(DE11)), "PAGE REF MISSING", "")
A12: Ackermans & van Haaren NV | B12: B3K | C12: =IF(ISBLANK('Universe Tracker'!D8),"",'Universe Tracker'!D8) | F12: =IF(ISBLANK('Universe Tracker'!F8),"",'Universe Tracker'!F8) | G12: =IF(ISBLANK('Universe Tracker'!G8),"",'Universe Tracker'!G8) | J12: =IF(ISBLANK(B12),"",B12&"_"&C12) | Y12: =IF(AND(V12>=2,K12="Yes",L12="Yes"),"Sufficient",IF(AND(V12>=1,OR(K12="Yes",L12="Yes")),"Thin","Insufficient")) | AR12: {=MIN(100, MAX(0, IFERROR(_xlfn.XLOOKUP(AJ12,'Lookup Tables'!$A$2:$A$7,'Lookup Tables'!$B$2:$B$7,0),0) + IF(Z12="Yes", IF(IFERROR(_xlfn.XLOOKUP(AJ12,'Lookup Tables'!$A$2:$A$7,'Lookup Tables'!$B$2:$B$7,0),0)<20, 5, 0), 0) + _xlfn.IFS(AB12="Yes", IF(ISNUMBER(AC12)*AND(AC12<=2030),15,10), AB12="Long-term Only", 5, AB12="No", 0, TRUE, 0) + _xlfn.IFS(AF12="Full",10, AF12="Partial",5, AF12="Scope 2 Only",3, TRUE,0) + _xlfn.IFS(AG12="Yes", IF(ISNUMBER(AH12)*AND(AH12>=5),10,6), AG12="Partial",4, TRUE,0) + _xlfn.IFS(AI12="Yes",5, AI12="Partial (material categories only)",3, TRUE,0) + _xlfn.IFS(AL12="Yes — Detailed",10, AL12="Yes — High Level",5, TRUE,0) + _xlfn.IFS(AM12="Yes — Quantified",15, AM12="Yes — Directional Only",7, TRUE,0) + _xlfn.IFS(AP12="Formal",5, AP12="Referenced",2, TRUE,0) + _xlfn.IFS(AQ12="No Issues Found",5, AQ12="Concern Identified",-5, AQ12="Severe Contradiction",-15, TRUE,0) + _xlfn.IFS(BC12="Reasonable Assurance",5, BC12="Limited Assurance",3, TRUE,0) - IF(AND(Z12="Yes", AI12="No"), 10, 0) - IF(AND(Z12="Yes", AM12="No"), 10, 0) ))} | BE12: {=MIN(100, MAX(0, IFERROR(_xlfn.XLOOKUP(AT12,'Lookup Tables'!$D$2:$D$6,'Lookup Tables'!$E$2:$E$6,0),0) + IFERROR(_xlfn.XLOOKUP(AV12,'Lookup Tables'!$G$2:$G$5,'Lookup Tables'!$H$2:$H$5,0),0) + IFERROR(_xlfn.XLOOKUP(AW12,'Lookup Tables'!$J$2:$J$5,'Lookup Tables'!$K$2:$K$5,0),0) + _xlfn.IFS(AX12="No Issues",10, AX12="Complaint Filed",3, AX12="Confirmed Breach",-15, TRUE,0) + IFERROR(_xlfn.XLOOKUP(AY12,'Lookup Tables'!$M$2:$M$6,'Lookup Tables'!$N$2:$N$6,0),0) + IFERROR(_xlfn.XLOOKUP(AZ12,'Lookup Tables'!$P$2:$P$6,'Lookup Tables'!$Q$2:$Q$6,0),0) + _xlfn.IFS(BA12="Formal Board Committee",5, BA12="Board Oversight Mentioned",2, TRUE,0) + _xlfn.IFS(BB12="Yes — Quantified Targets",5, BB12="Yes — Discretionary Only",2, TRUE,0) + _xlfn.IFS(BC12="Reasonable Assurance",5, BC12="Limited Assurance",3, BC12="Management Review Only",1, TRUE,0) ))} | BS12: {=MIN(100, MAX(0, IFERROR(_xlfn.XLOOKUP(BG12,'Lookup Tables'!$A$11:$A$16,'Lookup Tables'!$B$11:$B$16,0),0) + IFERROR(_xlfn.XLOOKUP(BR12,'Lookup Tables'!$M$11:$M$14,'Lookup Tables'!$N$11:$N$14,0),0) + IFERROR(_xlfn.XLOOKUP(BQ12,'Lookup Tables'!$J$11:$J$15,'Lookup Tables'!$K$11:$K$15,0),0) + IFERROR(_xlfn.XLOOKUP(BH12,'Lookup Tables'!$D$11:$D$15,'Lookup Tables'!$E$11:$E$15,0),0) + IFERROR(_xlfn.XLOOKUP(BJ12,'Lookup Tables'!$G$11:$G$16,'Lookup Tables'!$H$11:$H$16,0),0) + IFERROR(_xlfn.XLOOKUP(BN12,'Lookup Tables'!$P$11:$P$15,'Lookup Tables'!$Q$11:$Q$15,0),0) + _xlfn.IFS(BM12="No Evidence",10, BM12="Unknown",3, BM12="Likely",0, BM12="Confirmed",-10, TRUE,3) + IFERROR(_xlfn.XLOOKUP(BP12,'Lookup Tables'!$J$21:$J$24,'Lookup Tables'!$K$21:$K$24,0),0) ))} | CE12: {=MIN(100, MAX(0, IF(ISNUMBER(BV12)*AND(BV12>0), 10, 0) + _xlfn.IFS(BY12="Independently Verified",25, BY12="Yes",15, TRUE,0) + IFERROR(_xlfn.XLOOKUP(BZ12,'Lookup Tables'!$A$21:$A$24,'Lookup Tables'!$B$21:$B$24,0),0) + IFERROR(_xlfn.XLOOKUP(CA12,'Lookup Tables'!$D$21:$D$24,'Lookup Tables'!$E$21:$E$24,0),0) + _xlfn.IFS(ISNUMBER(CB12)*AND(CB12>=11),15, ISNUMBER(CB12)*AND(CB12>=6),10, ISNUMBER(CB12)*AND(CB12>=1),5, TRUE,0) + IFERROR(_xlfn.XLOOKUP(CC12,'Lookup Tables'!$G$21:$G$25,'Lookup Tables'!$H$21:$H$25,0),0) - IF(ISNUMBER(BW12)*AND(ISNUMBER(BV12))*AND(BW12>BV12), 20, 0) - IF(AND(BY12="Yes", ISNUMBER(BW12), BW12>60), 10, 0) ))} | CR12: =COUNTIF(CJ12:CQ12,"FAIL") | CS12: =COUNTIF(CJ12:CQ12,"PARTIAL") | CT12: =COUNTIF(CJ12:CQ12,"MISSING") | CU12: =MIN(100, CR12*15 + CS12*6 + CT12*3 + IFERROR(_xlfn.XLOOKUP(CW12,'Lookup Tables'!$M$21:$M$25,'Lookup Tables'!$N$21:$N$25,0),0) ) | CV12: =IFERROR( CHOOSE( MATCH("FAIL",CJ12:CQ12,0), "1-Specificity","2-Metric","3-Baseline","4-Target", "5-Time Horizon","6-Scope","7-Verification","8-Consistency" ), IFERROR( CHOOSE( MATCH("PARTIAL",CJ12:CQ12,0), "1-Specificity","2-Metric","3-Baseline","4-Target", "5-Time Horizon","6-Scope","7-Verification","8-Consistency" ), "No failures" ) ) | DA12: =IF(OR(CU12>=50,CW12="Material",CW12="Severe",AS12="Material",AS12="Severe",BF12="Material",BF12="Severe — Exclusion Trigger",AND(ISNUMBER(BS12),BS12<30)),"Yes","No") | DB12: =IF(OR(CR12>=6,AW12="Confirmed Violation",AX12="Confirmed Breach"),"Yes — Automatic",IF(CW12="Severe","Yes — Requires Captain Confirmation","No")) | DL12: =IF(OR(IFERROR(VALUE(LEFT(DF12,1)),99)<=2,IFERROR(VALUE(LEFT(DG12,1)),99)<=2),"Flagged","Clear") | DM12: =IF(OR(DA12="Yes",DB12<>"No",DH12="Unverified",DL12="Flagged"),"Yes","No") | DN12: {=MIN(100, IF(ISNUMBER(V12), _xlfn.IFS(V12>=3,25, V12=2,15, V12=1,5, TRUE,0), 0) + IFERROR(_xlfn.IFS(VALUE(LEFT(DF12,1))=5,25, VALUE(LEFT(DF12,1))=4,20, VALUE(LEFT(DF12,1))=3,15, VALUE(LEFT(DF12,1))=2,8, TRUE,0), 15) + IFERROR(_xlfn.IFS(VALUE(LEFT(DG12,1))=5,25, VALUE(LEFT(DG12,1))=4,20, VALUE(LEFT(DG12,1))=3,15, VALUE(LEFT(DG12,1))=2,8, TRUE,0), 15) + _xlfn.IFS(DH12="Fully Verified",25, DH12="Partially Verified",12, TRUE,0) )} | DO12: {=_xlfn.IFS( ISBLANK(AR12), "Insufficient Evidence", AND(AR12>=65, AJ12="Approved"), "Strong", AR12>=65, "Adequate", AR12>=40, "Adequate", AR12>=20, "Weak", TRUE, "Insufficient Evidence" )} | DP12: {=_xlfn.IFS( ISBLANK(BS12), "Insufficient Evidence", BS12>=65, "Strong", BS12>=40, "Adequate", BS12>=20, "Weak", TRUE, "Insufficient Evidence" )} | DQ12: {=_xlfn.IFS( ISBLANK(BE12), "Insufficient Evidence", OR(AW12="Confirmed Violation", AX12="Confirmed Breach"), "Severe — Hard Trigger", BE12>=65, "Strong", BE12>=40, "Adequate", BE12>=20, "Weak", TRUE, "Insufficient Evidence" )} | DR12: {=_xlfn.IFS( ISBLANK(CU12), "Insufficient Evidence", CU12<=20, "Low Risk", CU12<=50, "Moderate Risk", CU12<=75, "High Risk", TRUE, "Very High Risk" )} | DS12: {=_xlfn.IFS( ISBLANK(CE12), "Insufficient Evidence", AND(ISNUMBER(BW12),ISNUMBER(BV12),BW12>BV12), "Overclaiming Risk", CE12>=65, "Strong", CE12>=40, "Adequate", TRUE, "Weak" )} | DT12: =IF(DB12="Yes — Automatic",0,ROUND((IF(ISNUMBER(AR12),AR12,0)*0.3+IF(ISNUMBER(BS12),BS12,0)*0.2+IF(ISNUMBER(BE12),BE12,0)*0.2+IF(ISNUMBER(CE12),CE12,0)*0.15+(100-IF(ISNUMBER(CU12),CU12,50))*0.15)*IF(DN12>=75,1,IF(DN12>=50,0.9,IF(DN12>=25,0.75,0.6))),1)) | DU12: {=_xlfn.IFS( DV12="Upgraded to Clear", "Clear", DV12="Downgraded to Watchlist", "Watchlist", DV12="Downgraded to Exclusion", "Exclusion Risk", DB12="Yes — Automatic", "Exclusion Risk", OR(AW12="Confirmed Violation", AX12="Confirmed Breach"), "Exclusion Risk", OR(V12=0, ISBLANK(V12), DN12<20), "Insufficient Evidence", AND(DT12>=65, DA12="No", DB12="No"), "Clear", OR(DT12>=40, DA12="Yes"), "Watchlist", TRUE, "Exclusion Risk" )} | DW12: {=_xlfn.IFS( DU12="Exclusion Risk", "Exclude — Hard Trigger", DU12="Insufficient Evidence", "Watchlist — Further Evidence Needed", DU12="Watchlist", "Watchlist — Further Evidence Needed", AND(DU12="Clear", DT12>=80), "Include — No Conditions", DU12="Clear", "Include — Monitor", TRUE, "Watchlist — Further Evidence Needed" )} | EB12: =IF(OR(V12=0, ISBLANK(V12)), "MISSING — No sources reviewed", "") | EC12: =IF(AND(NOT(ISBLANK(DC12)), ISBLANK(DE12)), "PAGE REF MISSING", "")
A13: Novartis AG | B13: NOT | C13: =IF(ISBLANK('Universe Tracker'!D9),"",'Universe Tracker'!D9) | F13: =IF(ISBLANK('Universe Tracker'!F9),"",'Universe Tracker'!F9) | G13: =IF(ISBLANK('Universe Tracker'!G9),"",'Universe Tracker'!G9) | J13: =IF(ISBLANK(B13),"",B13&"_"&C13) | Y13: =IF(AND(V13>=2,K13="Yes",L13="Yes"),"Sufficient",IF(AND(V13>=1,OR(K13="Yes",L13="Yes")),"Thin","Insufficient")) | AR13: {=MIN(100, MAX(0, IFERROR(_xlfn.XLOOKUP(AJ13,'Lookup Tables'!$A$2:$A$7,'Lookup Tables'!$B$2:$B$7,0),0) + IF(Z13="Yes", IF(IFERROR(_xlfn.XLOOKUP(AJ13,'Lookup Tables'!$A$2:$A$7,'Lookup Tables'!$B$2:$B$7,0),0)<20, 5, 0), 0) + _xlfn.IFS(AB13="Yes", IF(ISNUMBER(AC13)*AND(AC13<=2030),15,10), AB13="Long-term Only", 5, AB13="No", 0, TRUE, 0) + _xlfn.IFS(AF13="Full",10, AF13="Partial",5, AF13="Scope 2 Only",3, TRUE,0) + _xlfn.IFS(AG13="Yes", IF(ISNUMBER(AH13)*AND(AH13>=5),10,6), AG13="Partial",4, TRUE,0) + _xlfn.IFS(AI13="Yes",5, AI13="Partial (material categories only)",3, TRUE,0) + _xlfn.IFS(AL13="Yes — Detailed",10, AL13="Yes — High Level",5, TRUE,0) + _xlfn.IFS(AM13="Yes — Quantified",15, AM13="Yes — Directional Only",7, TRUE,0) + _xlfn.IFS(AP13="Formal",5, AP13="Referenced",2, TRUE,0) + _xlfn.IFS(AQ13="No Issues Found",5, AQ13="Concern Identified",-5, AQ13="Severe Contradiction",-15, TRUE,0) + _xlfn.IFS(BC13="Reasonable Assurance",5, BC13="Limited Assurance",3, TRUE,0) - IF(AND(Z13="Yes", AI13="No"), 10, 0) - IF(AND(Z13="Yes", AM13="No"), 10, 0) ))} | BE13: {=MIN(100, MAX(0, IFERROR(_xlfn.XLOOKUP(AT13,'Lookup Tables'!$D$2:$D$6,'Lookup Tables'!$E$2:$E$6,0),0) + IFERROR(_xlfn.XLOOKUP(AV13,'Lookup Tables'!$G$2:$G$5,'Lookup Tables'!$H$2:$H$5,0),0) + IFERROR(_xlfn.XLOOKUP(AW13,'Lookup Tables'!$J$2:$J$5,'Lookup Tables'!$K$2:$K$5,0),0) + _xlfn.IFS(AX13="No Issues",10, AX13="Complaint Filed",3, AX13="Confirmed Breach",-15, TRUE,0) + IFERROR(_xlfn.XLOOKUP(AY13,'Lookup Tables'!$M$2:$M$6,'Lookup Tables'!$N$2:$N$6,0),0) + IFERROR(_xlfn.XLOOKUP(AZ13,'Lookup Tables'!$P$2:$P$6,'Lookup Tables'!$Q$2:$Q$6,0),0) + _xlfn.IFS(BA13="Formal Board Committee",5, BA13="Board Oversight Mentioned",2, TRUE,0) + _xlfn.IFS(BB13="Yes — Quantified Targets",5, BB13="Yes — Discretionary Only",2, TRUE,0) + _xlfn.IFS(BC13="Reasonable Assurance",5, BC13="Limited Assurance",3, BC13="Management Review Only",1, TRUE,0) ))} | BS13: {=MIN(100, MAX(0, IFERROR(_xlfn.XLOOKUP(BG13,'Lookup Tables'!$A$11:$A$16,'Lookup Tables'!$B$11:$B$16,0),0) + IFERROR(_xlfn.XLOOKUP(BR13,'Lookup Tables'!$M$11:$M$14,'Lookup Tables'!$N$11:$N$14,0),0) + IFERROR(_xlfn.XLOOKUP(BQ13,'Lookup Tables'!$J$11:$J$15,'Lookup Tables'!$K$11:$K$15,0),0) + IFERROR(_xlfn.XLOOKUP(BH13,'Lookup Tables'!$D$11:$D$15,'Lookup Tables'!$E$11:$E$15,0),0) + IFERROR(_xlfn.XLOOKUP(BJ13,'Lookup Tables'!$G$11:$G$16,'Lookup Tables'!$H$11:$H$16,0),0) + IFERROR(_xlfn.XLOOKUP(BN13,'Lookup Tables'!$P$11:$P$15,'Lookup Tables'!$Q$11:$Q$15,0),0) + _xlfn.IFS(BM13="No Evidence",10, BM13="Unknown",3, BM13="Likely",0, BM13="Confirmed",-10, TRUE,3) + IFERROR(_xlfn.XLOOKUP(BP13,'Lookup Tables'!$J$21:$J$24,'Lookup Tables'!$K$21:$K$24,0),0) ))} | CE13: {=MIN(100, MAX(0, IF(ISNUMBER(BV13)*AND(BV13>0), 10, 0) + _xlfn.IFS(BY13="Independently Verified",25, BY13="Yes",15, TRUE,0) + IFERROR(_xlfn.XLOOKUP(BZ13,'Lookup Tables'!$A$21:$A$24,'Lookup Tables'!$B$21:$B$24,0),0) + IFERROR(_xlfn.XLOOKUP(CA13,'Lookup Tables'!$D$21:$D$24,'Lookup Tables'!$E$21:$E$24,0),0) + _xlfn.IFS(ISNUMBER(CB13)*AND(CB13>=11),15, ISNUMBER(CB13)*AND(CB13>=6),10, ISNUMBER(CB13)*AND(CB13>=1),5, TRUE,0) + IFERROR(_xlfn.XLOOKUP(CC13,'Lookup Tables'!$G$21:$G$25,'Lookup Tables'!$H$21:$H$25,0),0) - IF(ISNUMBER(BW13)*AND(ISNUMBER(BV13))*AND(BW13>BV13), 20, 0) - IF(AND(BY13="Yes", ISNUMBER(BW13), BW13>60), 10, 0) ))} | CR13: =COUNTIF(CJ13:CQ13,"FAIL") | CS13: =COUNTIF(CJ13:CQ13,"PARTIAL") | CT13: =COUNTIF(CJ13:CQ13,"MISSING") | CU13: =MIN(100, CR13*15 + CS13*6 + CT13*3 + IFERROR(_xlfn.XLOOKUP(CW13,'Lookup Tables'!$M$21:$M$25,'Lookup Tables'!$N$21:$N$25,0),0) ) | CV13: =IFERROR( CHOOSE( MATCH("FAIL",CJ13:CQ13,0), "1-Specificity","2-Metric","3-Baseline","4-Target", "5-Time Horizon","6-Scope","7-Verification","8-Consistency" ), IFERROR( CHOOSE( MATCH("PARTIAL",CJ13:CQ13,0), "1-Specificity","2-Metric","3-Baseline","4-Target", "5-Time Horizon","6-Scope","7-Verification","8-Consistency" ), "No failures" ) ) | DA13: =IF(OR(CU13>=50,CW13="Material",CW13="Severe",AS13="Material",AS13="Severe",BF13="Material",BF13="Severe — Exclusion Trigger",AND(ISNUMBER(BS13),BS13<30)),"Yes","No") | DB13: =IF(OR(CR13>=6,AW13="Confirmed Violation",AX13="Confirmed Breach"),"Yes — Automatic",IF(CW13="Severe","Yes — Requires Captain Confirmation","No")) | DL13: =IF(OR(IFERROR(VALUE(LEFT(DF13,1)),99)<=2,IFERROR(VALUE(LEFT(DG13,1)),99)<=2),"Flagged","Clear") | DM13: =IF(OR(DA13="Yes",DB13<>"No",DH13="Unverified",DL13="Flagged"),"Yes","No") | DN13: {=MIN(100, IF(ISNUMBER(V13), _xlfn.IFS(V13>=3,25, V13=2,15, V13=1,5, TRUE,0), 0) + IFERROR(_xlfn.IFS(VALUE(LEFT(DF13,1))=5,25, VALUE(LEFT(DF13,1))=4,20, VALUE(LEFT(DF13,1))=3,15, VALUE(LEFT(DF13,1))=2,8, TRUE,0), 15) + IFERROR(_xlfn.IFS(VALUE(LEFT(DG13,1))=5,25, VALUE(LEFT(DG13,1))=4,20, VALUE(LEFT(DG13,1))=3,15, VALUE(LEFT(DG13,1))=2,8, TRUE,0), 15) + _xlfn.IFS(DH13="Fully Verified",25, DH13="Partially Verified",12, TRUE,0) )} | DO13: {=_xlfn.IFS( ISBLANK(AR13), "Insufficient Evidence", AND(AR13>=65, AJ13="Approved"), "Strong", AR13>=65, "Adequate", AR13>=40, "Adequate", AR13>=20, "Weak", TRUE, "Insufficient Evidence" )} | DP13: {=_xlfn.IFS( ISBLANK(BS13), "Insufficient Evidence", BS13>=65, "Strong", BS13>=40, "Adequate", BS13>=20, "Weak", TRUE, "Insufficient Evidence" )} | DQ13: {=_xlfn.IFS( ISBLANK(BE13), "Insufficient Evidence", OR(AW13="Confirmed Violation", AX13="Confirmed Breach"), "Severe — Hard Trigger", BE13>=65, "Strong", BE13>=40, "Adequate", BE13>=20, "Weak", TRUE, "Insufficient Evidence" )} | DR13: {=_xlfn.IFS( ISBLANK(CU13), "Insufficient Evidence", CU13<=20, "Low Risk", CU13<=50, "Moderate Risk", CU13<=75, "High Risk", TRUE, "Very High Risk" )} | DS13: {=_xlfn.IFS( ISBLANK(CE13), "Insufficient Evidence", AND(ISNUMBER(BW13),ISNUMBER(BV13),BW13>BV13), "Overclaiming Risk", CE13>=65, "Strong", CE13>=40, "Adequate", TRUE, "Weak" )} | DT13: =IF(DB13="Yes — Automatic",0,ROUND((IF(ISNUMBER(AR13),AR13,0)*0.3+IF(ISNUMBER(BS13),BS13,0)*0.2+IF(ISNUMBER(BE13),BE13,0)*0.2+IF(ISNUMBER(CE13),CE13,0)*0.15+(100-IF(ISNUMBER(CU13),CU13,50))*0.15)*IF(DN13>=75,1,IF(DN13>=50,0.9,IF(DN13>=25,0.75,0.6))),1)) | DU13: {=_xlfn.IFS( DV13="Upgraded to Clear", "Clear", DV13="Downgraded to Watchlist", "Watchlist", DV13="Downgraded to Exclusion", "Exclusion Risk", DB13="Yes — Automatic", "Exclusion Risk", OR(AW13="Confirmed Violation", AX13="Confirmed Breach"), "Exclusion Risk", OR(V13=0, ISBLANK(V13), DN13<20), "Insufficient Evidence", AND(DT13>=65, DA13="No", DB13="No"), "Clear", OR(DT13>=40, DA13="Yes"), "Watchlist", TRUE, "Exclusion Risk" )} | DW13: {=_xlfn.IFS( DU13="Exclusion Risk", "Exclude — Hard Trigger", DU13="Insufficient Evidence", "Watchlist — Further Evidence Needed", DU13="Watchlist", "Watchlist — Further Evidence Needed", AND(DU13="Clear", DT13>=80), "Include — No Conditions", DU13="Clear", "Include — Monitor", TRUE, "Watchlist — Further Evidence Needed" )} | EB13: =IF(OR(V13=0, ISBLANK(V13)), "MISSING — No sources reviewed", "") | EC13: =IF(AND(NOT(ISBLANK(DC13)), ISBLANK(DE13)), "PAGE REF MISSING", "")
A14: Terna - Rete Elettrica Nazionale | B14: UEI | C14: =IF(ISBLANK('Universe Tracker'!D10),"",'Universe Tracker'!D10) | F14: =IF(ISBLANK('Universe Tracker'!F10),"",'Universe Tracker'!F10) | G14: =IF(ISBLANK('Universe Tracker'!G10),"",'Universe Tracker'!G10) | J14: =IF(ISBLANK(B14),"",B14&"_"&C14) | Y14: =IF(AND(V14>=2,K14="Yes",L14="Yes"),"Sufficient",IF(AND(V14>=1,OR(K14="Yes",L14="Yes")),"Thin","Insufficient")) | AR14: {=MIN(100, MAX(0, IFERROR(_xlfn.XLOOKUP(AJ14,'Lookup Tables'!$A$2:$A$7,'Lookup Tables'!$B$2:$B$7,0),0) + IF(Z14="Yes", IF(IFERROR(_xlfn.XLOOKUP(AJ14,'Lookup Tables'!$A$2:$A$7,'Lookup Tables'!$B$2:$B$7,0),0)<20, 5, 0), 0) + _xlfn.IFS(AB14="Yes", IF(ISNUMBER(AC14)*AND(AC14<=2030),15,10), AB14="Long-term Only", 5, AB14="No", 0, TRUE, 0) + _xlfn.IFS(AF14="Full",10, AF14="Partial",5, AF14="Scope 2 Only",3, TRUE,0) + _xlfn.IFS(AG14="Yes", IF(ISNUMBER(AH14)*AND(AH14>=5),10,6), AG14="Partial",4, TRUE,0) + _xlfn.IFS(AI14="Yes",5, AI14="Partial (material categories only)",3, TRUE,0) + _xlfn.IFS(AL14="Yes — Detailed",10, AL14="Yes — High Level",5, TRUE,0) + _xlfn.IFS(AM14="Yes — Quantified",15, AM14="Yes — Directional Only",7, TRUE,0) + _xlfn.IFS(AP14="Formal",5, AP14="Referenced",2, TRUE,0) + _xlfn.IFS(AQ14="No Issues Found",5, AQ14="Concern Identified",-5, AQ14="Severe Contradiction",-15, TRUE,0) + _xlfn.IFS(BC14="Reasonable Assurance",5, BC14="Limited Assurance",3, TRUE,0) - IF(AND(Z14="Yes", AI14="No"), 10, 0) - IF(AND(Z14="Yes", AM14="No"), 10, 0) ))} | BE14: {=MIN(100, MAX(0, IFERROR(_xlfn.XLOOKUP(AT14,'Lookup Tables'!$D$2:$D$6,'Lookup Tables'!$E$2:$E$6,0),0) + IFERROR(_xlfn.XLOOKUP(AV14,'Lookup Tables'!$G$2:$G$5,'Lookup Tables'!$H$2:$H$5,0),0) + IFERROR(_xlfn.XLOOKUP(AW14,'Lookup Tables'!$J$2:$J$5,'Lookup Tables'!$K$2:$K$5,0),0) + _xlfn.IFS(AX14="No Issues",10, AX14="Complaint Filed",3, AX14="Confirmed Breach",-15, TRUE,0) + IFERROR(_xlfn.XLOOKUP(AY14,'Lookup Tables'!$M$2:$M$6,'Lookup Tables'!$N$2:$N$6,0),0) + IFERROR(_xlfn.XLOOKUP(AZ14,'Lookup Tables'!$P$2:$P$6,'Lookup Tables'!$Q$2:$Q$6,0),0) + _xlfn.IFS(BA14="Formal Board Committee",5, BA14="Board Oversight Mentioned",2, TRUE,0) + _xlfn.IFS(BB14="Yes — Quantified Targets",5, BB14="Yes — Discretionary Only",2, TRUE,0) + _xlfn.IFS(BC14="Reasonable Assurance",5, BC14="Limited Assurance",3, BC14="Management Review Only",1, TRUE,0) ))} | BS14: {=MIN(100, MAX(0, IFERROR(_xlfn.XLOOKUP(BG14,'Lookup Tables'!$A$11:$A$16,'Lookup Tables'!$B$11:$B$16,0),0) + IFERROR(_xlfn.XLOOKUP(BR14,'Lookup Tables'!$M$11:$M$14,'Lookup Tables'!$N$11:$N$14,0),0) + IFERROR(_xlfn.XLOOKUP(BQ14,'Lookup Tables'!$J$11:$J$15,'Lookup Tables'!$K$11:$K$15,0),0) + IFERROR(_xlfn.XLOOKUP(BH14,'Lookup Tables'!$D$11:$D$15,'Lookup Tables'!$E$11:$E$15,0),0) + IFERROR(_xlfn.XLOOKUP(BJ14,'Lookup Tables'!$G$11:$G$16,'Lookup Tables'!$H$11:$H$16,0),0) + IFERROR(_xlfn.XLOOKUP(BN14,'Lookup Tables'!$P$11:$P$15,'Lookup Tables'!$Q$11:$Q$15,0),0) + _xlfn.IFS(BM14="No Evidence",10, BM14="Unknown",3, BM14="Likely",0, BM14="Confirmed",-10, TRUE,3) + IFERROR(_xlfn.XLOOKUP(BP14,'Lookup Tables'!$J$21:$J$24,'Lookup Tables'!$K$21:$K$24,0),0) ))} | CE14: {=MIN(100, MAX(0, IF(ISNUMBER(BV14)*AND(BV14>0), 10, 0) + _xlfn.IFS(BY14="Independently Verified",25, BY14="Yes",15, TRUE,0) + IFERROR(_xlfn.XLOOKUP(BZ14,'Lookup Tables'!$A$21:$A$24,'Lookup Tables'!$B$21:$B$24,0),0) + IFERROR(_xlfn.XLOOKUP(CA14,'Lookup Tables'!$D$21:$D$24,'Lookup Tables'!$E$21:$E$24,0),0) + _xlfn.IFS(ISNUMBER(CB14)*AND(CB14>=11),15, ISNUMBER(CB14)*AND(CB14>=6),10, ISNUMBER(CB14)*AND(CB14>=1),5, TRUE,0) + IFERROR(_xlfn.XLOOKUP(CC14,'Lookup Tables'!$G$21:$G$25,'Lookup Tables'!$H$21:$H$25,0),0) - IF(ISNUMBER(BW14)*AND(ISNUMBER(BV14))*AND(BW14>BV14), 20, 0) - IF(AND(BY14="Yes", ISNUMBER(BW14), BW14>60), 10, 0) ))} | CR14: =COUNTIF(CJ14:CQ14,"FAIL") | CS14: =COUNTIF(CJ14:CQ14,"PARTIAL") | CT14: =COUNTIF(CJ14:CQ14,"MISSING") | CU14: =MIN(100, CR14*15 + CS14*6 + CT14*3 + IFERROR(_xlfn.XLOOKUP(CW14,'Lookup Tables'!$M$21:$M$25,'Lookup Tables'!$N$21:$N$25,0),0) ) | CV14: =IFERROR( CHOOSE( MATCH("FAIL",CJ14:CQ14,0), "1-Specificity","2-Metric","3-Baseline","4-Target", "5-Time Horizon","6-Scope","7-Verification","8-Consistency" ), IFERROR( CHOOSE( MATCH("PARTIAL",CJ14:CQ14,0), "1-Specificity","2-Metric","3-Baseline","4-Target", "5-Time Horizon","6-Scope","7-Verification","8-Consistency" ), "No failures" ) ) | DA14: =IF(OR(CU14>=50,CW14="Material",CW14="Severe",AS14="Material",AS14="Severe",BF14="Material",BF14="Severe — Exclusion Trigger",AND(ISNUMBER(BS14),BS14<30)),"Yes","No") | DB14: =IF(OR(CR14>=6,AW14="Confirmed Violation",AX14="Confirmed Breach"),"Yes — Automatic",IF(CW14="Severe","Yes — Requires Captain Confirmation","No")) | DL14: =IF(OR(IFERROR(VALUE(LEFT(DF14,1)),99)<=2,IFERROR(VALUE(LEFT(DG14,1)),99)<=2),"Flagged","Clear") | DM14: =IF(OR(DA14="Yes",DB14<>"No",DH14="Unverified",DL14="Flagged"),"Yes","No") | DN14: {=MIN(100, IF(ISNUMBER(V14), _xlfn.IFS(V14>=3,25, V14=2,15, V14=1,5, TRUE,0), 0) + IFERROR(_xlfn.IFS(VALUE(LEFT(DF14,1))=5,25, VALUE(LEFT(DF14,1))=4,20, VALUE(LEFT(DF14,1))=3,15, VALUE(LEFT(DF14,1))=2,8, TRUE,0), 15) + IFERROR(_xlfn.IFS(VALUE(LEFT(DG14,1))=5,25, VALUE(LEFT(DG14,1))=4,20, VALUE(LEFT(DG14,1))=3,15, VALUE(LEFT(DG14,1))=2,8, TRUE,0), 15) + _xlfn.IFS(DH14="Fully Verified",25, DH14="Partially Verified",12, TRUE,0) )} | DO14: {=_xlfn.IFS( ISBLANK(AR14), "Insufficient Evidence", AND(AR14>=65, AJ14="Approved"), "Strong", AR14>=65, "Adequate", AR14>=40, "Adequate", AR14>=20, "Weak", TRUE, "Insufficient Evidence" )} | DP14: {=_xlfn.IFS( ISBLANK(BS14), "Insufficient Evidence", BS14>=65, "Strong", BS14>=40, "Adequate", BS14>=20, "Weak", TRUE, "Insufficient Evidence" )} | DQ14: {=_xlfn.IFS( ISBLANK(BE14), "Insufficient Evidence", OR(AW14="Confirmed Violation", AX14="Confirmed Breach"), "Severe — Hard Trigger", BE14>=65, "Strong", BE14>=40, "Adequate", BE14>=20, "Weak", TRUE, "Insufficient Evidence" )} | DR14: {=_xlfn.IFS( ISBLANK(CU14), "Insufficient Evidence", CU14<=20, "Low Risk", CU14<=50, "Moderate Risk", CU14<=75, "High Risk", TRUE, "Very High Risk" )} | DS14: {=_xlfn.IFS( ISBLANK(CE14), "Insufficient Evidence", AND(ISNUMBER(BW14),ISNUMBER(BV14),BW14>BV14), "Overclaiming Risk", CE14>=65, "Strong", CE14>=40, "Adequate", TRUE, "Weak" )} | DT14: =IF(DB14="Yes — Automatic",0,ROUND((IF(ISNUMBER(AR14),AR14,0)*0.3+IF(ISNUMBER(BS14),BS14,0)*0.2+IF(ISNUMBER(BE14),BE14,0)*0.2+IF(ISNUMBER(CE14),CE14,0)*0.15+(100-IF(ISNUMBER(CU14),CU14,50))*0.15)*IF(DN14>=75,1,IF(DN14>=50,0.9,IF(DN14>=25,0.75,0.6))),1)) | DU14: {=_xlfn.IFS( DV14="Upgraded to Clear", "Clear", DV14="Downgraded to Watchlist", "Watchlist", DV14="Downgraded to Exclusion", "Exclusion Risk", DB14="Yes — Automatic", "Exclusion Risk", OR(AW14="Confirmed Violation", AX14="Confirmed Breach"), "Exclusion Risk", OR(V14=0, ISBLANK(V14), DN14<20), "Insufficient Evidence", AND(DT14>=65, DA14="No", DB14="No"), "Clear", OR(DT14>=40, DA14="Yes"), "Watchlist", TRUE, "Exclusion Risk" )} | DW14: {=_xlfn.IFS( DU14="Exclusion Risk", "Exclude — Hard Trigger", DU14="Insufficient Evidence", "Watchlist — Further Evidence Needed", DU14="Watchlist", "Watchlist — Further Evidence Needed", AND(DU14="Clear", DT14>=80), "Include — No Conditions", DU14="Clear", "Include — Monitor", TRUE, "Watchlist — Further Evidence Needed" )} | EB14: =IF(OR(V14=0, ISBLANK(V14)), "MISSING — No sources reviewed", "") | EC14: =IF(AND(NOT(ISBLANK(DC14)), ISBLANK(DE14)), "PAGE REF MISSING", "")
A15: NatWest Group PLC | B15: RYSD | C15: =IF(ISBLANK('Universe Tracker'!D11),"",'Universe Tracker'!D11) | F15: =IF(ISBLANK('Universe Tracker'!F11),"",'Universe Tracker'!F11) | G15: =IF(ISBLANK('Universe Tracker'!G11),"",'Universe Tracker'!G11) | J15: =IF(ISBLANK(B15),"",B15&"_"&C15) | Y15: =IF(AND(V15>=2,K15="Yes",L15="Yes"),"Sufficient",IF(AND(V15>=1,OR(K15="Yes",L15="Yes")),"Thin","Insufficient")) | AR15: {=MIN(100, MAX(0, IFERROR(_xlfn.XLOOKUP(AJ15,'Lookup Tables'!$A$2:$A$7,'Lookup Tables'!$B$2:$B$7,0),0) + IF(Z15="Yes", IF(IFERROR(_xlfn.XLOOKUP(AJ15,'Lookup Tables'!$A$2:$A$7,'Lookup Tables'!$B$2:$B$7,0),0)<20, 5, 0), 0) + _xlfn.IFS(AB15="Yes", IF(ISNUMBER(AC15)*AND(AC15<=2030),15,10), AB15="Long-term Only", 5, AB15="No", 0, TRUE, 0) + _xlfn.IFS(AF15="Full",10, AF15="Partial",5, AF15="Scope 2 Only",3, TRUE,0) + _xlfn.IFS(AG15="Yes", IF(ISNUMBER(AH15)*AND(AH15>=5),10,6), AG15="Partial",4, TRUE,0) + _xlfn.IFS(AI15="Yes",5, AI15="Partial (material categories only)",3, TRUE,0) + _xlfn.IFS(AL15="Yes — Detailed",10, AL15="Yes — High Level",5, TRUE,0) + _xlfn.IFS(AM15="Yes — Quantified",15, AM15="Yes — Directional Only",7, TRUE,0) + _xlfn.IFS(AP15="Formal",5, AP15="Referenced",2, TRUE,0) + _xlfn.IFS(AQ15="No Issues Found",5, AQ15="Concern Identified",-5, AQ15="Severe Contradiction",-15, TRUE,0) + _xlfn.IFS(BC15="Reasonable Assurance",5, BC15="Limited Assurance",3, TRUE,0) - IF(AND(Z15="Yes", AI15="No"), 10, 0) - IF(AND(Z15="Yes", AM15="No"), 10, 0) ))} | BE15: {=MIN(100, MAX(0, IFERROR(_xlfn.XLOOKUP(AT15,'Lookup Tables'!$D$2:$D$6,'Lookup Tables'!$E$2:$E$6,0),0) + IFERROR(_xlfn.XLOOKUP(AV15,'Lookup Tables'!$G$2:$G$5,'Lookup Tables'!$H$2:$H$5,0),0) + IFERROR(_xlfn.XLOOKUP(AW15,'Lookup Tables'!$J$2:$J$5,'Lookup Tables'!$K$2:$K$5,0),0) + _xlfn.IFS(AX15="No Issues",10, AX15="Complaint Filed",3, AX15="Confirmed Breach",-15, TRUE,0) + IFERROR(_xlfn.XLOOKUP(AY15,'Lookup Tables'!$M$2:$M$6,'Lookup Tables'!$N$2:$N$6,0),0) + IFERROR(_xlfn.XLOOKUP(AZ15,'Lookup Tables'!$P$2:$P$6,'Lookup Tables'!$Q$2:$Q$6,0),0) + _xlfn.IFS(BA15="Formal Board Committee",5, BA15="Board Oversight Mentioned",2, TRUE,0) + _xlfn.IFS(BB15="Yes — Quantified Targets",5, BB15="Yes — Discretionary Only",2, TRUE,0) + _xlfn.IFS(BC15="Reasonable Assurance",5, BC15="Limited Assurance",3, BC15="Management Review Only",1, TRUE,0) ))} | BS15: {=MIN(100, MAX(0, IFERROR(_xlfn.XLOOKUP(BG15,'Lookup Tables'!$A$11:$A$16,'Lookup Tables'!$B$11:$B$16,0),0) + IFERROR(_xlfn.XLOOKUP(BR15,'Lookup Tables'!$M$11:$M$14,'Lookup Tables'!$N$11:$N$14,0),0) + IFERROR(_xlfn.XLOOKUP(BQ15,'Lookup Tables'!$J$11:$J$15,'Lookup Tables'!$K$11:$K$15,0),0) + IFERROR(_xlfn.XLOOKUP(BH15,'Lookup Tables'!$D$11:$D$15,'Lookup Tables'!$E$11:$E$15,0),0) + IFERROR(_xlfn.XLOOKUP(BJ15,'Lookup Tables'!$G$11:$G$16,'Lookup Tables'!$H$11:$H$16,0),0) + IFERROR(_xlfn.XLOOKUP(BN15,'Lookup Tables'!$P$11:$P$15,'Lookup Tables'!$Q$11:$Q$15,0),0) + _xlfn.IFS(BM15="No Evidence",10, BM15="Unknown",3, BM15="Likely",0, BM15="Confirmed",-10, TRUE,3) + IFERROR(_xlfn.XLOOKUP(BP15,'Lookup Tables'!$J$21:$J$24,'Lookup Tables'!$K$21:$K$24,0),0) ))} | CE15: {=MIN(100, MAX(0, IF(ISNUMBER(BV15)*AND(BV15>0), 10, 0) + _xlfn.IFS(BY15="Independently Verified",25, BY15="Yes",15, TRUE,0) + IFERROR(_xlfn.XLOOKUP(BZ15,'Lookup Tables'!$A$21:$A$24,'Lookup Tables'!$B$21:$B$24,0),0) + IFERROR(_xlfn.XLOOKUP(CA15,'Lookup Tables'!$D$21:$D$24,'Lookup Tables'!$E$21:$E$24,0),0) + _xlfn.IFS(ISNUMBER(CB15)*AND(CB15>=11),15, ISNUMBER(CB15)*AND(CB15>=6),10, ISNUMBER(CB15)*AND(CB15>=1),5, TRUE,0) + IFERROR(_xlfn.XLOOKUP(CC15,'Lookup Tables'!$G$21:$G$25,'Lookup Tables'!$H$21:$H$25,0),0) - IF(ISNUMBER(BW15)*AND(ISNUMBER(BV15))*AND(BW15>BV15), 20, 0) - IF(AND(BY15="Yes", ISNUMBER(BW15), BW15>60), 10, 0) ))} | CR15: =COUNTIF(CJ15:CQ15,"FAIL") | CS15: =COUNTIF(CJ15:CQ15,"PARTIAL") | CT15: =COUNTIF(CJ15:CQ15,"MISSING") | CU15: =MIN(100, CR15*15 + CS15*6 + CT15*3 + IFERROR(_xlfn.XLOOKUP(CW15,'Lookup Tables'!$M$21:$M$25,'Lookup Tables'!$N$21:$N$25,0),0) ) | CV15: =IFERROR( CHOOSE( MATCH("FAIL",CJ15:CQ15,0), "1-Specificity","2-Metric","3-Baseline","4-Target", "5-Time Horizon","6-Scope","7-Verification","8-Consistency" ), IFERROR( CHOOSE( MATCH("PARTIAL",CJ15:CQ15,0), "1-Specificity","2-Metric","3-Baseline","4-Target", "5-Time Horizon","6-Scope","7-Verification","8-Consistency" ), "No failures" ) ) | DA15: =IF(OR(CU15>=50,CW15="Material",CW15="Severe",AS15="Material",AS15="Severe",BF15="Material",BF15="Severe — Exclusion Trigger",AND(ISNUMBER(BS15),BS15<30)),"Yes","No") | DB15: =IF(OR(CR15>=6,AW15="Confirmed Violation",AX15="Confirmed Breach"),"Yes — Automatic",IF(CW15="Severe","Yes — Requires Captain Confirmation","No")) | DL15: =IF(OR(IFERROR(VALUE(LEFT(DF15,1)),99)<=2,IFERROR(VALUE(LEFT(DG15,1)),99)<=2),"Flagged","Clear") | DM15: =IF(OR(DA15="Yes",DB15<>"No",DH15="Unverified",DL15="Flagged"),"Yes","No") | DN15: {=MIN(100, IF(ISNUMBER(V15), _xlfn.IFS(V15>=3,25, V15=2,15, V15=1,5, TRUE,0), 0) + IFERROR(_xlfn.IFS(VALUE(LEFT(DF15,1))=5,25, VALUE(LEFT(DF15,1))=4,20, VALUE(LEFT(DF15,1))=3,15, VALUE(LEFT(DF15,1))=2,8, TRUE,0), 15) + IFERROR(_xlfn.IFS(VALUE(LEFT(DG15,1))=5,25, VALUE(LEFT(DG15,1))=4,20, VALUE(LEFT(DG15,1))=3,15, VALUE(LEFT(DG15,1))=2,8, TRUE,0), 15) + _xlfn.IFS(DH15="Fully Verified",25, DH15="Partially Verified",12, TRUE,0) )} | DO15: {=_xlfn.IFS( ISBLANK(AR15), "Insufficient Evidence", AND(AR15>=65, AJ15="Approved"), "Strong", AR15>=65, "Adequate", AR15>=40, "Adequate", AR15>=20, "Weak", TRUE, "Insufficient Evidence" )} | DP15: {=_xlfn.IFS( ISBLANK(BS15), "Insufficient Evidence", BS15>=65, "Strong", BS15>=40, "Adequate", BS15>=20, "Weak", TRUE, "Insufficient Evidence" )} | DQ15: {=_xlfn.IFS( ISBLANK(BE15), "Insufficient Evidence", OR(AW15="Confirmed Violation", AX15="Confirmed Breach"), "Severe — Hard Trigger", BE15>=65, "Strong", BE15>=40, "Adequate", BE15>=20, "Weak", TRUE, "Insufficient Evidence" )} | DR15: {=_xlfn.IFS( ISBLANK(CU15), "Insufficient Evidence", CU15<=20, "Low Risk", CU15<=50, "Moderate Risk", CU15<=75, "High Risk", TRUE, "Very High Risk" )} | DS15: {=_xlfn.IFS( ISBLANK(CE15), "Insufficient Evidence", AND(ISNUMBER(BW15),ISNUMBER(BV15),BW15>BV15), "Overclaiming Risk", CE15>=65, "Strong", CE15>=40, "Adequate", TRUE, "Weak" )} | DT15: =IF(DB15="Yes — Automatic",0,ROUND((IF(ISNUMBER(AR15),AR15,0)*0.3+IF(ISNUMBER(BS15),BS15,0)*0.2+IF(ISNUMBER(BE15),BE15,0)*0.2+IF(ISNUMBER(CE15),CE15,0)*0.15+(100-IF(ISNUMBER(CU15),CU15,50))*0.15)*IF(DN15>=75,1,IF(DN15>=50,0.9,IF(DN15>=25,0.75,0.6))),1)) | DU15: {=_xlfn.IFS( DV15="Upgraded to Clear", "Clear", DV15="Downgraded to Watchlist", "Watchlist", DV15="Downgraded to Exclusion", "Exclusion Risk", DB15="Yes — Automatic", "Exclusion Risk", OR(AW15="Confirmed Violation", AX15="Confirmed Breach"), "Exclusion Risk", OR(V15=0, ISBLANK(V15), DN15<20), "Insufficient Evidence", AND(DT15>=65, DA15="No", DB15="No"), "Clear", OR(DT15>=40, DA15="Yes"), "Watchlist", TRUE, "Exclusion Risk" )} | DW15: {=_xlfn.IFS( DU15="Exclusion Risk", "Exclude — Hard Trigger", DU15="Insufficient Evidence", "Watchlist — Further Evidence Needed", DU15="Watchlist", "Watchlist — Further Evidence Needed", AND(DU15="Clear", DT15>=80), "Include — No Conditions", DU15="Clear", "Include — Monitor", TRUE, "Watchlist — Further Evidence Needed" )} | EB15: =IF(OR(V15=0, ISBLANK(V15)), "MISSING — No sources reviewed", "") | EC15: =IF(AND(NOT(ISBLANK(DC15)), ISBLANK(DE15)), "PAGE REF MISSING", "")
A16: Wartsila OYJ Abp | B16: MTA | C16: =IF(ISBLANK('Universe Tracker'!D12),"",'Universe Tracker'!D12) | F16: =IF(ISBLANK('Universe Tracker'!F12),"",'Universe Tracker'!F12) | G16: =IF(ISBLANK('Universe Tracker'!G12),"",'Universe Tracker'!G12) | J16: =IF(ISBLANK(B16),"",B16&"_"&C16) | Y16: =IF(AND(V16>=2,K16="Yes",L16="Yes"),"Sufficient",IF(AND(V16>=1,OR(K16="Yes",L16="Yes")),"Thin","Insufficient")) | AR16: {=MIN(100, MAX(0, IFERROR(_xlfn.XLOOKUP(AJ16,'Lookup Tables'!$A$2:$A$7,'Lookup Tables'!$B$2:$B$7,0),0) + IF(Z16="Yes", IF(IFERROR(_xlfn.XLOOKUP(AJ16,'Lookup Tables'!$A$2:$A$7,'Lookup Tables'!$B$2:$B$7,0),0)<20, 5, 0), 0) + _xlfn.IFS(AB16="Yes", IF(ISNUMBER(AC16)*AND(AC16<=2030),15,10), AB16="Long-term Only", 5, AB16="No", 0, TRUE, 0) + _xlfn.IFS(AF16="Full",10, AF16="Partial",5, AF16="Scope 2 Only",3, TRUE,0) + _xlfn.IFS(AG16="Yes", IF(ISNUMBER(AH16)*AND(AH16>=5),10,6), AG16="Partial",4, TRUE,0) + _xlfn.IFS(AI16="Yes",5, AI16="Partial (material categories only)",3, TRUE,0) + _xlfn.IFS(AL16="Yes — Detailed",10, AL16="Yes — High Level",5, TRUE,0) + _xlfn.IFS(AM16="Yes — Quantified",15, AM16="Yes — Directional Only",7, TRUE,0) + _xlfn.IFS(AP16="Formal",5, AP16="Referenced",2, TRUE,0) + _xlfn.IFS(AQ16="No Issues Found",5, AQ16="Concern Identified",-5, AQ16="Severe Contradiction",-15, TRUE,0) + _xlfn.IFS(BC16="Reasonable Assurance",5, BC16="Limited Assurance",3, TRUE,0) - IF(AND(Z16="Yes", AI16="No"), 10, 0) - IF(AND(Z16="Yes", AM16="No"), 10, 0) ))} | BE16: {=MIN(100, MAX(0, IFERROR(_xlfn.XLOOKUP(AT16,'Lookup Tables'!$D$2:$D$6,'Lookup Tables'!$E$2:$E$6,0),0) + IFERROR(_xlfn.XLOOKUP(AV16,'Lookup Tables'!$G$2:$G$5,'Lookup Tables'!$H$2:$H$5,0),0) + IFERROR(_xlfn.XLOOKUP(AW16,'Lookup Tables'!$J$2:$J$5,'Lookup Tables'!$K$2:$K$5,0),0) + _xlfn.IFS(AX16="No Issues",10, AX16="Complaint Filed",3, AX16="Confirmed Breach",-15, TRUE,0) + IFERROR(_xlfn.XLOOKUP(AY16,'Lookup Tables'!$M$2:$M$6,'Lookup Tables'!$N$2:$N$6,0),0) + IFERROR(_xlfn.XLOOKUP(AZ16,'Lookup Tables'!$P$2:$P$6,'Lookup Tables'!$Q$2:$Q$6,0),0) + _xlfn.IFS(BA16="Formal Board Committee",5, BA16="Board Oversight Mentioned",2, TRUE,0) + _xlfn.IFS(BB16="Yes — Quantified Targets",5, BB16="Yes — Discretionary Only",2, TRUE,0) + _xlfn.IFS(BC16="Reasonable Assurance",5, BC16="Limited Assurance",3, BC16="Management Review Only",1, TRUE,0) ))} | BS16: {=MIN(100, MAX(0, IFERROR(_xlfn.XLOOKUP(BG16,'Lookup Tables'!$A$11:$A$16,'Lookup Tables'!$B$11:$B$16,0),0) + IFERROR(_xlfn.XLOOKUP(BR16,'Lookup Tables'!$M$11:$M$14,'Lookup Tables'!$N$11:$N$14,0),0) + IFERROR(_xlfn.XLOOKUP(BQ16,'Lookup Tables'!$J$11:$J$15,'Lookup Tables'!$K$11:$K$15,0),0) + IFERROR(_xlfn.XLOOKUP(BH16,'Lookup Tables'!$D$11:$D$15,'Lookup Tables'!$E$11:$E$15,0),0) + IFERROR(_xlfn.XLOOKUP(BJ16,'Lookup Tables'!$G$11:$G$16,'Lookup Tables'!$H$11:$H$16,0),0) + IFERROR(_xlfn.XLOOKUP(BN16,'Lookup Tables'!$P$11:$P$15,'Lookup Tables'!$Q$11:$Q$15,0),0) + _xlfn.IFS(BM16="No Evidence",10, BM16="Unknown",3, BM16="Likely",0, BM16="Confirmed",-10, TRUE,3) + IFERROR(_xlfn.XLOOKUP(BP16,'Lookup Tables'!$J$21:$J$24,'Lookup Tables'!$K$21:$K$24,0),0) ))} | CE16: {=MIN(100, MAX(0, IF(ISNUMBER(BV16)*AND(BV16>0), 10, 0) + _xlfn.IFS(BY16="Independently Verified",25, BY16="Yes",15, TRUE,0) + IFERROR(_xlfn.XLOOKUP(BZ16,'Lookup Tables'!$A$21:$A$24,'Lookup Tables'!$B$21:$B$24,0),0) + IFERROR(_xlfn.XLOOKUP(CA16,'Lookup Tables'!$D$21:$D$24,'Lookup Tables'!$E$21:$E$24,0),0) + _xlfn.IFS(ISNUMBER(CB16)*AND(CB16>=11),15, ISNUMBER(CB16)*AND(CB16>=6),10, ISNUMBER(CB16)*AND(CB16>=1),5, TRUE,0) + IFERROR(_xlfn.XLOOKUP(CC16,'Lookup Tables'!$G$21:$G$25,'Lookup Tables'!$H$21:$H$25,0),0) - IF(ISNUMBER(BW16)*AND(ISNUMBER(BV16))*AND(BW16>BV16), 20, 0) - IF(AND(BY16="Yes", ISNUMBER(BW16), BW16>60), 10, 0) ))} | CR16: =COUNTIF(CJ16:CQ16,"FAIL") | CS16: =COUNTIF(CJ16:CQ16,"PARTIAL") | CT16: =COUNTIF(CJ16:CQ16,"MISSING") | CU16: =MIN(100, CR16*15 + CS16*6 + CT16*3 + IFERROR(_xlfn.XLOOKUP(CW16,'Lookup Tables'!$M$21:$M$25,'Lookup Tables'!$N$21:$N$25,0),0) ) | CV16: =IFERROR( CHOOSE( MATCH("FAIL",CJ16:CQ16,0), "1-Specificity","2-Metric","3-Baseline","4-Target", "5-Time Horizon","6-Scope","7-Verification","8-Consistency" ), IFERROR( CHOOSE( MATCH("PARTIAL",CJ16:CQ16,0), "1-Specificity","2-Metric","3-Baseline","4-Target", "5-Time Horizon","6-Scope","7-Verification","8-Consistency" ), "No failures" ) ) | DA16: =IF(OR(CU16>=50,CW16="Material",CW16="Severe",AS16="Material",AS16="Severe",BF16="Material",BF16="Severe — Exclusion Trigger",AND(ISNUMBER(BS16),BS16<30)),"Yes","No") | DB16: =IF(OR(CR16>=6,AW16="Confirmed Violation",AX16="Confirmed Breach"),"Yes — Automatic",IF(CW16="Severe","Yes — Requires Captain Confirmation","No")) | DL16: =IF(OR(IFERROR(VALUE(LEFT(DF16,1)),99)<=2,IFERROR(VALUE(LEFT(DG16,1)),99)<=2),"Flagged","Clear") | DM16: =IF(OR(DA16="Yes",DB16<>"No",DH16="Unverified",DL16="Flagged"),"Yes","No") | DN16: {=MIN(100, IF(ISNUMBER(V16), _xlfn.IFS(V16>=3,25, V16=2,15, V16=1,5, TRUE,0), 0) + IFERROR(_xlfn.IFS(VALUE(LEFT(DF16,1))=5,25, VALUE(LEFT(DF16,1))=4,20, VALUE(LEFT(DF16,1))=3,15, VALUE(LEFT(DF16,1))=2,8, TRUE,0), 15) + IFERROR(_xlfn.IFS(VALUE(LEFT(DG16,1))=5,25, VALUE(LEFT(DG16,1))=4,20, VALUE(LEFT(DG16,1))=3,15, VALUE(LEFT(DG16,1))=2,8, TRUE,0), 15) + _xlfn.IFS(DH16="Fully Verified",25, DH16="Partially Verified",12, TRUE,0) )} | DO16: {=_xlfn.IFS( ISBLANK(AR16), "Insufficient Evidence", AND(AR16>=65, AJ16="Approved"), "Strong", AR16>=65, "Adequate", AR16>=40, "Adequate", AR16>=20, "Weak", TRUE, "Insufficient Evidence" )} | DP16: {=_xlfn.IFS( ISBLANK(BS16), "Insufficient Evidence", BS16>=65, "Strong", BS16>=40, "Adequate", BS16>=20, "Weak", TRUE, "Insufficient Evidence" )} | DQ16: {=_xlfn.IFS( ISBLANK(BE16), "Insufficient Evidence", OR(AW16="Confirmed Violation", AX16="Confirmed Breach"), "Severe — Hard Trigger", BE16>=65, "Strong", BE16>=40, "Adequate", BE16>=20, "Weak", TRUE, "Insufficient Evidence" )} | DR16: {=_xlfn.IFS( ISBLANK(CU16), "Insufficient Evidence", CU16<=20, "Low Risk", CU16<=50, "Moderate Risk", CU16<=75, "High Risk", TRUE, "Very High Risk" )} | DS16: {=_xlfn.IFS( ISBLANK(CE16), "Insufficient Evidence", AND(ISNUMBER(BW16),ISNUMBER(BV16),BW16>BV16), "Overclaiming Risk", CE16>=65, "Strong", CE16>=40, "Adequate", TRUE, "Weak" )} | DT16: =IF(DB16="Yes — Automatic",0,ROUND((IF(ISNUMBER(AR16),AR16,0)*0.3+IF(ISNUMBER(BS16),BS16,0)*0.2+IF(ISNUMBER(BE16),BE16,0)*0.2+IF(ISNUMBER(CE16),CE16,0)*0.15+(100-IF(ISNUMBER(CU16),CU16,50))*0.15)*IF(DN16>=75,1,IF(DN16>=50,0.9,IF(DN16>=25,0.75,0.6))),1)) | DU16: {=_xlfn.IFS( DV16="Upgraded to Clear", "Clear", DV16="Downgraded to Watchlist", "Watchlist", DV16="Downgraded to Exclusion", "Exclusion Risk", DB16="Yes — Automatic", "Exclusion Risk", OR(AW16="Confirmed Violation", AX16="Confirmed Breach"), "Exclusion Risk", OR(V16=0, ISBLANK(V16), DN16<20), "Insufficient Evidence", AND(DT16>=65, DA16="No", DB16="No"), "Clear", OR(DT16>=40, DA16="Yes"), "Watchlist", TRUE, "Exclusion Risk" )} | DW16: {=_xlfn.IFS( DU16="Exclusion Risk", "Exclude — Hard Trigger", DU16="Insufficient Evidence", "Watchlist — Further Evidence Needed", DU16="Watchlist", "Watchlist — Further Evidence Needed", AND(DU16="Clear", DT16>=80), "Include — No Conditions", DU16="Clear", "Include — Monitor", TRUE, "Watchlist — Further Evidence Needed" )} | EB16: =IF(OR(V16=0, ISBLANK(V16)), "MISSING — No sources reviewed", "") | EC16: =IF(AND(NOT(ISBLANK(DC16)), ISBLANK(DE16)), "PAGE REF MISSING", "")
A17: UniCredit SpA | B17: CRIN | C17: =IF(ISBLANK('Universe Tracker'!D13),"",'Universe Tracker'!D13) | F17: =IF(ISBLANK('Universe Tracker'!F13),"",'Universe Tracker'!F13) | G17: =IF(ISBLANK('Universe Tracker'!G13),"",'Universe Tracker'!G13) | J17: =IF(ISBLANK(B17),"",B17&"_"&C17) | Y17: =IF(AND(V17>=2,K17="Yes",L17="Yes"),"Sufficient",IF(AND(V17>=1,OR(K17="Yes",L17="Yes")),"Thin","Insufficient")) | AR17: {=MIN(100, MAX(0, IFERROR(_xlfn.XLOOKUP(AJ17,'Lookup Tables'!$A$2:$A$7,'Lookup Tables'!$B$2:$B$7,0),0) + IF(Z17="Yes", IF(IFERROR(_xlfn.XLOOKUP(AJ17,'Lookup Tables'!$A$2:$A$7,'Lookup Tables'!$B$2:$B$7,0),0)<20, 5, 0), 0) + _xlfn.IFS(AB17="Yes", IF(ISNUMBER(AC17)*AND(AC17<=2030),15,10), AB17="Long-term Only", 5, AB17="No", 0, TRUE, 0) + _xlfn.IFS(AF17="Full",10, AF17="Partial",5, AF17="Scope 2 Only",3, TRUE,0) + _xlfn.IFS(AG17="Yes", IF(ISNUMBER(AH17)*AND(AH17>=5),10,6), AG17="Partial",4, TRUE,0) + _xlfn.IFS(AI17="Yes",5, AI17="Partial (material categories only)",3, TRUE,0) + _xlfn.IFS(AL17="Yes — Detailed",10, AL17="Yes — High Level",5, TRUE,0) + _xlfn.IFS(AM17="Yes — Quantified",15, AM17="Yes — Directional Only",7, TRUE,0) + _xlfn.IFS(AP17="Formal",5, AP17="Referenced",2, TRUE,0) + _xlfn.IFS(AQ17="No Issues Found",5, AQ17="Concern Identified",-5, AQ17="Severe Contradiction",-15, TRUE,0) + _xlfn.IFS(BC17="Reasonable Assurance",5, BC17="Limited Assurance",3, TRUE,0) - IF(AND(Z17="Yes", AI17="No"), 10, 0) - IF(AND(Z17="Yes", AM17="No"), 10, 0) ))} | BE17: {=MIN(100, MAX(0, IFERROR(_xlfn.XLOOKUP(AT17,'Lookup Tables'!$D$2:$D$6,'Lookup Tables'!$E$2:$E$6,0),0) + IFERROR(_xlfn.XLOOKUP(AV17,'Lookup Tables'!$G$2:$G$5,'Lookup Tables'!$H$2:$H$5,0),0) + IFERROR(_xlfn.XLOOKUP(AW17,'Lookup Tables'!$J$2:$J$5,'Lookup Tables'!$K$2:$K$5,0),0) + _xlfn.IFS(AX17="No Issues",10, AX17="Complaint Filed",3, AX17="Confirmed Breach",-15, TRUE,0) + IFERROR(_xlfn.XLOOKUP(AY17,'Lookup Tables'!$M$2:$M$6,'Lookup Tables'!$N$2:$N$6,0),0) + IFERROR(_xlfn.XLOOKUP(AZ17,'Lookup Tables'!$P$2:$P$6,'Lookup Tables'!$Q$2:$Q$6,0),0) + _xlfn.IFS(BA17="Formal Board Committee",5, BA17="Board Oversight Mentioned",2, TRUE,0) + _xlfn.IFS(BB17="Yes — Quantified Targets",5, BB17="Yes — Discretionary Only",2, TRUE,0) + _xlfn.IFS(BC17="Reasonable Assurance",5, BC17="Limited Assurance",3, BC17="Management Review Only",1, TRUE,0) ))} | BS17: {=MIN(100, MAX(0, IFERROR(_xlfn.XLOOKUP(BG17,'Lookup Tables'!$A$11:$A$16,'Lookup Tables'!$B$11:$B$16,0),0) + IFERROR(_xlfn.XLOOKUP(BR17,'Lookup Tables'!$M$11:$M$14,'Lookup Tables'!$N$11:$N$14,0),0) + IFERROR(_xlfn.XLOOKUP(BQ17,'Lookup Tables'!$J$11:$J$15,'Lookup Tables'!$K$11:$K$15,0),0) + IFERROR(_xlfn.XLOOKUP(BH17,'Lookup Tables'!$D$11:$D$15,'Lookup Tables'!$E$11:$E$15,0),0) + IFERROR(_xlfn.XLOOKUP(BJ17,'Lookup Tables'!$G$11:$G$16,'Lookup Tables'!$H$11:$H$16,0),0) + IFERROR(_xlfn.XLOOKUP(BN17,'Lookup Tables'!$P$11:$P$15,'Lookup Tables'!$Q$11:$Q$15,0),0) + _xlfn.IFS(BM17="No Evidence",10, BM17="Unknown",3, BM17="Likely",0, BM17="Confirmed",-10, TRUE,3) + IFERROR(_xlfn.XLOOKUP(BP17,'Lookup Tables'!$J$21:$J$24,'Lookup Tables'!$K$21:$K$24,0),0) ))} | CE17: {=MIN(100, MAX(0, IF(ISNUMBER(BV17)*AND(BV17>0), 10, 0) + _xlfn.IFS(BY17="Independently Verified",25, BY17="Yes",15, TRUE,0) + IFERROR(_xlfn.XLOOKUP(BZ17,'Lookup Tables'!$A$21:$A$24,'Lookup Tables'!$B$21:$B$24,0),0) + IFERROR(_xlfn.XLOOKUP(CA17,'Lookup Tables'!$D$21:$D$24,'Lookup Tables'!$E$21:$E$24,0),0) + _xlfn.IFS(ISNUMBER(CB17)*AND(CB17>=11),15, ISNUMBER(CB17)*AND(CB17>=6),10, ISNUMBER(CB17)*AND(CB17>=1),5, TRUE,0) + IFERROR(_xlfn.XLOOKUP(CC17,'Lookup Tables'!$G$21:$G$25,'Lookup Tables'!$H$21:$H$25,0),0) - IF(ISNUMBER(BW17)*AND(ISNUMBER(BV17))*AND(BW17>BV17), 20, 0) - IF(AND(BY17="Yes", ISNUMBER(BW17), BW17>60), 10, 0) ))} | CR17: =COUNTIF(CJ17:CQ17,"FAIL") | CS17: =COUNTIF(CJ17:CQ17,"PARTIAL") | CT17: =COUNTIF(CJ17:CQ17,"MISSING") | CU17: =MIN(100, CR17*15 + CS17*6 + CT17*3 + IFERROR(_xlfn.XLOOKUP(CW17,'Lookup Tables'!$M$21:$M$25,'Lookup Tables'!$N$21:$N$25,0),0) ) | CV17: =IFERROR( CHOOSE( MATCH("FAIL",CJ17:CQ17,0), "1-Specificity","2-Metric","3-Baseline","4-Target", "5-Time Horizon","6-Scope","7-Verification","8-Consistency" ), IFERROR( CHOOSE( MATCH("PARTIAL",CJ17:CQ17,0), "1-Specificity","2-Metric","3-Baseline","4-Target", "5-Time Horizon","6-Scope","7-Verification","8-Consistency" ), "No failures" ) ) | DA17: =IF(OR(CU17>=50,CW17="Material",CW17="Severe",AS17="Material",AS17="Severe",BF17="Material",BF17="Severe — Exclusion Trigger",AND(ISNUMBER(BS17),BS17<30)),"Yes","No") | DB17: =IF(OR(CR17>=6,AW17="Confirmed Violation",AX17="Confirmed Breach"),"Yes — Automatic",IF(CW17="Severe","Yes — Requires Captain Confirmation","No")) | DL17: =IF(OR(IFERROR(VALUE(LEFT(DF17,1)),99)<=2,IFERROR(VALUE(LEFT(DG17,1)),99)<=2),"Flagged","Clear") | DM17: =IF(OR(DA17="Yes",DB17<>"No",DH17="Unverified",DL17="Flagged"),"Yes","No") | DN17: {=MIN(100, IF(ISNUMBER(V17), _xlfn.IFS(V17>=3,25, V17=2,15, V17=1,5, TRUE,0), 0) + IFERROR(_xlfn.IFS(VALUE(LEFT(DF17,1))=5,25, VALUE(LEFT(DF17,1))=4,20, VALUE(LEFT(DF17,1))=3,15, VALUE(LEFT(DF17,1))=2,8, TRUE,0), 15) + IFERROR(_xlfn.IFS(VALUE(LEFT(DG17,1))=5,25, VALUE(LEFT(DG17,1))=4,20, VALUE(LEFT(DG17,1))=3,15, VALUE(LEFT(DG17,1))=2,8, TRUE,0), 15) + _xlfn.IFS(DH17="Fully Verified",25, DH17="Partially Verified",12, TRUE,0) )} | DO17: {=_xlfn.IFS( ISBLANK(AR17), "Insufficient Evidence", AND(AR17>=65, AJ17="Approved"), "Strong", AR17>=65, "Adequate", AR17>=40, "Adequate", AR17>=20, "Weak", TRUE, "Insufficient Evidence" )} | DP17: {=_xlfn.IFS( ISBLANK(BS17), "Insufficient Evidence", BS17>=65, "Strong", BS17>=40, "Adequate", BS17>=20, "Weak", TRUE, "Insufficient Evidence" )} | DQ17: {=_xlfn.IFS( ISBLANK(BE17), "Insufficient Evidence", OR(AW17="Confirmed Violation", AX17="Confirmed Breach"), "Severe — Hard Trigger", BE17>=65, "Strong", BE17>=40, "Adequate", BE17>=20, "Weak", TRUE, "Insufficient Evidence" )} | DR17: {=_xlfn.IFS( ISBLANK(CU17), "Insufficient Evidence", CU17<=20, "Low Risk", CU17<=50, "Moderate Risk", CU17<=75, "High Risk", TRUE, "Very High Risk" )} | DS17: {=_xlfn.IFS( ISBLANK(CE17), "Insufficient Evidence", AND(ISNUMBER(BW17),ISNUMBER(BV17),BW17>BV17), "Overclaiming Risk", CE17>=65, "Strong", CE17>=40, "Adequate", TRUE, "Weak" )} | DT17: =IF(DB17="Yes — Automatic",0,ROUND((IF(ISNUMBER(AR17),AR17,0)*0.3+IF(ISNUMBER(BS17),BS17,0)*0.2+IF(ISNUMBER(BE17),BE17,0)*0.2+IF(ISNUMBER(CE17),CE17,0)*0.15+(100-IF(ISNUMBER(CU17),CU17,50))*0.15)*IF(DN17>=75,1,IF(DN17>=50,0.9,IF(DN17>=25,0.75,0.6))),1)) | DU17: {=_xlfn.IFS( DV17="Upgraded to Clear", "Clear", DV17="Downgraded to Watchlist", "Watchlist", DV17="Downgraded to Exclusion", "Exclusion Risk", DB17="Yes — Automatic", "Exclusion Risk", OR(AW17="Confirmed Violation", AX17="Confirmed Breach"), "Exclusion Risk", OR(V17=0, ISBLANK(V17), DN17<20), "Insufficient Evidence", AND(DT17>=65, DA17="No", DB17="No"), "Clear", OR(DT17>=40, DA17="Yes"), "Watchlist", TRUE, "Exclusion Risk" )} | DW17: {=_xlfn.IFS( DU17="Exclusion Risk", "Exclude — Hard Trigger", DU17="Insufficient Evidence", "Watchlist — Further Evidence Needed", DU17="Watchlist", "Watchlist — Further Evidence Needed", AND(DU17="Clear", DT17>=80), "Include — No Conditions", DU17="Clear", "Include — Monitor", TRUE, "Watchlist — Further Evidence Needed" )} | EB17: =IF(OR(V17=0, ISBLANK(V17)), "MISSING — No sources reviewed", "") | EC17: =IF(AND(NOT(ISBLANK(DC17)), ISBLANK(DE17)), "PAGE REF MISSING", "")
A18: Games Workshop Group PLC | B18: G7W | C18: =IF(ISBLANK('Universe Tracker'!D14),"",'Universe Tracker'!D14) | F18: =IF(ISBLANK('Universe Tracker'!F14),"",'Universe Tracker'!F14) | G18: =IF(ISBLANK('Universe Tracker'!G14),"",'Universe Tracker'!G14) | J18: =IF(ISBLANK(B18),"",B18&"_"&C18) | Y18: =IF(AND(V18>=2,K18="Yes",L18="Yes"),"Sufficient",IF(AND(V18>=1,OR(K18="Yes",L18="Yes")),"Thin","Insufficient")) | AR18: {=MIN(100, MAX(0, IFERROR(_xlfn.XLOOKUP(AJ18,'Lookup Tables'!$A$2:$A$7,'Lookup Tables'!$B$2:$B$7,0),0) + IF(Z18="Yes", IF(IFERROR(_xlfn.XLOOKUP(AJ18,'Lookup Tables'!$A$2:$A$7,'Lookup Tables'!$B$2:$B$7,0),0)<20, 5, 0), 0) + _xlfn.IFS(AB18="Yes", IF(ISNUMBER(AC18)*AND(AC18<=2030),15,10), AB18="Long-term Only", 5, AB18="No", 0, TRUE, 0) + _xlfn.IFS(AF18="Full",10, AF18="Partial",5, AF18="Scope 2 Only",3, TRUE,0) + _xlfn.IFS(AG18="Yes", IF(ISNUMBER(AH18)*AND(AH18>=5),10,6), AG18="Partial",4, TRUE,0) + _xlfn.IFS(AI18="Yes",5, AI18="Partial (material categories only)",3, TRUE,0) + _xlfn.IFS(AL18="Yes — Detailed",10, AL18="Yes — High Level",5, TRUE,0) + _xlfn.IFS(AM18="Yes — Quantified",15, AM18="Yes — Directional Only",7, TRUE,0) + _xlfn.IFS(AP18="Formal",5, AP18="Referenced",2, TRUE,0) + _xlfn.IFS(AQ18="No Issues Found",5, AQ18="Concern Identified",-5, AQ18="Severe Contradiction",-15, TRUE,0) + _xlfn.IFS(BC18="Reasonable Assurance",5, BC18="Limited Assurance",3, TRUE,0) - IF(AND(Z18="Yes", AI18="No"), 10, 0) - IF(AND(Z18="Yes", AM18="No"), 10, 0) ))} | BE18: {=MIN(100, MAX(0, IFERROR(_xlfn.XLOOKUP(AT18,'Lookup Tables'!$D$2:$D$6,'Lookup Tables'!$E$2:$E$6,0),0) + IFERROR(_xlfn.XLOOKUP(AV18,'Lookup Tables'!$G$2:$G$5,'Lookup Tables'!$H$2:$H$5,0),0) + IFERROR(_xlfn.XLOOKUP(AW18,'Lookup Tables'!$J$2:$J$5,'Lookup Tables'!$K$2:$K$5,0),0) + _xlfn.IFS(AX18="No Issues",10, AX18="Complaint Filed",3, AX18="Confirmed Breach",-15, TRUE,0) + IFERROR(_xlfn.XLOOKUP(AY18,'Lookup Tables'!$M$2:$M$6,'Lookup Tables'!$N$2:$N$6,0),0) + IFERROR(_xlfn.XLOOKUP(AZ18,'Lookup Tables'!$P$2:$P$6,'Lookup Tables'!$Q$2:$Q$6,0),0) + _xlfn.IFS(BA18="Formal Board Committee",5, BA18="Board Oversight Mentioned",2, TRUE,0) + _xlfn.IFS(BB18="Yes — Quantified Targets",5, BB18="Yes — Discretionary Only",2, TRUE,0) + _xlfn.IFS(BC18="Reasonable Assurance",5, BC18="Limited Assurance",3, BC18="Management Review Only",1, TRUE,0) ))} | BS18: {=MIN(100, MAX(0, IFERROR(_xlfn.XLOOKUP(BG18,'Lookup Tables'!$A$11:$A$16,'Lookup Tables'!$B$11:$B$16,0),0) + IFERROR(_xlfn.XLOOKUP(BR18,'Lookup Tables'!$M$11:$M$14,'Lookup Tables'!$N$11:$N$14,0),0) + IFERROR(_xlfn.XLOOKUP(BQ18,'Lookup Tables'!$J$11:$J$15,'Lookup Tables'!$K$11:$K$15,0),0) + IFERROR(_xlfn.XLOOKUP(BH18,'Lookup Tables'!$D$11:$D$15,'Lookup Tables'!$E$11:$E$15,0),0) + IFERROR(_xlfn.XLOOKUP(BJ18,'Lookup Tables'!$G$11:$G$16,'Lookup Tables'!$H$11:$H$16,0),0) + IFERROR(_xlfn.XLOOKUP(BN18,'Lookup Tables'!$P$11:$P$15,'Lookup Tables'!$Q$11:$Q$15,0),0) + _xlfn.IFS(BM18="No Evidence",10, BM18="Unknown",3, BM18="Likely",0, BM18="Confirmed",-10, TRUE,3) + IFERROR(_xlfn.XLOOKUP(BP18,'Lookup Tables'!$J$21:$J$24,'Lookup Tables'!$K$21:$K$24,0),0) ))} | CE18: {=MIN(100, MAX(0, IF(ISNUMBER(BV18)*AND(BV18>0), 10, 0) + _xlfn.IFS(BY18="Independently Verified",25, BY18="Yes",15, TRUE,0) + IFERROR(_xlfn.XLOOKUP(BZ18,'Lookup Tables'!$A$21:$A$24,'Lookup Tables'!$B$21:$B$24,0),0) + IFERROR(_xlfn.XLOOKUP(CA18,'Lookup Tables'!$D$21:$D$24,'Lookup Tables'!$E$21:$E$24,0),0) + _xlfn.IFS(ISNUMBER(CB18)*AND(CB18>=11),15, ISNUMBER(CB18)*AND(CB18>=6),10, ISNUMBER(CB18)*AND(CB18>=1),5, TRUE,0) + IFERROR(_xlfn.XLOOKUP(CC18,'Lookup Tables'!$G$21:$G$25,'Lookup Tables'!$H$21:$H$25,0),0) - IF(ISNUMBER(BW18)*AND(ISNUMBER(BV18))*AND(BW18>BV18), 20, 0) - IF(AND(BY18="Yes", ISNUMBER(BW18), BW18>60), 10, 0) ))} | CR18: =COUNTIF(CJ18:CQ18,"FAIL") | CS18: =COUNTIF(CJ18:CQ18,"PARTIAL") | CT18: =COUNTIF(CJ18:CQ18,"MISSING") | CU18: =MIN(100, CR18*15 + CS18*6 + CT18*3 + IFERROR(_xlfn.XLOOKUP(CW18,'Lookup Tables'!$M$21:$M$25,'Lookup Tables'!$N$21:$N$25,0),0) ) | CV18: =IFERROR( CHOOSE( MATCH("FAIL",CJ18:CQ18,0), "1-Specificity","2-Metric","3-Baseline","4-Target", "5-Time Horizon","6-Scope","7-Verification","8-Consistency" ), IFERROR( CHOOSE( MATCH("PARTIAL",CJ18:CQ18,0), "1-Specificity","2-Metric","3-Baseline","4-Target", "5-Time Horizon","6-Scope","7-Verification","8-Consistency" ), "No failures" ) ) | DA18: =IF(OR(CU18>=50,CW18="Material",CW18="Severe",AS18="Material",AS18="Severe",BF18="Material",BF18="Severe — Exclusion Trigger",AND(ISNUMBER(BS18),BS18<30)),"Yes","No") | DB18: =IF(OR(CR18>=6,AW18="Confirmed Violation",AX18="Confirmed Breach"),"Yes — Automatic",IF(CW18="Severe","Yes — Requires Captain Confirmation","No")) | DL18: =IF(OR(IFERROR(VALUE(LEFT(DF18,1)),99)<=2,IFERROR(VALUE(LEFT(DG18,1)),99)<=2),"Flagged","Clear") | DM18: =IF(OR(DA18="Yes",DB18<>"No",DH18="Unverified",DL18="Flagged"),"Yes","No") | DN18: {=MIN(100, IF(ISNUMBER(V18), _xlfn.IFS(V18>=3,25, V18=2,15, V18=1,5, TRUE,0), 0) + IFERROR(_xlfn.IFS(VALUE(LEFT(DF18,1))=5,25, VALUE(LEFT(DF18,1))=4,20, VALUE(LEFT(DF18,1))=3,15, VALUE(LEFT(DF18,1))=2,8, TRUE,0), 15) + IFERROR(_xlfn.IFS(VALUE(LEFT(DG18,1))=5,25, VALUE(LEFT(DG18,1))=4,20, VALUE(LEFT(DG18,1))=3,15, VALUE(LEFT(DG18,1))=2,8, TRUE,0), 15) + _xlfn.IFS(DH18="Fully Verified",25, DH18="Partially Verified",12, TRUE,0) )} | DO18: {=_xlfn.IFS( ISBLANK(AR18), "Insufficient Evidence", AND(AR18>=65, AJ18="Approved"), "Strong", AR18>=65, "Adequate", AR18>=40, "Adequate", AR18>=20, "Weak", TRUE, "Insufficient Evidence" )} | DP18: {=_xlfn.IFS( ISBLANK(BS18), "Insufficient Evidence", BS18>=65, "Strong", BS18>=40, "Adequate", BS18>=20, "Weak", TRUE, "Insufficient Evidence" )} | DQ18: {=_xlfn.IFS( ISBLANK(BE18), "Insufficient Evidence", OR(AW18="Confirmed Violation", AX18="Confirmed Breach"), "Severe — Hard Trigger", BE18>=65, "Strong", BE18>=40, "Adequate", BE18>=20, "Weak", TRUE, "Insufficient Evidence" )} | DR18: {=_xlfn.IFS( ISBLANK(CU18), "Insufficient Evidence", CU18<=20, "Low Risk", CU18<=50, "Moderate Risk", CU18<=75, "High Risk", TRUE, "Very High Risk" )} | DS18: {=_xlfn.IFS( ISBLANK(CE18), "Insufficient Evidence", AND(ISNUMBER(BW18),ISNUMBER(BV18),BW18>BV18), "Overclaiming Risk", CE18>=65, "Strong", CE18>=40, "Adequate", TRUE, "Weak" )} | DT18: =IF(DB18="Yes — Automatic",0,ROUND((IF(ISNUMBER(AR18),AR18,0)*0.3+IF(ISNUMBER(BS18),BS18,0)*0.2+IF(ISNUMBER(BE18),BE18,0)*0.2+IF(ISNUMBER(CE18),CE18,0)*0.15+(100-IF(ISNUMBER(CU18),CU18,50))*0.15)*IF(DN18>=75,1,IF(DN18>=50,0.9,IF(DN18>=25,0.75,0.6))),1)) | DU18: {=_xlfn.IFS( DV18="Upgraded to Clear", "Clear", DV18="Downgraded to Watchlist", "Watchlist", DV18="Downgraded to Exclusion", "Exclusion Risk", DB18="Yes — Automatic", "Exclusion Risk", OR(AW18="Confirmed Violation", AX18="Confirmed Breach"), "Exclusion Risk", OR(V18=0, ISBLANK(V18), DN18<20), "Insufficient Evidence", AND(DT18>=65, DA18="No", DB18="No"), "Clear", OR(DT18>=40, DA18="Yes"), "Watchlist", TRUE, "Exclusion Risk" )} | DW18: {=_xlfn.IFS( DU18="Exclusion Risk", "Exclude — Hard Trigger", DU18="Insufficient Evidence", "Watchlist — Further Evidence Needed", DU18="Watchlist", "Watchlist — Further Evidence Needed", AND(DU18="Clear", DT18>=80), "Include — No Conditions", DU18="Clear", "Include — Monitor", TRUE, "Watchlist — Further Evidence Needed" )} | EB18: =IF(OR(V18=0, ISBLANK(V18)), "MISSING — No sources reviewed", "") | EC18: =IF(AND(NOT(ISBLANK(DC18)), ISBLANK(DE18)), "PAGE REF MISSING", "")
A19: 3i Group PLC | B19: IGQ5 | C19: =IF(ISBLANK('Universe Tracker'!D15),"",'Universe Tracker'!D15) | F19: =IF(ISBLANK('Universe Tracker'!F15),"",'Universe Tracker'!F15) | G19: =IF(ISBLANK('Universe Tracker'!G15),"",'Universe Tracker'!G15) | J19: =IF(ISBLANK(B19),"",B19&"_"&C19) | Y19: =IF(AND(V19>=2,K19="Yes",L19="Yes"),"Sufficient",IF(AND(V19>=1,OR(K19="Yes",L19="Yes")),"Thin","Insufficient")) | AR19: {=MIN(100, MAX(0, IFERROR(_xlfn.XLOOKUP(AJ19,'Lookup Tables'!$A$2:$A$7,'Lookup Tables'!$B$2:$B$7,0),0) + IF(Z19="Yes", IF(IFERROR(_xlfn.XLOOKUP(AJ19,'Lookup Tables'!$A$2:$A$7,'Lookup Tables'!$B$2:$B$7,0),0)<20, 5, 0), 0) + _xlfn.IFS(AB19="Yes", IF(ISNUMBER(AC19)*AND(AC19<=2030),15,10), AB19="Long-term Only", 5, AB19="No", 0, TRUE, 0) + _xlfn.IFS(AF19="Full",10, AF19="Partial",5, AF19="Scope 2 Only",3, TRUE,0) + _xlfn.IFS(AG19="Yes", IF(ISNUMBER(AH19)*AND(AH19>=5),10,6), AG19="Partial",4, TRUE,0) + _xlfn.IFS(AI19="Yes",5, AI19="Partial (material categories only)",3, TRUE,0) + _xlfn.IFS(AL19="Yes — Detailed",10, AL19="Yes — High Level",5, TRUE,0) + _xlfn.IFS(AM19="Yes — Quantified",15, AM19="Yes — Directional Only",7, TRUE,0) + _xlfn.IFS(AP19="Formal",5, AP19="Referenced",2, TRUE,0) + _xlfn.IFS(AQ19="No Issues Found",5, AQ19="Concern Identified",-5, AQ19="Severe Contradiction",-15, TRUE,0) + _xlfn.IFS(BC19="Reasonable Assurance",5, BC19="Limited Assurance",3, TRUE,0) - IF(AND(Z19="Yes", AI19="No"), 10, 0) - IF(AND(Z19="Yes", AM19="No"), 10, 0) ))} | BE19: {=MIN(100, MAX(0, IFERROR(_xlfn.XLOOKUP(AT19,'Lookup Tables'!$D$2:$D$6,'Lookup Tables'!$E$2:$E$6,0),0) + IFERROR(_xlfn.XLOOKUP(AV19,'Lookup Tables'!$G$2:$G$5,'Lookup Tables'!$H$2:$H$5,0),0) + IFERROR(_xlfn.XLOOKUP(AW19,'Lookup Tables'!$J$2:$J$5,'Lookup Tables'!$K$2:$K$5,0),0) + _xlfn.IFS(AX19="No Issues",10, AX19="Complaint Filed",3, AX19="Confirmed Breach",-15, TRUE,0) + IFERROR(_xlfn.XLOOKUP(AY19,'Lookup Tables'!$M$2:$M$6,'Lookup Tables'!$N$2:$N$6,0),0) + IFERROR(_xlfn.XLOOKUP(AZ19,'Lookup Tables'!$P$2:$P$6,'Lookup Tables'!$Q$2:$Q$6,0),0) + _xlfn.IFS(BA19="Formal Board Committee",5, BA19="Board Oversight Mentioned",2, TRUE,0) + _xlfn.IFS(BB19="Yes — Quantified Targets",5, BB19="Yes — Discretionary Only",2, TRUE,0) + _xlfn.IFS(BC19="Reasonable Assurance",5, BC19="Limited Assurance",3, BC19="Management Review Only",1, TRUE,0) ))} | BS19: {=MIN(100, MAX(0, IFERROR(_xlfn.XLOOKUP(BG19,'Lookup Tables'!$A$11:$A$16,'Lookup Tables'!$B$11:$B$16,0),0) + IFERROR(_xlfn.XLOOKUP(BR19,'Lookup Tables'!$M$11:$M$14,'Lookup Tables'!$N$11:$N$14,0),0) + IFERROR(_xlfn.XLOOKUP(BQ19,'Lookup Tables'!$J$11:$J$15,'Lookup Tables'!$K$11:$K$15,0),0) + IFERROR(_xlfn.XLOOKUP(BH19,'Lookup Tables'!$D$11:$D$15,'Lookup Tables'!$E$11:$E$15,0),0) + IFERROR(_xlfn.XLOOKUP(BJ19,'Lookup Tables'!$G$11:$G$16,'Lookup Tables'!$H$11:$H$16,0),0) + IFERROR(_xlfn.XLOOKUP(BN19,'Lookup Tables'!$P$11:$P$15,'Lookup Tables'!$Q$11:$Q$15,0),0) + _xlfn.IFS(BM19="No Evidence",10, BM19="Unknown",3, BM19="Likely",0, BM19="Confirmed",-10, TRUE,3) + IFERROR(_xlfn.XLOOKUP(BP19,'Lookup Tables'!$J$21:$J$24,'Lookup Tables'!$K$21:$K$24,0),0) ))} | CE19: {=MIN(100, MAX(0, IF(ISNUMBER(BV19)*AND(BV19>0), 10, 0) + _xlfn.IFS(BY19="Independently Verified",25, BY19="Yes",15, TRUE,0) + IFERROR(_xlfn.XLOOKUP(BZ19,'Lookup Tables'!$A$21:$A$24,'Lookup Tables'!$B$21:$B$24,0),0) + IFERROR(_xlfn.XLOOKUP(CA19,'Lookup Tables'!$D$21:$D$24,'Lookup Tables'!$E$21:$E$24,0),0) + _xlfn.IFS(ISNUMBER(CB19)*AND(CB19>=11),15, ISNUMBER(CB19)*AND(CB19>=6),10, ISNUMBER(CB19)*AND(CB19>=1),5, TRUE,0) + IFERROR(_xlfn.XLOOKUP(CC19,'Lookup Tables'!$G$21:$G$25,'Lookup Tables'!$H$21:$H$25,0),0) - IF(ISNUMBER(BW19)*AND(ISNUMBER(BV19))*AND(BW19>BV19), 20, 0) - IF(AND(BY19="Yes", ISNUMBER(BW19), BW19>60), 10, 0) ))} | CR19: =COUNTIF(CJ19:CQ19,"FAIL") | CS19: =COUNTIF(CJ19:CQ19,"PARTIAL") | CT19: =COUNTIF(CJ19:CQ19,"MISSING") | CU19: =MIN(100, CR19*15 + CS19*6 + CT19*3 + IFERROR(_xlfn.XLOOKUP(CW19,'Lookup Tables'!$M$21:$M$25,'Lookup Tables'!$N$21:$N$25,0),0) ) | CV19: =IFERROR( CHOOSE( MATCH("FAIL",CJ19:CQ19,0), "1-Specificity","2-Metric","3-Baseline","4-Target", "5-Time Horizon","6-Scope","7-Verification","8-Consistency" ), IFERROR( CHOOSE( MATCH("PARTIAL",CJ19:CQ19,0), "1-Specificity","2-Metric","3-Baseline","4-Target", "5-Time Horizon","6-Scope","7-Verification","8-Consistency" ), "No failures" ) ) | DA19: =IF(OR(CU19>=50,CW19="Material",CW19="Severe",AS19="Material",AS19="Severe",BF19="Material",BF19="Severe — Exclusion Trigger",AND(ISNUMBER(BS19),BS19<30)),"Yes","No") | DB19: =IF(OR(CR19>=6,AW19="Confirmed Violation",AX19="Confirmed Breach"),"Yes — Automatic",IF(CW19="Severe","Yes — Requires Captain Confirmation","No")) | DL19: =IF(OR(IFERROR(VALUE(LEFT(DF19,1)),99)<=2,IFERROR(VALUE(LEFT(DG19,1)),99)<=2),"Flagged","Clear") | DM19: =IF(OR(DA19="Yes",DB19<>"No",DH19="Unverified",DL19="Flagged"),"Yes","No") | DN19: {=MIN(100, IF(ISNUMBER(V19), _xlfn.IFS(V19>=3,25, V19=2,15, V19=1,5, TRUE,0), 0) + IFERROR(_xlfn.IFS(VALUE(LEFT(DF19,1))=5,25, VALUE(LEFT(DF19,1))=4,20, VALUE(LEFT(DF19,1))=3,15, VALUE(LEFT(DF19,1))=2,8, TRUE,0), 15) + IFERROR(_xlfn.IFS(VALUE(LEFT(DG19,1))=5,25, VALUE(LEFT(DG19,1))=4,20, VALUE(LEFT(DG19,1))=3,15, VALUE(LEFT(DG19,1))=2,8, TRUE,0), 15) + _xlfn.IFS(DH19="Fully Verified",25, DH19="Partially Verified",12, TRUE,0) )} | DO19: {=_xlfn.IFS( ISBLANK(AR19), "Insufficient Evidence", AND(AR19>=65, AJ19="Approved"), "Strong", AR19>=65, "Adequate", AR19>=40, "Adequate", AR19>=20, "Weak", TRUE, "Insufficient Evidence" )} | DP19: {=_xlfn.IFS( ISBLANK(BS19), "Insufficient Evidence", BS19>=65, "Strong", BS19>=40, "Adequate", BS19>=20, "Weak", TRUE, "Insufficient Evidence" )} | DQ19: {=_xlfn.IFS( ISBLANK(BE19), "Insufficient Evidence", OR(AW19="Confirmed Violation", AX19="Confirmed Breach"), "Severe — Hard Trigger", BE19>=65, "Strong", BE19>=40, "Adequate", BE19>=20, "Weak", TRUE, "Insufficient Evidence" )} | DR19: {=_xlfn.IFS( ISBLANK(CU19), "Insufficient Evidence", CU19<=20, "Low Risk", CU19<=50, "Moderate Risk", CU19<=75, "High Risk", TRUE, "Very High Risk" )} | DS19: {=_xlfn.IFS( ISBLANK(CE19), "Insufficient Evidence", AND(ISNUMBER(BW19),ISNUMBER(BV19),BW19>BV19), "Overclaiming Risk", CE19>=65, "Strong", CE19>=40, "Adequate", TRUE, "Weak" )} | DT19: =IF(DB19="Yes — Automatic",0,ROUND((IF(ISNUMBER(AR19),AR19,0)*0.3+IF(ISNUMBER(BS19),BS19,0)*0.2+IF(ISNUMBER(BE19),BE19,0)*0.2+IF(ISNUMBER(CE19),CE19,0)*0.15+(100-IF(ISNUMBER(CU19),CU19,50))*0.15)*IF(DN19>=75,1,IF(DN19>=50,0.9,IF(DN19>=25,0.75,0.6))),1)) | DU19: {=_xlfn.IFS( DV19="Upgraded to Clear", "Clear", DV19="Downgraded to Watchlist", "Watchlist", DV19="Downgraded to Exclusion", "Exclusion Risk", DB19="Yes — Automatic", "Exclusion Risk", OR(AW19="Confirmed Violation", AX19="Confirmed Breach"), "Exclusion Risk", OR(V19=0, ISBLANK(V19), DN19<20), "Insufficient Evidence", AND(DT19>=65, DA19="No", DB19="No"), "Clear", OR(DT19>=40, DA19="Yes"), "Watchlist", TRUE, "Exclusion Risk" )} | DW19: {=_xlfn.IFS( DU19="Exclusion Risk", "Exclude — Hard Trigger", DU19="Insufficient Evidence", "Watchlist — Further Evidence Needed", DU19="Watchlist", "Watchlist — Further Evidence Needed", AND(DU19="Clear", DT19>=80), "Include — No Conditions", DU19="Clear", "Include — Monitor", TRUE, "Watchlist — Further Evidence Needed" )} | EB19: =IF(OR(V19=0, ISBLANK(V19)), "MISSING — No sources reviewed", "") | EC19: =IF(AND(NOT(ISBLANK(DC19)), ISBLANK(DE19)), "PAGE REF MISSING", "")
A20: Powszechna Kasa Oszczednosci Bank Polski SA | B20: P9O | C20: =IF(ISBLANK('Universe Tracker'!D16),"",'Universe Tracker'!D16) | F20: =IF(ISBLANK('Universe Tracker'!F16),"",'Universe Tracker'!F16) | G20: =IF(ISBLANK('Universe Tracker'!G16),"",'Universe Tracker'!G16) | J20: =IF(ISBLANK(B20),"",B20&"_"&C20) | Y20: =IF(AND(V20>=2,K20="Yes",L20="Yes"),"Sufficient",IF(AND(V20>=1,OR(K20="Yes",L20="Yes")),"Thin","Insufficient")) | AR20: {=MIN(100, MAX(0, IFERROR(_xlfn.XLOOKUP(AJ20,'Lookup Tables'!$A$2:$A$7,'Lookup Tables'!$B$2:$B$7,0),0) + IF(Z20="Yes", IF(IFERROR(_xlfn.XLOOKUP(AJ20,'Lookup Tables'!$A$2:$A$7,'Lookup Tables'!$B$2:$B$7,0),0)<20, 5, 0), 0) + _xlfn.IFS(AB20="Yes", IF(ISNUMBER(AC20)*AND(AC20<=2030),15,10), AB20="Long-term Only", 5, AB20="No", 0, TRUE, 0) + _xlfn.IFS(AF20="Full",10, AF20="Partial",5, AF20="Scope 2 Only",3, TRUE,0) + _xlfn.IFS(AG20="Yes", IF(ISNUMBER(AH20)*AND(AH20>=5),10,6), AG20="Partial",4, TRUE,0) + _xlfn.IFS(AI20="Yes",5, AI20="Partial (material categories only)",3, TRUE,0) + _xlfn.IFS(AL20="Yes — Detailed",10, AL20="Yes — High Level",5, TRUE,0) + _xlfn.IFS(AM20="Yes — Quantified",15, AM20="Yes — Directional Only",7, TRUE,0) + _xlfn.IFS(AP20="Formal",5, AP20="Referenced",2, TRUE,0) + _xlfn.IFS(AQ20="No Issues Found",5, AQ20="Concern Identified",-5, AQ20="Severe Contradiction",-15, TRUE,0) + _xlfn.IFS(BC20="Reasonable Assurance",5, BC20="Limited Assurance",3, TRUE,0) - IF(AND(Z20="Yes", AI20="No"), 10, 0) - IF(AND(Z20="Yes", AM20="No"), 10, 0) ))} | BE20: {=MIN(100, MAX(0, IFERROR(_xlfn.XLOOKUP(AT20,'Lookup Tables'!$D$2:$D$6,'Lookup Tables'!$E$2:$E$6,0),0) + IFERROR(_xlfn.XLOOKUP(AV20,'Lookup Tables'!$G$2:$G$5,'Lookup Tables'!$H$2:$H$5,0),0) + IFERROR(_xlfn.XLOOKUP(AW20,'Lookup Tables'!$J$2:$J$5,'Lookup Tables'!$K$2:$K$5,0),0) + _xlfn.IFS(AX20="No Issues",10, AX20="Complaint Filed",3, AX20="Confirmed Breach",-15, TRUE,0) + IFERROR(_xlfn.XLOOKUP(AY20,'Lookup Tables'!$M$2:$M$6,'Lookup Tables'!$N$2:$N$6,0),0) + IFERROR(_xlfn.XLOOKUP(AZ20,'Lookup Tables'!$P$2:$P$6,'Lookup Tables'!$Q$2:$Q$6,0),0) + _xlfn.IFS(BA20="Formal Board Committee",5, BA20="Board Oversight Mentioned",2, TRUE,0) + _xlfn.IFS(BB20="Yes — Quantified Targets",5, BB20="Yes — Discretionary Only",2, TRUE,0) + _xlfn.IFS(BC20="Reasonable Assurance",5, BC20="Limited Assurance",3, BC20="Management Review Only",1, TRUE,0) ))} | BS20: {=MIN(100, MAX(0, IFERROR(_xlfn.XLOOKUP(BG20,'Lookup Tables'!$A$11:$A$16,'Lookup Tables'!$B$11:$B$16,0),0) + IFERROR(_xlfn.XLOOKUP(BR20,'Lookup Tables'!$M$11:$M$14,'Lookup Tables'!$N$11:$N$14,0),0) + IFERROR(_xlfn.XLOOKUP(BQ20,'Lookup Tables'!$J$11:$J$15,'Lookup Tables'!$K$11:$K$15,0),0) + IFERROR(_xlfn.XLOOKUP(BH20,'Lookup Tables'!$D$11:$D$15,'Lookup Tables'!$E$11:$E$15,0),0) + IFERROR(_xlfn.XLOOKUP(BJ20,'Lookup Tables'!$G$11:$G$16,'Lookup Tables'!$H$11:$H$16,0),0) + IFERROR(_xlfn.XLOOKUP(BN20,'Lookup Tables'!$P$11:$P$15,'Lookup Tables'!$Q$11:$Q$15,0),0) + _xlfn.IFS(BM20="No Evidence",10, BM20="Unknown",3, BM20="Likely",0, BM20="Confirmed",-10, TRUE,3) + IFERROR(_xlfn.XLOOKUP(BP20,'Lookup Tables'!$J$21:$J$24,'Lookup Tables'!$K$21:$K$24,0),0) ))} | CE20: {=MIN(100, MAX(0, IF(ISNUMBER(BV20)*AND(BV20>0), 10, 0) + _xlfn.IFS(BY20="Independently Verified",25, BY20="Yes",15, TRUE,0) + IFERROR(_xlfn.XLOOKUP(BZ20,'Lookup Tables'!$A$21:$A$24,'Lookup Tables'!$B$21:$B$24,0),0) + IFERROR(_xlfn.XLOOKUP(CA20,'Lookup Tables'!$D$21:$D$24,'Lookup Tables'!$E$21:$E$24,0),0) + _xlfn.IFS(ISNUMBER(CB20)*AND(CB20>=11),15, ISNUMBER(CB20)*AND(CB20>=6),10, ISNUMBER(CB20)*AND(CB20>=1),5, TRUE,0) + IFERROR(_xlfn.XLOOKUP(CC20,'Lookup Tables'!$G$21:$G$25,'Lookup Tables'!$H$21:$H$25,0),0) - IF(ISNUMBER(BW20)*AND(ISNUMBER(BV20))*AND(BW20>BV20), 20, 0) - IF(AND(BY20="Yes", ISNUMBER(BW20), BW20>60), 10, 0) ))} | CR20: =COUNTIF(CJ20:CQ20,"FAIL") | CS20: =COUNTIF(CJ20:CQ20,"PARTIAL") | CT20: =COUNTIF(CJ20:CQ20,"MISSING") | CU20: =MIN(100, CR20*15 + CS20*6 + CT20*3 + IFERROR(_xlfn.XLOOKUP(CW20,'Lookup Tables'!$M$21:$M$25,'Lookup Tables'!$N$21:$N$25,0),0) ) | CV20: =IFERROR( CHOOSE( MATCH("FAIL",CJ20:CQ20,0), "1-Specificity","2-Metric","3-Baseline","4-Target", "5-Time Horizon","6-Scope","7-Verification","8-Consistency" ), IFERROR( CHOOSE( MATCH("PARTIAL",CJ20:CQ20,0), "1-Specificity","2-Metric","3-Baseline","4-Target", "5-Time Horizon","6-Scope","7-Verification","8-Consistency" ), "No failures" ) ) | DA20: =IF(OR(CU20>=50,CW20="Material",CW20="Severe",AS20="Material",AS20="Severe",BF20="Material",BF20="Severe — Exclusion Trigger",AND(ISNUMBER(BS20),BS20<30)),"Yes","No") | DB20: =IF(OR(CR20>=6,AW20="Confirmed Violation",AX20="Confirmed Breach"),"Yes — Automatic",IF(CW20="Severe","Yes — Requires Captain Confirmation","No")) | DL20: =IF(OR(IFERROR(VALUE(LEFT(DF20,1)),99)<=2,IFERROR(VALUE(LEFT(DG20,1)),99)<=2),"Flagged","Clear") | DM20: =IF(OR(DA20="Yes",DB20<>"No",DH20="Unverified",DL20="Flagged"),"Yes","No") | DN20: {=MIN(100, IF(ISNUMBER(V20), _xlfn.IFS(V20>=3,25, V20=2,15, V20=1,5, TRUE,0), 0) + IFERROR(_xlfn.IFS(VALUE(LEFT(DF20,1))=5,25, VALUE(LEFT(DF20,1))=4,20, VALUE(LEFT(DF20,1))=3,15, VALUE(LEFT(DF20,1))=2,8, TRUE,0), 15) + IFERROR(_xlfn.IFS(VALUE(LEFT(DG20,1))=5,25, VALUE(LEFT(DG20,1))=4,20, VALUE(LEFT(DG20,1))=3,15, VALUE(LEFT(DG20,1))=2,8, TRUE,0), 15) + _xlfn.IFS(DH20="Fully Verified",25, DH20="Partially Verified",12, TRUE,0) )} | DO20: {=_xlfn.IFS( ISBLANK(AR20), "Insufficient Evidence", AND(AR20>=65, AJ20="Approved"), "Strong", AR20>=65, "Adequate", AR20>=40, "Adequate", AR20>=20, "Weak", TRUE, "Insufficient Evidence" )} | DP20: {=_xlfn.IFS( ISBLANK(BS20), "Insufficient Evidence", BS20>=65, "Strong", BS20>=40, "Adequate", BS20>=20, "Weak", TRUE, "Insufficient Evidence" )} | DQ20: {=_xlfn.IFS( ISBLANK(BE20), "Insufficient Evidence", OR(AW20="Confirmed Violation", AX20="Confirmed Breach"), "Severe — Hard Trigger", BE20>=65, "Strong", BE20>=40, "Adequate", BE20>=20, "Weak", TRUE, "Insufficient Evidence" )} | DR20: {=_xlfn.IFS( ISBLANK(CU20), "Insufficient Evidence", CU20<=20, "Low Risk", CU20<=50, "Moderate Risk", CU20<=75, "High Risk", TRUE, "Very High Risk" )} | DS20: {=_xlfn.IFS( ISBLANK(CE20), "Insufficient Evidence", AND(ISNUMBER(BW20),ISNUMBER(BV20),BW20>BV20), "Overclaiming Risk", CE20>=65, "Strong", CE20>=40, "Adequate", TRUE, "Weak" )} | DT20: =IF(DB20="Yes — Automatic",0,ROUND((IF(ISNUMBER(AR20),AR20,0)*0.3+IF(ISNUMBER(BS20),BS20,0)*0.2+IF(ISNUMBER(BE20),BE20,0)*0.2+IF(ISNUMBER(CE20),CE20,0)*0.15+(100-IF(ISNUMBER(CU20),CU20,50))*0.15)*IF(DN20>=75,1,IF(DN20>=50,0.9,IF(DN20>=25,0.75,0.6))),1)) | DU20: {=_xlfn.IFS( DV20="Upgraded to Clear", "Clear", DV20="Downgraded to Watchlist", "Watchlist", DV20="Downgraded to Exclusion", "Exclusion Risk", DB20="Yes — Automatic", "Exclusion Risk", OR(AW20="Confirmed Violation", AX20="Confirmed Breach"), "Exclusion Risk", OR(V20=0, ISBLANK(V20), DN20<20), "Insufficient Evidence", AND(DT20>=65, DA20="No", DB20="No"), "Clear", OR(DT20>=40, DA20="Yes"), "Watchlist", TRUE, "Exclusion Risk" )} | DW20: {=_xlfn.IFS( DU20="Exclusion Risk", "Exclude — Hard Trigger", DU20="Insufficient Evidence", "Watchlist — Further Evidence Needed", DU20="Watchlist", "Watchlist — Further Evidence Needed", AND(DU20="Clear", DT20>=80), "Include — No Conditions", DU20="Clear", "Include — Monitor", TRUE, "Watchlist — Further Evidence Needed" )} | EB20: =IF(OR(V20=0, ISBLANK(V20)), "MISSING — No sources reviewed", "") | EC20: =IF(AND(NOT(ISBLANK(DC20)), ISBLANK(DE20)), "PAGE REF MISSING", "")
A21: Legrand SA | B21: LRC | C21: =IF(ISBLANK('Universe Tracker'!D17),"",'Universe Tracker'!D17) | F21: =IF(ISBLANK('Universe Tracker'!F17),"",'Universe Tracker'!F17) | G21: =IF(ISBLANK('Universe Tracker'!G17),"",'Universe Tracker'!G17) | J21: =IF(ISBLANK(B21),"",B21&"_"&C21) | Y21: =IF(AND(V21>=2,K21="Yes",L21="Yes"),"Sufficient",IF(AND(V21>=1,OR(K21="Yes",L21="Yes")),"Thin","Insufficient")) | AR21: {=MIN(100, MAX(0, IFERROR(_xlfn.XLOOKUP(AJ21,'Lookup Tables'!$A$2:$A$7,'Lookup Tables'!$B$2:$B$7,0),0) + IF(Z21="Yes", IF(IFERROR(_xlfn.XLOOKUP(AJ21,'Lookup Tables'!$A$2:$A$7,'Lookup Tables'!$B$2:$B$7,0),0)<20, 5, 0), 0) + _xlfn.IFS(AB21="Yes", IF(ISNUMBER(AC21)*AND(AC21<=2030),15,10), AB21="Long-term Only", 5, AB21="No", 0, TRUE, 0) + _xlfn.IFS(AF21="Full",10, AF21="Partial",5, AF21="Scope 2 Only",3, TRUE,0) + _xlfn.IFS(AG21="Yes", IF(ISNUMBER(AH21)*AND(AH21>=5),10,6), AG21="Partial",4, TRUE,0) + _xlfn.IFS(AI21="Yes",5, AI21="Partial (material categories only)",3, TRUE,0) + _xlfn.IFS(AL21="Yes — Detailed",10, AL21="Yes — High Level",5, TRUE,0) + _xlfn.IFS(AM21="Yes — Quantified",15, AM21="Yes — Directional Only",7, TRUE,0) + _xlfn.IFS(AP21="Formal",5, AP21="Referenced",2, TRUE,0) + _xlfn.IFS(AQ21="No Issues Found",5, AQ21="Concern Identified",-5, AQ21="Severe Contradiction",-15, TRUE,0) + _xlfn.IFS(BC21="Reasonable Assurance",5, BC21="Limited Assurance",3, TRUE,0) - IF(AND(Z21="Yes", AI21="No"), 10, 0) - IF(AND(Z21="Yes", AM21="No"), 10, 0) ))} | BE21: {=MIN(100, MAX(0, IFERROR(_xlfn.XLOOKUP(AT21,'Lookup Tables'!$D$2:$D$6,'Lookup Tables'!$E$2:$E$6,0),0) + IFERROR(_xlfn.XLOOKUP(AV21,'Lookup Tables'!$G$2:$G$5,'Lookup Tables'!$H$2:$H$5,0),0) + IFERROR(_xlfn.XLOOKUP(AW21,'Lookup Tables'!$J$2:$J$5,'Lookup Tables'!$K$2:$K$5,0),0) + _xlfn.IFS(AX21="No Issues",10, AX21="Complaint Filed",3, AX21="Confirmed Breach",-15, TRUE,0) + IFERROR(_xlfn.XLOOKUP(AY21,'Lookup Tables'!$M$2:$M$6,'Lookup Tables'!$N$2:$N$6,0),0) + IFERROR(_xlfn.XLOOKUP(AZ21,'Lookup Tables'!$P$2:$P$6,'Lookup Tables'!$Q$2:$Q$6,0),0) + _xlfn.IFS(BA21="Formal Board Committee",5, BA21="Board Oversight Mentioned",2, TRUE,0) + _xlfn.IFS(BB21="Yes — Quantified Targets",5, BB21="Yes — Discretionary Only",2, TRUE,0) + _xlfn.IFS(BC21="Reasonable Assurance",5, BC21="Limited Assurance",3, BC21="Management Review Only",1, TRUE,0) ))} | BS21: {=MIN(100, MAX(0, IFERROR(_xlfn.XLOOKUP(BG21,'Lookup Tables'!$A$11:$A$16,'Lookup Tables'!$B$11:$B$16,0),0) + IFERROR(_xlfn.XLOOKUP(BR21,'Lookup Tables'!$M$11:$M$14,'Lookup Tables'!$N$11:$N$14,0),0) + IFERROR(_xlfn.XLOOKUP(BQ21,'Lookup Tables'!$J$11:$J$15,'Lookup Tables'!$K$11:$K$15,0),0) + IFERROR(_xlfn.XLOOKUP(BH21,'Lookup Tables'!$D$11:$D$15,'Lookup Tables'!$E$11:$E$15,0),0) + IFERROR(_xlfn.XLOOKUP(BJ21,'Lookup Tables'!$G$11:$G$16,'Lookup Tables'!$H$11:$H$16,0),0) + IFERROR(_xlfn.XLOOKUP(BN21,'Lookup Tables'!$P$11:$P$15,'Lookup Tables'!$Q$11:$Q$15,0),0) + _xlfn.IFS(BM21="No Evidence",10, BM21="Unknown",3, BM21="Likely",0, BM21="Confirmed",-10, TRUE,3) + IFERROR(_xlfn.XLOOKUP(BP21,'Lookup Tables'!$J$21:$J$24,'Lookup Tables'!$K$21:$K$24,0),0) ))} | CE21: {=MIN(100, MAX(0, IF(ISNUMBER(BV21)*AND(BV21>0), 10, 0) + _xlfn.IFS(BY21="Independently Verified",25, BY21="Yes",15, TRUE,0) + IFERROR(_xlfn.XLOOKUP(BZ21,'Lookup Tables'!$A$21:$A$24,'Lookup Tables'!$B$21:$B$24,0),0) + IFERROR(_xlfn.XLOOKUP(CA21,'Lookup Tables'!$D$21:$D$24,'Lookup Tables'!$E$21:$E$24,0),0) + _xlfn.IFS(ISNUMBER(CB21)*AND(CB21>=11),15, ISNUMBER(CB21)*AND(CB21>=6),10, ISNUMBER(CB21)*AND(CB21>=1),5, TRUE,0) + IFERROR(_xlfn.XLOOKUP(CC21,'Lookup Tables'!$G$21:$G$25,'Lookup Tables'!$H$21:$H$25,0),0) - IF(ISNUMBER(BW21)*AND(ISNUMBER(BV21))*AND(BW21>BV21), 20, 0) - IF(AND(BY21="Yes", ISNUMBER(BW21), BW21>60), 10, 0) ))} | CR21: =COUNTIF(CJ21:CQ21,"FAIL") | CS21: =COUNTIF(CJ21:CQ21,"PARTIAL") | CT21: =COUNTIF(CJ21:CQ21,"MISSING") | CU21: =MIN(100, CR21*15 + CS21*6 + CT21*3 + IFERROR(_xlfn.XLOOKUP(CW21,'Lookup Tables'!$M$21:$M$25,'Lookup Tables'!$N$21:$N$25,0),0) ) | CV21: =IFERROR( CHOOSE( MATCH("FAIL",CJ21:CQ21,0), "1-Specificity","2-Metric","3-Baseline","4-Target", "5-Time Horizon","6-Scope","7-Verification","8-Consistency" ), IFERROR( CHOOSE( MATCH("PARTIAL",CJ21:CQ21,0), "1-Specificity","2-Metric","3-Baseline","4-Target", "5-Time Horizon","6-Scope","7-Verification","8-Consistency" ), "No failures" ) ) | DA21: =IF(OR(CU21>=50,CW21="Material",CW21="Severe",AS21="Material",AS21="Severe",BF21="Material",BF21="Severe — Exclusion Trigger",AND(ISNUMBER(BS21),BS21<30)),"Yes","No") | DB21: =IF(OR(CR21>=6,AW21="Confirmed Violation",AX21="Confirmed Breach"),"Yes — Automatic",IF(CW21="Severe","Yes — Requires Captain Confirmation","No")) | DL21: =IF(OR(IFERROR(VALUE(LEFT(DF21,1)),99)<=2,IFERROR(VALUE(LEFT(DG21,1)),99)<=2),"Flagged","Clear") | DM21: =IF(OR(DA21="Yes",DB21<>"No",DH21="Unverified",DL21="Flagged"),"Yes","No") | DN21: {=MIN(100, IF(ISNUMBER(V21), _xlfn.IFS(V21>=3,25, V21=2,15, V21=1,5, TRUE,0), 0) + IFERROR(_xlfn.IFS(VALUE(LEFT(DF21,1))=5,25, VALUE(LEFT(DF21,1))=4,20, VALUE(LEFT(DF21,1))=3,15, VALUE(LEFT(DF21,1))=2,8, TRUE,0), 15) + IFERROR(_xlfn.IFS(VALUE(LEFT(DG21,1))=5,25, VALUE(LEFT(DG21,1))=4,20, VALUE(LEFT(DG21,1))=3,15, VALUE(LEFT(DG21,1))=2,8, TRUE,0), 15) + _xlfn.IFS(DH21="Fully Verified",25, DH21="Partially Verified",12, TRUE,0) )} | DO21: {=_xlfn.IFS( ISBLANK(AR21), "Insufficient Evidence", AND(AR21>=65, AJ21="Approved"), "Strong", AR21>=65, "Adequate", AR21>=40, "Adequate", AR21>=20, "Weak", TRUE, "Insufficient Evidence" )} | DP21: {=_xlfn.IFS( ISBLANK(BS21), "Insufficient Evidence", BS21>=65, "Strong", BS21>=40, "Adequate", BS21>=20, "Weak", TRUE, "Insufficient Evidence" )} | DQ21: {=_xlfn.IFS( ISBLANK(BE21), "Insufficient Evidence", OR(AW21="Confirmed Violation", AX21="Confirmed Breach"), "Severe — Hard Trigger", BE21>=65, "Strong", BE21>=40, "Adequate", BE21>=20, "Weak", TRUE, "Insufficient Evidence" )} | DR21: {=_xlfn.IFS( ISBLANK(CU21), "Insufficient Evidence", CU21<=20, "Low Risk", CU21<=50, "Moderate Risk", CU21<=75, "High Risk", TRUE, "Very High Risk" )} | DS21: {=_xlfn.IFS( ISBLANK(CE21), "Insufficient Evidence", AND(ISNUMBER(BW21),ISNUMBER(BV21),BW21>BV21), "Overclaiming Risk", CE21>=65, "Strong", CE21>=40, "Adequate", TRUE, "Weak" )} | DT21: =IF(DB21="Yes — Automatic",0,ROUND((IF(ISNUMBER(AR21),AR21,0)*0.3+IF(ISNUMBER(BS21),BS21,0)*0.2+IF(ISNUMBER(BE21),BE21,0)*0.2+IF(ISNUMBER(CE21),CE21,0)*0.15+(100-IF(ISNUMBER(CU21),CU21,50))*0.15)*IF(DN21>=75,1,IF(DN21>=50,0.9,IF(DN21>=25,0.75,0.6))),1)) | DU21: {=_xlfn.IFS( DV21="Upgraded to Clear", "Clear", DV21="Downgraded to Watchlist", "Watchlist", DV21="Downgraded to Exclusion", "Exclusion Risk", DB21="Yes — Automatic", "Exclusion Risk", OR(AW21="Confirmed Violation", AX21="Confirmed Breach"), "Exclusion Risk", OR(V21=0, ISBLANK(V21), DN21<20), "Insufficient Evidence", AND(DT21>=65, DA21="No", DB21="No"), "Clear", OR(DT21>=40, DA21="Yes"), "Watchlist", TRUE, "Exclusion Risk" )} | DW21: {=_xlfn.IFS( DU21="Exclusion Risk", "Exclude — Hard Trigger", DU21="Insufficient Evidence", "Watchlist — Further Evidence Needed", DU21="Watchlist", "Watchlist — Further Evidence Needed", AND(DU21="Clear", DT21>=80), "Include — No Conditions", DU21="Clear", "Include — Monitor", TRUE, "Watchlist — Further Evidence Needed" )} | EB21: =IF(OR(V21=0, ISBLANK(V21)), "MISSING — No sources reviewed", "") | EC21: =IF(AND(NOT(ISBLANK(DC21)), ISBLANK(DE21)), "PAGE REF MISSING", "")
A22: Swissquote Group Holding SA | B22: 1SQ | C22: CH0010675863 | F22: =IF(ISBLANK('Universe Tracker'!F18),"",'Universe Tracker'!F18) | G22: =IF(ISBLANK('Universe Tracker'!G18),"",'Universe Tracker'!G18) | J22: =IF(ISBLANK(B22),"",B22&"_"&C22) | O22: Yes | P22: Yes | Y22: =IF(AND(V22>=2,K22="Yes",L22="Yes"),"Sufficient",IF(AND(V22>=1,OR(K22="Yes",L22="Yes")),"Thin","Insufficient")) | AJ22: Not in SBTi database (checked 2026-05-21) | AR22: {=MIN(100, MAX(0, IFERROR(_xlfn.XLOOKUP(AJ22,'Lookup Tables'!$A$2:$A$7,'Lookup Tables'!$B$2:$B$7,0),0) + IF(Z22="Yes", IF(IFERROR(_xlfn.XLOOKUP(AJ22,'Lookup Tables'!$A$2:$A$7,'Lookup Tables'!$B$2:$B$7,0),0)<20, 5, 0), 0) + _xlfn.IFS(AB22="Yes", IF(ISNUMBER(AC22)*AND(AC22<=2030),15,10), AB22="Long-term Only", 5, AB22="No", 0, TRUE, 0) + _xlfn.IFS(AF22="Full",10, AF22="Partial",5, AF22="Scope 2 Only",3, TRUE,0) + _xlfn.IFS(AG22="Yes", IF(ISNUMBER(AH22)*AND(AH22>=5),10,6), AG22="Partial",4, TRUE,0) + _xlfn.IFS(AI22="Yes",5, AI22="Partial (material categories only)",3, TRUE,0) + _xlfn.IFS(AL22="Yes — Detailed",10, AL22="Yes — High Level",5, TRUE,0) + _xlfn.IFS(AM22="Yes — Quantified",15, AM22="Yes — Directional Only",7, TRUE,0) + _xlfn.IFS(AP22="Formal",5, AP22="Referenced",2, TRUE,0) + _xlfn.IFS(AQ22="No Issues Found",5, AQ22="Concern Identified",-5, AQ22="Severe Contradiction",-15, TRUE,0) + _xlfn.IFS(BC22="Reasonable Assurance",5, BC22="Limited Assurance",3, TRUE,0) - IF(AND(Z22="Yes", AI22="No"), 10, 0) - IF(AND(Z22="Yes", AM22="No"), 10, 0) ))} | BE22: {=MIN(100, MAX(0, IFERROR(_xlfn.XLOOKUP(AT22,'Lookup Tables'!$D$2:$D$6,'Lookup Tables'!$E$2:$E$6,0),0) + IFERROR(_xlfn.XLOOKUP(AV22,'Lookup Tables'!$G$2:$G$5,'Lookup Tables'!$H$2:$H$5,0),0) + IFERROR(_xlfn.XLOOKUP(AW22,'Lookup Tables'!$J$2:$J$5,'Lookup Tables'!$K$2:$K$5,0),0) + _xlfn.IFS(AX22="No Issues",10, AX22="Complaint Filed",3, AX22="Confirmed Breach",-15, TRUE,0) + IFERROR(_xlfn.XLOOKUP(AY22,'Lookup Tables'!$M$2:$M$6,'Lookup Tables'!$N$2:$N$6,0),0) + IFERROR(_xlfn.XLOOKUP(AZ22,'Lookup Tables'!$P$2:$P$6,'Lookup Tables'!$Q$2:$Q$6,0),0) + _xlfn.IFS(BA22="Formal Board Committee",5, BA22="Board Oversight Mentioned",2, TRUE,0) + _xlfn.IFS(BB22="Yes — Quantified Targets",5, BB22="Yes — Discretionary Only",2, TRUE,0) + _xlfn.IFS(BC22="Reasonable Assurance",5, BC22="Limited Assurance",3, BC22="Management Review Only",1, TRUE,0) ))} | BS22: {=MIN(100, MAX(0, IFERROR(_xlfn.XLOOKUP(BG22,'Lookup Tables'!$A$11:$A$16,'Lookup Tables'!$B$11:$B$16,0),0) + IFERROR(_xlfn.XLOOKUP(BR22,'Lookup Tables'!$M$11:$M$14,'Lookup Tables'!$N$11:$N$14,0),0) + IFERROR(_xlfn.XLOOKUP(BQ22,'Lookup Tables'!$J$11:$J$15,'Lookup Tables'!$K$11:$K$15,0),0) + IFERROR(_xlfn.XLOOKUP(BH22,'Lookup Tables'!$D$11:$D$15,'Lookup Tables'!$E$11:$E$15,0),0) + IFERROR(_xlfn.XLOOKUP(BJ22,'Lookup Tables'!$G$11:$G$16,'Lookup Tables'!$H$11:$H$16,0),0) + IFERROR(_xlfn.XLOOKUP(BN22,'Lookup Tables'!$P$11:$P$15,'Lookup Tables'!$Q$11:$Q$15,0),0) + _xlfn.IFS(BM22="No Evidence",10, BM22="Unknown",3, BM22="Likely",0, BM22="Confirmed",-10, TRUE,3) + IFERROR(_xlfn.XLOOKUP(BP22,'Lookup Tables'!$J$21:$J$24,'Lookup Tables'!$K$21:$K$24,0),0) ))} | CE22: {=MIN(100, MAX(0, IF(ISNUMBER(BV22)*AND(BV22>0), 10, 0) + _xlfn.IFS(BY22="Independently Verified",25, BY22="Yes",15, TRUE,0) + IFERROR(_xlfn.XLOOKUP(BZ22,'Lookup Tables'!$A$21:$A$24,'Lookup Tables'!$B$21:$B$24,0),0) + IFERROR(_xlfn.XLOOKUP(CA22,'Lookup Tables'!$D$21:$D$24,'Lookup Tables'!$E$21:$E$24,0),0) + _xlfn.IFS(ISNUMBER(CB22)*AND(CB22>=11),15, ISNUMBER(CB22)*AND(CB22>=6),10, ISNUMBER(CB22)*AND(CB22>=1),5, TRUE,0) + IFERROR(_xlfn.XLOOKUP(CC22,'Lookup Tables'!$G$21:$G$25,'Lookup Tables'!$H$21:$H$25,0),0) - IF(ISNUMBER(BW22)*AND(ISNUMBER(BV22))*AND(BW22>BV22), 20, 0) - IF(AND(BY22="Yes", ISNUMBER(BW22), BW22>60), 10, 0) ))} | CG22: net-zero operations in our property portfolio by 2040 | CH22: SPS_ESG-Booklet_EN.pdf | CI22: 3 | CJ22: PASS | CK22: PARTIAL | CL22: MISSING | CM22: PARTIAL | CN22: PASS | CO22: PASS | CP22: PARTIAL | CQ22: MISSING | CR22: =COUNTIF(CJ22:CQ22,"FAIL") | CS22: =COUNTIF(CJ22:CQ22,"PARTIAL") | CT22: =COUNTIF(CJ22:CQ22,"MISSING") | CU22: =MIN(100, CR22*15 + CS22*6 + CT22*3 + IFERROR(_xlfn.XLOOKUP(CW22,'Lookup Tables'!$M$21:$M$25,'Lookup Tables'!$N$21:$N$25,0),0) ) | CV22: =IFERROR( CHOOSE( MATCH("FAIL",CJ22:CQ22,0), "1-Specificity","2-Metric","3-Baseline","4-Target", "5-Time Horizon","6-Scope","7-Verification","8-Consistency" ), IFERROR( CHOOSE( MATCH("PARTIAL",CJ22:CQ22,0), "1-Specificity","2-Metric","3-Baseline","4-Target", "5-Time Horizon","6-Scope","7-Verification","8-Consistency" ), "No failures" ) ) | DA22: =IF(OR(CU22>=50,CW22="Material",CW22="Severe",AS22="Material",AS22="Severe",BF22="Material",BF22="Severe — Exclusion Trigger",AND(ISNUMBER(BS22),BS22<30)),"Yes","No") | DB22: =IF(OR(CR22>=6,AW22="Confirmed Violation",AX22="Confirmed Breach"),"Yes — Automatic",IF(CW22="Severe","Yes — Requires Captain Confirmation","No")) | DC22: net-zero operations in our property portfolio by 2040 | DD22: SPS_ESG-Booklet_EN.pdf | DE22: 3 | DF22: 3 | DG22: 4 | DH22: PENDING | DL22: =IF(OR(IFERROR(VALUE(LEFT(DF22,1)),99)<=2,IFERROR(VALUE(LEFT(DG22,1)),99)<=2),"Flagged","Clear") | DM22: =IF(OR(DA22="Yes",DB22<>"No",DH22="Unverified",DL22="Flagged"),"Yes","No") | DN22: {=MIN(100, IF(ISNUMBER(V22), _xlfn.IFS(V22>=3,25, V22=2,15, V22=1,5, TRUE,0), 0) + IFERROR(_xlfn.IFS(VALUE(LEFT(DF22,1))=5,25, VALUE(LEFT(DF22,1))=4,20, VALUE(LEFT(DF22,1))=3,15, VALUE(LEFT(DF22,1))=2,8, TRUE,0), 15) + IFERROR(_xlfn.IFS(VALUE(LEFT(DG22,1))=5,25, VALUE(LEFT(DG22,1))=4,20, VALUE(LEFT(DG22,1))=3,15, VALUE(LEFT(DG22,1))=2,8, TRUE,0), 15) + _xlfn.IFS(DH22="Fully Verified",25, DH22="Partially Verified",12, TRUE,0) )} | DO22: {=_xlfn.IFS( ISBLANK(AR22), "Insufficient Evidence", AND(AR22>=65, AJ22="Approved"), "Strong", AR22>=65, "Adequate", AR22>=40, "Adequate", AR22>=20, "Weak", TRUE, "Insufficient Evidence" )} | DP22: {=_xlfn.IFS( ISBLANK(BS22), "Insufficient Evidence", BS22>=65, "Strong", BS22>=40, "Adequate", BS22>=20, "Weak", TRUE, "Insufficient Evidence" )} | DQ22: {=_xlfn.IFS( ISBLANK(BE22), "Insufficient Evidence", OR(AW22="Confirmed Violation", AX22="Confirmed Breach"), "Severe — Hard Trigger", BE22>=65, "Strong", BE22>=40, "Adequate", BE22>=20, "Weak", TRUE, "Insufficient Evidence" )} | DR22: {=_xlfn.IFS( ISBLANK(CU22), "Insufficient Evidence", CU22<=20, "Low Risk", CU22<=50, "Moderate Risk", CU22<=75, "High Risk", TRUE, "Very High Risk" )} | DS22: {=_xlfn.IFS( ISBLANK(CE22), "Insufficient Evidence", AND(ISNUMBER(BW22),ISNUMBER(BV22),BW22>BV22), "Overclaiming Risk", CE22>=65, "Strong", CE22>=40, "Adequate", TRUE, "Weak" )} | DT22: =IF(DB22="Yes — Automatic",0,ROUND((IF(ISNUMBER(AR22),AR22,0)*0.3+IF(ISNUMBER(BS22),BS22,0)*0.2+IF(ISNUMBER(BE22),BE22,0)*0.2+IF(ISNUMBER(CE22),CE22,0)*0.15+(100-IF(ISNUMBER(CU22),CU22,50))*0.15)*IF(DN22>=75,1,IF(DN22>=50,0.9,IF(DN22>=25,0.75,0.6))),1)) | DU22: {=_xlfn.IFS( DV22="Upgraded to Clear", "Clear", DV22="Downgraded to Watchlist", "Watchlist", DV22="Downgraded to Exclusion", "Exclusion Risk", DB22="Yes — Automatic", "Exclusion Risk", OR(AW22="Confirmed Violation", AX22="Confirmed Breach"), "Exclusion Risk", OR(V22=0, ISBLANK(V22), DN22<20), "Insufficient Evidence", AND(DT22>=65, DA22="No", DB22="No"), "Clear", OR(DT22>=40, DA22="Yes"), "Watchlist", TRUE, "Exclusion Risk" )} | DW22: {=_xlfn.IFS( DU22="Exclusion Risk", "Exclude — Hard Trigger", DU22="Insufficient Evidence", "Watchlist — Further Evidence Needed", DU22="Watchlist", "Watchlist — Further Evidence Needed", AND(DU22="Clear", DT22>=80), "Include — No Conditions", DU22="Clear", "Include — Monitor", TRUE, "Watchlist — Further Evidence Needed" )} | DX22: Main claim: "net-zero operations in our property portfolio by 2040" (SPS_ESG-Booklet_EN.pdf, p3). SBTi: no validated target in the SBTi database. 8-Test: 3 PARTIAL, 0 FAIL, 2 MISSING -> PASS. SOURCE LIMITATION: assessed from Swiss Prime's 16-page ESG summary booklet; the company's full disclosures are split across separate E/S/G reports. 'baseline' and 'consistency' are marked MISSING because they are absent from this... | EB22: =IF(OR(V22=0, ISBLANK(V22)), "MISSING — No sources reviewed", "") | EC22: =IF(AND(NOT(ISBLANK(DC22)), ISBLANK(DE22)), "PAGE REF MISSING", "")
A23: AXA SA | B23: AXA | C23: =IF(ISBLANK('Universe Tracker'!D19),"",'Universe Tracker'!D19) | F23: =IF(ISBLANK('Universe Tracker'!F19),"",'Universe Tracker'!F19) | G23: =IF(ISBLANK('Universe Tracker'!G19),"",'Universe Tracker'!G19) | J23: =IF(ISBLANK(B23),"",B23&"_"&C23) | Y23: =IF(AND(V23>=2,K23="Yes",L23="Yes"),"Sufficient",IF(AND(V23>=1,OR(K23="Yes",L23="Yes")),"Thin","Insufficient")) | AR23: {=MIN(100, MAX(0, IFERROR(_xlfn.XLOOKUP(AJ23,'Lookup Tables'!$A$2:$A$7,'Lookup Tables'!$B$2:$B$7,0),0) + IF(Z23="Yes", IF(IFERROR(_xlfn.XLOOKUP(AJ23,'Lookup Tables'!$A$2:$A$7,'Lookup Tables'!$B$2:$B$7,0),0)<20, 5, 0), 0) + _xlfn.IFS(AB23="Yes", IF(ISNUMBER(AC23)*AND(AC23<=2030),15,10), AB23="Long-term Only", 5, AB23="No", 0, TRUE, 0) + _xlfn.IFS(AF23="Full",10, AF23="Partial",5, AF23="Scope 2 Only",3, TRUE,0) + _xlfn.IFS(AG23="Yes", IF(ISNUMBER(AH23)*AND(AH23>=5),10,6), AG23="Partial",4, TRUE,0) + _xlfn.IFS(AI23="Yes",5, AI23="Partial (material categories only)",3, TRUE,0) + _xlfn.IFS(AL23="Yes — Detailed",10, AL23="Yes — High Level",5, TRUE,0) + _xlfn.IFS(AM23="Yes — Quantified",15, AM23="Yes — Directional Only",7, TRUE,0) + _xlfn.IFS(AP23="Formal",5, AP23="Referenced",2, TRUE,0) + _xlfn.IFS(AQ23="No Issues Found",5, AQ23="Concern Identified",-5, AQ23="Severe Contradiction",-15, TRUE,0) + _xlfn.IFS(BC23="Reasonable Assurance",5, BC23="Limited Assurance",3, TRUE,0) - IF(AND(Z23="Yes", AI23="No"), 10, 0) - IF(AND(Z23="Yes", AM23="No"), 10, 0) ))} | BE23: {=MIN(100, MAX(0, IFERROR(_xlfn.XLOOKUP(AT23,'Lookup Tables'!$D$2:$D$6,'Lookup Tables'!$E$2:$E$6,0),0) + IFERROR(_xlfn.XLOOKUP(AV23,'Lookup Tables'!$G$2:$G$5,'Lookup Tables'!$H$2:$H$5,0),0) + IFERROR(_xlfn.XLOOKUP(AW23,'Lookup Tables'!$J$2:$J$5,'Lookup Tables'!$K$2:$K$5,0),0) + _xlfn.IFS(AX23="No Issues",10, AX23="Complaint Filed",3, AX23="Confirmed Breach",-15, TRUE,0) + IFERROR(_xlfn.XLOOKUP(AY23,'Lookup Tables'!$M$2:$M$6,'Lookup Tables'!$N$2:$N$6,0),0) + IFERROR(_xlfn.XLOOKUP(AZ23,'Lookup Tables'!$P$2:$P$6,'Lookup Tables'!$Q$2:$Q$6,0),0) + _xlfn.IFS(BA23="Formal Board Committee",5, BA23="Board Oversight Mentioned",2, TRUE,0) + _xlfn.IFS(BB23="Yes — Quantified Targets",5, BB23="Yes — Discretionary Only",2, TRUE,0) + _xlfn.IFS(BC23="Reasonable Assurance",5, BC23="Limited Assurance",3, BC23="Management Review Only",1, TRUE,0) ))} | BS23: {=MIN(100, MAX(0, IFERROR(_xlfn.XLOOKUP(BG23,'Lookup Tables'!$A$11:$A$16,'Lookup Tables'!$B$11:$B$16,0),0) + IFERROR(_xlfn.XLOOKUP(BR23,'Lookup Tables'!$M$11:$M$14,'Lookup Tables'!$N$11:$N$14,0),0) + IFERROR(_xlfn.XLOOKUP(BQ23,'Lookup Tables'!$J$11:$J$15,'Lookup Tables'!$K$11:$K$15,0),0) + IFERROR(_xlfn.XLOOKUP(BH23,'Lookup Tables'!$D$11:$D$15,'Lookup Tables'!$E$11:$E$15,0),0) + IFERROR(_xlfn.XLOOKUP(BJ23,'Lookup Tables'!$G$11:$G$16,'Lookup Tables'!$H$11:$H$16,0),0) + IFERROR(_xlfn.XLOOKUP(BN23,'Lookup Tables'!$P$11:$P$15,'Lookup Tables'!$Q$11:$Q$15,0),0) + _xlfn.IFS(BM23="No Evidence",10, BM23="Unknown",3, BM23="Likely",0, BM23="Confirmed",-10, TRUE,3) + IFERROR(_xlfn.XLOOKUP(BP23,'Lookup Tables'!$J$21:$J$24,'Lookup Tables'!$K$21:$K$24,0),0) ))} | CE23: {=MIN(100, MAX(0, IF(ISNUMBER(BV23)*AND(BV23>0), 10, 0) + _xlfn.IFS(BY23="Independently Verified",25, BY23="Yes",15, TRUE,0) + IFERROR(_xlfn.XLOOKUP(BZ23,'Lookup Tables'!$A$21:$A$24,'Lookup Tables'!$B$21:$B$24,0),0) + IFERROR(_xlfn.XLOOKUP(CA23,'Lookup Tables'!$D$21:$D$24,'Lookup Tables'!$E$21:$E$24,0),0) + _xlfn.IFS(ISNUMBER(CB23)*AND(CB23>=11),15, ISNUMBER(CB23)*AND(CB23>=6),10, ISNUMBER(CB23)*AND(CB23>=1),5, TRUE,0) + IFERROR(_xlfn.XLOOKUP(CC23,'Lookup Tables'!$G$21:$G$25,'Lookup Tables'!$H$21:$H$25,0),0) - IF(ISNUMBER(BW23)*AND(ISNUMBER(BV23))*AND(BW23>BV23), 20, 0) - IF(AND(BY23="Yes", ISNUMBER(BW23), BW23>60), 10, 0) ))} | CR23: =COUNTIF(CJ23:CQ23,"FAIL") | CS23: =COUNTIF(CJ23:CQ23,"PARTIAL") | CT23: =COUNTIF(CJ23:CQ23,"MISSING") | CU23: =MIN(100, CR23*15 + CS23*6 + CT23*3 + IFERROR(_xlfn.XLOOKUP(CW23,'Lookup Tables'!$M$21:$M$25,'Lookup Tables'!$N$21:$N$25,0),0) ) | CV23: =IFERROR( CHOOSE( MATCH("FAIL",CJ23:CQ23,0), "1-Specificity","2-Metric","3-Baseline","4-Target", "5-Time Horizon","6-Scope","7-Verification","8-Consistency" ), IFERROR( CHOOSE( MATCH("PARTIAL",CJ23:CQ23,0), "1-Specificity","2-Metric","3-Baseline","4-Target", "5-Time Horizon","6-Scope","7-Verification","8-Consistency" ), "No failures" ) ) | DA23: =IF(OR(CU23>=50,CW23="Material",CW23="Severe",AS23="Material",AS23="Severe",BF23="Material",BF23="Severe — Exclusion Trigger",AND(ISNUMBER(BS23),BS23<30)),"Yes","No") | DB23: =IF(OR(CR23>=6,AW23="Confirmed Violation",AX23="Confirmed Breach"),"Yes — Automatic",IF(CW23="Severe","Yes — Requires Captain Confirmation","No")) | DL23: =IF(OR(IFERROR(VALUE(LEFT(DF23,1)),99)<=2,IFERROR(VALUE(LEFT(DG23,1)),99)<=2),"Flagged","Clear") | DM23: =IF(OR(DA23="Yes",DB23<>"No",DH23="Unverified",DL23="Flagged"),"Yes","No") | DN23: {=MIN(100, IF(ISNUMBER(V23), _xlfn.IFS(V23>=3,25, V23=2,15, V23=1,5, TRUE,0), 0) + IFERROR(_xlfn.IFS(VALUE(LEFT(DF23,1))=5,25, VALUE(LEFT(DF23,1))=4,20, VALUE(LEFT(DF23,1))=3,15, VALUE(LEFT(DF23,1))=2,8, TRUE,0), 15) + IFERROR(_xlfn.IFS(VALUE(LEFT(DG23,1))=5,25, VALUE(LEFT(DG23,1))=4,20, VALUE(LEFT(DG23,1))=3,15, VALUE(LEFT(DG23,1))=2,8, TRUE,0), 15) + _xlfn.IFS(DH23="Fully Verified",25, DH23="Partially Verified",12, TRUE,0) )} | DO23: {=_xlfn.IFS( ISBLANK(AR23), "Insufficient Evidence", AND(AR23>=65, AJ23="Approved"), "Strong", AR23>=65, "Adequate", AR23>=40, "Adequate", AR23>=20, "Weak", TRUE, "Insufficient Evidence" )} | DP23: {=_xlfn.IFS( ISBLANK(BS23), "Insufficient Evidence", BS23>=65, "Strong", BS23>=40, "Adequate", BS23>=20, "Weak", TRUE, "Insufficient Evidence" )} | DQ23: {=_xlfn.IFS( ISBLANK(BE23), "Insufficient Evidence", OR(AW23="Confirmed Violation", AX23="Confirmed Breach"), "Severe — Hard Trigger", BE23>=65, "Strong", BE23>=40, "Adequate", BE23>=20, "Weak", TRUE, "Insufficient Evidence" )} | DR23: {=_xlfn.IFS( ISBLANK(CU23), "Insufficient Evidence", CU23<=20, "Low Risk", CU23<=50, "Moderate Risk", CU23<=75, "High Risk", TRUE, "Very High Risk" )} | DS23: {=_xlfn.IFS( ISBLANK(CE23), "Insufficient Evidence", AND(ISNUMBER(BW23),ISNUMBER(BV23),BW23>BV23), "Overclaiming Risk", CE23>=65, "Strong", CE23>=40, "Adequate", TRUE, "Weak" )} | DT23: =IF(DB23="Yes — Automatic",0,ROUND((IF(ISNUMBER(AR23),AR23,0)*0.3+IF(ISNUMBER(BS23),BS23,0)*0.2+IF(ISNUMBER(BE23),BE23,0)*0.2+IF(ISNUMBER(CE23),CE23,0)*0.15+(100-IF(ISNUMBER(CU23),CU23,50))*0.15)*IF(DN23>=75,1,IF(DN23>=50,0.9,IF(DN23>=25,0.75,0.6))),1)) | DU23: {=_xlfn.IFS( DV23="Upgraded to Clear", "Clear", DV23="Downgraded to Watchlist", "Watchlist", DV23="Downgraded to Exclusion", "Exclusion Risk", DB23="Yes — Automatic", "Exclusion Risk", OR(AW23="Confirmed Violation", AX23="Confirmed Breach"), "Exclusion Risk", OR(V23=0, ISBLANK(V23), DN23<20), "Insufficient Evidence", AND(DT23>=65, DA23="No", DB23="No"), "Clear", OR(DT23>=40, DA23="Yes"), "Watchlist", TRUE, "Exclusion Risk" )} | DW23: {=_xlfn.IFS( DU23="Exclusion Risk", "Exclude — Hard Trigger", DU23="Insufficient Evidence", "Watchlist — Further Evidence Needed", DU23="Watchlist", "Watchlist — Further Evidence Needed", AND(DU23="Clear", DT23>=80), "Include — No Conditions", DU23="Clear", "Include — Monitor", TRUE, "Watchlist — Further Evidence Needed" )} | EB23: =IF(OR(V23=0, ISBLANK(V23)), "MISSING — No sources reviewed", "") | EC23: =IF(AND(NOT(ISBLANK(DC23)), ISBLANK(DE23)), "PAGE REF MISSING", "")
A24: E.ON SE | B24: EOAN | C24: DE000ENAG999 | F24: =IF(ISBLANK('Universe Tracker'!F20),"",'Universe Tracker'!F20) | G24: =IF(ISBLANK('Universe Tracker'!G20),"",'Universe Tracker'!G20) | J24: =IF(ISBLANK(B24),"",B24&"_"&C24) | O24: Yes | P24: Yes | Y24: =IF(AND(V24>=2,K24="Yes",L24="Yes"),"Sufficient",IF(AND(V24>=1,OR(K24="Yes",L24="Yes")),"Thin","Insufficient")) | AJ24: Targets set (1.5°C) | AK24: 2030 | AR24: {=MIN(100, MAX(0, IFERROR(_xlfn.XLOOKUP(AJ24,'Lookup Tables'!$A$2:$A$7,'Lookup Tables'!$B$2:$B$7,0),0) + IF(Z24="Yes", IF(IFERROR(_xlfn.XLOOKUP(AJ24,'Lookup Tables'!$A$2:$A$7,'Lookup Tables'!$B$2:$B$7,0),0)<20, 5, 0), 0) + _xlfn.IFS(AB24="Yes", IF(ISNUMBER(AC24)*AND(AC24<=2030),15,10), AB24="Long-term Only", 5, AB24="No", 0, TRUE, 0) + _xlfn.IFS(AF24="Full",10, AF24="Partial",5, AF24="Scope 2 Only",3, TRUE,0) + _xlfn.IFS(AG24="Yes", IF(ISNUMBER(AH24)*AND(AH24>=5),10,6), AG24="Partial",4, TRUE,0) + _xlfn.IFS(AI24="Yes",5, AI24="Partial (material categories only)",3, TRUE,0) + _xlfn.IFS(AL24="Yes — Detailed",10, AL24="Yes — High Level",5, TRUE,0) + _xlfn.IFS(AM24="Yes — Quantified",15, AM24="Yes — Directional Only",7, TRUE,0) + _xlfn.IFS(AP24="Formal",5, AP24="Referenced",2, TRUE,0) + _xlfn.IFS(AQ24="No Issues Found",5, AQ24="Concern Identified",-5, AQ24="Severe Contradiction",-15, TRUE,0) + _xlfn.IFS(BC24="Reasonable Assurance",5, BC24="Limited Assurance",3, TRUE,0) - IF(AND(Z24="Yes", AI24="No"), 10, 0) - IF(AND(Z24="Yes", AM24="No"), 10, 0) ))} | BE24: {=MIN(100, MAX(0, IFERROR(_xlfn.XLOOKUP(AT24,'Lookup Tables'!$D$2:$D$6,'Lookup Tables'!$E$2:$E$6,0),0) + IFERROR(_xlfn.XLOOKUP(AV24,'Lookup Tables'!$G$2:$G$5,'Lookup Tables'!$H$2:$H$5,0),0) + IFERROR(_xlfn.XLOOKUP(AW24,'Lookup Tables'!$J$2:$J$5,'Lookup Tables'!$K$2:$K$5,0),0) + _xlfn.IFS(AX24="No Issues",10, AX24="Complaint Filed",3, AX24="Confirmed Breach",-15, TRUE,0) + IFERROR(_xlfn.XLOOKUP(AY24,'Lookup Tables'!$M$2:$M$6,'Lookup Tables'!$N$2:$N$6,0),0) + IFERROR(_xlfn.XLOOKUP(AZ24,'Lookup Tables'!$P$2:$P$6,'Lookup Tables'!$Q$2:$Q$6,0),0) + _xlfn.IFS(BA24="Formal Board Committee",5, BA24="Board Oversight Mentioned",2, TRUE,0) + _xlfn.IFS(BB24="Yes — Quantified Targets",5, BB24="Yes — Discretionary Only",2, TRUE,0) + _xlfn.IFS(BC24="Reasonable Assurance",5, BC24="Limited Assurance",3, BC24="Management Review Only",1, TRUE,0) ))} | BS24: {=MIN(100, MAX(0, IFERROR(_xlfn.XLOOKUP(BG24,'Lookup Tables'!$A$11:$A$16,'Lookup Tables'!$B$11:$B$16,0),0) + IFERROR(_xlfn.XLOOKUP(BR24,'Lookup Tables'!$M$11:$M$14,'Lookup Tables'!$N$11:$N$14,0),0) + IFERROR(_xlfn.XLOOKUP(BQ24,'Lookup Tables'!$J$11:$J$15,'Lookup Tables'!$K$11:$K$15,0),0) + IFERROR(_xlfn.XLOOKUP(BH24,'Lookup Tables'!$D$11:$D$15,'Lookup Tables'!$E$11:$E$15,0),0) + IFERROR(_xlfn.XLOOKUP(BJ24,'Lookup Tables'!$G$11:$G$16,'Lookup Tables'!$H$11:$H$16,0),0) + IFERROR(_xlfn.XLOOKUP(BN24,'Lookup Tables'!$P$11:$P$15,'Lookup Tables'!$Q$11:$Q$15,0),0) + _xlfn.IFS(BM24="No Evidence",10, BM24="Unknown",3, BM24="Likely",0, BM24="Confirmed",-10, TRUE,3) + IFERROR(_xlfn.XLOOKUP(BP24,'Lookup Tables'!$J$21:$J$24,'Lookup Tables'!$K$21:$K$24,0),0) ))} | CE24: {=MIN(100, MAX(0, IF(ISNUMBER(BV24)*AND(BV24>0), 10, 0) + _xlfn.IFS(BY24="Independently Verified",25, BY24="Yes",15, TRUE,0) + IFERROR(_xlfn.XLOOKUP(BZ24,'Lookup Tables'!$A$21:$A$24,'Lookup Tables'!$B$21:$B$24,0),0) + IFERROR(_xlfn.XLOOKUP(CA24,'Lookup Tables'!$D$21:$D$24,'Lookup Tables'!$E$21:$E$24,0),0) + _xlfn.IFS(ISNUMBER(CB24)*AND(CB24>=11),15, ISNUMBER(CB24)*AND(CB24>=6),10, ISNUMBER(CB24)*AND(CB24>=1),5, TRUE,0) + IFERROR(_xlfn.XLOOKUP(CC24,'Lookup Tables'!$G$21:$G$25,'Lookup Tables'!$H$21:$H$25,0),0) - IF(ISNUMBER(BW24)*AND(ISNUMBER(BV24))*AND(BW24>BV24), 20, 0) - IF(AND(BY24="Yes", ISNUMBER(BW24), BW24>60), 10, 0) ))} | CG24: reduce our own carbon emissions and aim to achieve climate neutrality by 2040 | CH24: GB25-gesamt-EN_final.pdf | CI24: 6 | CJ24: PASS | CK24: PASS | CL24: PASS | CM24: PASS | CN24: PASS | CO24: PASS | CP24: PASS | CQ24: PASS | CR24: =COUNTIF(CJ24:CQ24,"FAIL") | CS24: =COUNTIF(CJ24:CQ24,"PARTIAL") | CT24: =COUNTIF(CJ24:CQ24,"MISSING") | CU24: =MIN(100, CR24*15 + CS24*6 + CT24*3 + IFERROR(_xlfn.XLOOKUP(CW24,'Lookup Tables'!$M$21:$M$25,'Lookup Tables'!$N$21:$N$25,0),0) ) | CV24: =IFERROR( CHOOSE( MATCH("FAIL",CJ24:CQ24,0), "1-Specificity","2-Metric","3-Baseline","4-Target", "5-Time Horizon","6-Scope","7-Verification","8-Consistency" ), IFERROR( CHOOSE( MATCH("PARTIAL",CJ24:CQ24,0), "1-Specificity","2-Metric","3-Baseline","4-Target", "5-Time Horizon","6-Scope","7-Verification","8-Consistency" ), "No failures" ) ) | DA24: =IF(OR(CU24>=50,CW24="Material",CW24="Severe",AS24="Material",AS24="Severe",BF24="Material",BF24="Severe — Exclusion Trigger",AND(ISNUMBER(BS24),BS24<30)),"Yes","No") | DB24: =IF(OR(CR24>=6,AW24="Confirmed Violation",AX24="Confirmed Breach"),"Yes — Automatic",IF(CW24="Severe","Yes — Requires Captain Confirmation","No")) | DC24: reduce our own carbon emissions and aim to achieve climate neutrality by 2040 | DD24: GB25-gesamt-EN_final.pdf | DE24: 6 | DF24: 4 | DG24: 4 | DH24: PENDING | DL24: =IF(OR(IFERROR(VALUE(LEFT(DF24,1)),99)<=2,IFERROR(VALUE(LEFT(DG24,1)),99)<=2),"Flagged","Clear") | DM24: =IF(OR(DA24="Yes",DB24<>"No",DH24="Unverified",DL24="Flagged"),"Yes","No") | DN24: {=MIN(100, IF(ISNUMBER(V24), _xlfn.IFS(V24>=3,25, V24=2,15, V24=1,5, TRUE,0), 0) + IFERROR(_xlfn.IFS(VALUE(LEFT(DF24,1))=5,25, VALUE(LEFT(DF24,1))=4,20, VALUE(LEFT(DF24,1))=3,15, VALUE(LEFT(DF24,1))=2,8, TRUE,0), 15) + IFERROR(_xlfn.IFS(VALUE(LEFT(DG24,1))=5,25, VALUE(LEFT(DG24,1))=4,20, VALUE(LEFT(DG24,1))=3,15, VALUE(LEFT(DG24,1))=2,8, TRUE,0), 15) + _xlfn.IFS(DH24="Fully Verified",25, DH24="Partially Verified",12, TRUE,0) )} | DO24: {=_xlfn.IFS( ISBLANK(AR24), "Insufficient Evidence", AND(AR24>=65, AJ24="Approved"), "Strong", AR24>=65, "Adequate", AR24>=40, "Adequate", AR24>=20, "Weak", TRUE, "Insufficient Evidence" )} | DP24: {=_xlfn.IFS( ISBLANK(BS24), "Insufficient Evidence", BS24>=65, "Strong", BS24>=40, "Adequate", BS24>=20, "Weak", TRUE, "Insufficient Evidence" )} | DQ24: {=_xlfn.IFS( ISBLANK(BE24), "Insufficient Evidence", OR(AW24="Confirmed Violation", AX24="Confirmed Breach"), "Severe — Hard Trigger", BE24>=65, "Strong", BE24>=40, "Adequate", BE24>=20, "Weak", TRUE, "Insufficient Evidence" )} | DR24: {=_xlfn.IFS( ISBLANK(CU24), "Insufficient Evidence", CU24<=20, "Low Risk", CU24<=50, "Moderate Risk", CU24<=75, "High Risk", TRUE, "Very High Risk" )} | DS24: {=_xlfn.IFS( ISBLANK(CE24), "Insufficient Evidence", AND(ISNUMBER(BW24),ISNUMBER(BV24),BW24>BV24), "Overclaiming Risk", CE24>=65, "Strong", CE24>=40, "Adequate", TRUE, "Weak" )} | DT24: =IF(DB24="Yes — Automatic",0,ROUND((IF(ISNUMBER(AR24),AR24,0)*0.3+IF(ISNUMBER(BS24),BS24,0)*0.2+IF(ISNUMBER(BE24),BE24,0)*0.2+IF(ISNUMBER(CE24),CE24,0)*0.15+(100-IF(ISNUMBER(CU24),CU24,50))*0.15)*IF(DN24>=75,1,IF(DN24>=50,0.9,IF(DN24>=25,0.75,0.6))),1)) | DU24: {=_xlfn.IFS( DV24="Upgraded to Clear", "Clear", DV24="Downgraded to Watchlist", "Watchlist", DV24="Downgraded to Exclusion", "Exclusion Risk", DB24="Yes — Automatic", "Exclusion Risk", OR(AW24="Confirmed Violation", AX24="Confirmed Breach"), "Exclusion Risk", OR(V24=0, ISBLANK(V24), DN24<20), "Insufficient Evidence", AND(DT24>=65, DA24="No", DB24="No"), "Clear", OR(DT24>=40, DA24="Yes"), "Watchlist", TRUE, "Exclusion Risk" )} | DW24: {=_xlfn.IFS( DU24="Exclusion Risk", "Exclude — Hard Trigger", DU24="Insufficient Evidence", "Watchlist — Further Evidence Needed", DU24="Watchlist", "Watchlist — Further Evidence Needed", AND(DU24="Clear", DT24>=80), "Include — No Conditions", DU24="Clear", "Include — Monitor", TRUE, "Watchlist — Further Evidence Needed" )} | DX24: Main claim: "reduce our own carbon emissions and aim to achieve climate neutrality by 2040" (GB25-gesamt-EN_final.pdf, p6). SBTi: Targets set, 1.5°C near-term target (2030). 8-Test: 0 PARTIAL, 0 FAIL, 0 MISSING -> PASS. Utility/grid annual report. Strong climate disclosure — SBTi-validated near-term 2030 targets, climate neutrality by 2040 on a 2019 baseline, full scope coverage, lobbying disclosed. One MED (assurance level). (E.ON's high carbon... | EB24: =IF(OR(V24=0, ISBLANK(V24)), "MISSING — No sources reviewed", "") | EC24: =IF(AND(NOT(ISBLANK(DC24)), ISBLANK(DE24)), "PAGE REF MISSING", "")
A25: NN Group NV | B25: 2NN | C25: =IF(ISBLANK('Universe Tracker'!D21),"",'Universe Tracker'!D21) | F25: =IF(ISBLANK('Universe Tracker'!F21),"",'Universe Tracker'!F21) | G25: =IF(ISBLANK('Universe Tracker'!G21),"",'Universe Tracker'!G21) | J25: =IF(ISBLANK(B25),"",B25&"_"&C25) | Y25: =IF(AND(V25>=2,K25="Yes",L25="Yes"),"Sufficient",IF(AND(V25>=1,OR(K25="Yes",L25="Yes")),"Thin","Insufficient")) | AR25: {=MIN(100, MAX(0, IFERROR(_xlfn.XLOOKUP(AJ25,'Lookup Tables'!$A$2:$A$7,'Lookup Tables'!$B$2:$B$7,0),0) + IF(Z25="Yes", IF(IFERROR(_xlfn.XLOOKUP(AJ25,'Lookup Tables'!$A$2:$A$7,'Lookup Tables'!$B$2:$B$7,0),0)<20, 5, 0), 0) + _xlfn.IFS(AB25="Yes", IF(ISNUMBER(AC25)*AND(AC25<=2030),15,10), AB25="Long-term Only", 5, AB25="No", 0, TRUE, 0) + _xlfn.IFS(AF25="Full",10, AF25="Partial",5, AF25="Scope 2 Only",3, TRUE,0) + _xlfn.IFS(AG25="Yes", IF(ISNUMBER(AH25)*AND(AH25>=5),10,6), AG25="Partial",4, TRUE,0) + _xlfn.IFS(AI25="Yes",5, AI25="Partial (material categories only)",3, TRUE,0) + _xlfn.IFS(AL25="Yes — Detailed",10, AL25="Yes — High Level",5, TRUE,0) + _xlfn.IFS(AM25="Yes — Quantified",15, AM25="Yes — Directional Only",7, TRUE,0) + _xlfn.IFS(AP25="Formal",5, AP25="Referenced",2, TRUE,0) + _xlfn.IFS(AQ25="No Issues Found",5, AQ25="Concern Identified",-5, AQ25="Severe Contradiction",-15, TRUE,0) + _xlfn.IFS(BC25="Reasonable Assurance",5, BC25="Limited Assurance",3, TRUE,0) - IF(AND(Z25="Yes", AI25="No"), 10, 0) - IF(AND(Z25="Yes", AM25="No"), 10, 0) ))} | BE25: {=MIN(100, MAX(0, IFERROR(_xlfn.XLOOKUP(AT25,'Lookup Tables'!$D$2:$D$6,'Lookup Tables'!$E$2:$E$6,0),0) + IFERROR(_xlfn.XLOOKUP(AV25,'Lookup Tables'!$G$2:$G$5,'Lookup Tables'!$H$2:$H$5,0),0) + IFERROR(_xlfn.XLOOKUP(AW25,'Lookup Tables'!$J$2:$J$5,'Lookup Tables'!$K$2:$K$5,0),0) + _xlfn.IFS(AX25="No Issues",10, AX25="Complaint Filed",3, AX25="Confirmed Breach",-15, TRUE,0) + IFERROR(_xlfn.XLOOKUP(AY25,'Lookup Tables'!$M$2:$M$6,'Lookup Tables'!$N$2:$N$6,0),0) + IFERROR(_xlfn.XLOOKUP(AZ25,'Lookup Tables'!$P$2:$P$6,'Lookup Tables'!$Q$2:$Q$6,0),0) + _xlfn.IFS(BA25="Formal Board Committee",5, BA25="Board Oversight Mentioned",2, TRUE,0) + _xlfn.IFS(BB25="Yes — Quantified Targets",5, BB25="Yes — Discretionary Only",2, TRUE,0) + _xlfn.IFS(BC25="Reasonable Assurance",5, BC25="Limited Assurance",3, BC25="Management Review Only",1, TRUE,0) ))} | BS25: {=MIN(100, MAX(0, IFERROR(_xlfn.XLOOKUP(BG25,'Lookup Tables'!$A$11:$A$16,'Lookup Tables'!$B$11:$B$16,0),0) + IFERROR(_xlfn.XLOOKUP(BR25,'Lookup Tables'!$M$11:$M$14,'Lookup Tables'!$N$11:$N$14,0),0) + IFERROR(_xlfn.XLOOKUP(BQ25,'Lookup Tables'!$J$11:$J$15,'Lookup Tables'!$K$11:$K$15,0),0) + IFERROR(_xlfn.XLOOKUP(BH25,'Lookup Tables'!$D$11:$D$15,'Lookup Tables'!$E$11:$E$15,0),0) + IFERROR(_xlfn.XLOOKUP(BJ25,'Lookup Tables'!$G$11:$G$16,'Lookup Tables'!$H$11:$H$16,0),0) + IFERROR(_xlfn.XLOOKUP(BN25,'Lookup Tables'!$P$11:$P$15,'Lookup Tables'!$Q$11:$Q$15,0),0) + _xlfn.IFS(BM25="No Evidence",10, BM25="Unknown",3, BM25="Likely",0, BM25="Confirmed",-10, TRUE,3) + IFERROR(_xlfn.XLOOKUP(BP25,'Lookup Tables'!$J$21:$J$24,'Lookup Tables'!$K$21:$K$24,0),0) ))} | CE25: {=MIN(100, MAX(0, IF(ISNUMBER(BV25)*AND(BV25>0), 10, 0) + _xlfn.IFS(BY25="Independently Verified",25, BY25="Yes",15, TRUE,0) + IFERROR(_xlfn.XLOOKUP(BZ25,'Lookup Tables'!$A$21:$A$24,'Lookup Tables'!$B$21:$B$24,0),0) + IFERROR(_xlfn.XLOOKUP(CA25,'Lookup Tables'!$D$21:$D$24,'Lookup Tables'!$E$21:$E$24,0),0) + _xlfn.IFS(ISNUMBER(CB25)*AND(CB25>=11),15, ISNUMBER(CB25)*AND(CB25>=6),10, ISNUMBER(CB25)*AND(CB25>=1),5, TRUE,0) + IFERROR(_xlfn.XLOOKUP(CC25,'Lookup Tables'!$G$21:$G$25,'Lookup Tables'!$H$21:$H$25,0),0) - IF(ISNUMBER(BW25)*AND(ISNUMBER(BV25))*AND(BW25>BV25), 20, 0) - IF(AND(BY25="Yes", ISNUMBER(BW25), BW25>60), 10, 0) ))} | CR25: =COUNTIF(CJ25:CQ25,"FAIL") | CS25: =COUNTIF(CJ25:CQ25,"PARTIAL") | CT25: =COUNTIF(CJ25:CQ25,"MISSING") | CU25: =MIN(100, CR25*15 + CS25*6 + CT25*3 + IFERROR(_xlfn.XLOOKUP(CW25,'Lookup Tables'!$M$21:$M$25,'Lookup Tables'!$N$21:$N$25,0),0) ) | CV25: =IFERROR( CHOOSE( MATCH("FAIL",CJ25:CQ25,0), "1-Specificity","2-Metric","3-Baseline","4-Target", "5-Time Horizon","6-Scope","7-Verification","8-Consistency" ), IFERROR( CHOOSE( MATCH("PARTIAL",CJ25:CQ25,0), "1-Specificity","2-Metric","3-Baseline","4-Target", "5-Time Horizon","6-Scope","7-Verification","8-Consistency" ), "No failures" ) ) | DA25: =IF(OR(CU25>=50,CW25="Material",CW25="Severe",AS25="Material",AS25="Severe",BF25="Material",BF25="Severe — Exclusion Trigger",AND(ISNUMBER(BS25),BS25<30)),"Yes","No") | DB25: =IF(OR(CR25>=6,AW25="Confirmed Violation",AX25="Confirmed Breach"),"Yes — Automatic",IF(CW25="Severe","Yes — Requires Captain Confirmation","No")) | DL25: =IF(OR(IFERROR(VALUE(LEFT(DF25,1)),99)<=2,IFERROR(VALUE(LEFT(DG25,1)),99)<=2),"Flagged","Clear") | DM25: =IF(OR(DA25="Yes",DB25<>"No",DH25="Unverified",DL25="Flagged"),"Yes","No") | DN25: {=MIN(100, IF(ISNUMBER(V25), _xlfn.IFS(V25>=3,25, V25=2,15, V25=1,5, TRUE,0), 0) + IFERROR(_xlfn.IFS(VALUE(LEFT(DF25,1))=5,25, VALUE(LEFT(DF25,1))=4,20, VALUE(LEFT(DF25,1))=3,15, VALUE(LEFT(DF25,1))=2,8, TRUE,0), 15) + IFERROR(_xlfn.IFS(VALUE(LEFT(DG25,1))=5,25, VALUE(LEFT(DG25,1))=4,20, VALUE(LEFT(DG25,1))=3,15, VALUE(LEFT(DG25,1))=2,8, TRUE,0), 15) + _xlfn.IFS(DH25="Fully Verified",25, DH25="Partially Verified",12, TRUE,0) )} | DO25: {=_xlfn.IFS( ISBLANK(AR25), "Insufficient Evidence", AND(AR25>=65, AJ25="Approved"), "Strong", AR25>=65, "Adequate", AR25>=40, "Adequate", AR25>=20, "Weak", TRUE, "Insufficient Evidence" )} | DP25: {=_xlfn.IFS( ISBLANK(BS25), "Insufficient Evidence", BS25>=65, "Strong", BS25>=40, "Adequate", BS25>=20, "Weak", TRUE, "Insufficient Evidence" )} | DQ25: {=_xlfn.IFS( ISBLANK(BE25), "Insufficient Evidence", OR(AW25="Confirmed Violation", AX25="Confirmed Breach"), "Severe — Hard Trigger", BE25>=65, "Strong", BE25>=40, "Adequate", BE25>=20, "Weak", TRUE, "Insufficient Evidence" )} | DR25: {=_xlfn.IFS( ISBLANK(CU25), "Insufficient Evidence", CU25<=20, "Low Risk", CU25<=50, "Moderate Risk", CU25<=75, "High Risk", TRUE, "Very High Risk" )} | DS25: {=_xlfn.IFS( ISBLANK(CE25), "Insufficient Evidence", AND(ISNUMBER(BW25),ISNUMBER(BV25),BW25>BV25), "Overclaiming Risk", CE25>=65, "Strong", CE25>=40, "Adequate", TRUE, "Weak" )} | DT25: =IF(DB25="Yes — Automatic",0,ROUND((IF(ISNUMBER(AR25),AR25,0)*0.3+IF(ISNUMBER(BS25),BS25,0)*0.2+IF(ISNUMBER(BE25),BE25,0)*0.2+IF(ISNUMBER(CE25),CE25,0)*0.15+(100-IF(ISNUMBER(CU25),CU25,50))*0.15)*IF(DN25>=75,1,IF(DN25>=50,0.9,IF(DN25>=25,0.75,0.6))),1)) | DU25: {=_xlfn.IFS( DV25="Upgraded to Clear", "Clear", DV25="Downgraded to Watchlist", "Watchlist", DV25="Downgraded to Exclusion", "Exclusion Risk", DB25="Yes — Automatic", "Exclusion Risk", OR(AW25="Confirmed Violation", AX25="Confirmed Breach"), "Exclusion Risk", OR(V25=0, ISBLANK(V25), DN25<20), "Insufficient Evidence", AND(DT25>=65, DA25="No", DB25="No"), "Clear", OR(DT25>=40, DA25="Yes"), "Watchlist", TRUE, "Exclusion Risk" )} | DW25: {=_xlfn.IFS( DU25="Exclusion Risk", "Exclude — Hard Trigger", DU25="Insufficient Evidence", "Watchlist — Further Evidence Needed", DU25="Watchlist", "Watchlist — Further Evidence Needed", AND(DU25="Clear", DT25>=80), "Include — No Conditions", DU25="Clear", "Include — Monitor", TRUE, "Watchlist — Further Evidence Needed" )} | EB25: =IF(OR(V25=0, ISBLANK(V25)), "MISSING — No sources reviewed", "") | EC25: =IF(AND(NOT(ISBLANK(DC25)), ISBLANK(DE25)), "PAGE REF MISSING", "")
A26: Orion Oyj | B26: OFK | C26: FI0009014377 | F26: =IF(ISBLANK('Universe Tracker'!F22),"",'Universe Tracker'!F22) | G26: =IF(ISBLANK('Universe Tracker'!G22),"",'Universe Tracker'!G22) | J26: =IF(ISBLANK(B26),"",B26&"_"&C26) | O26: Yes | P26: Yes | Y26: =IF(AND(V26>=2,K26="Yes",L26="Yes"),"Sufficient",IF(AND(V26>=1,OR(K26="Yes",L26="Yes")),"Thin","Insufficient")) | AJ26: Targets set (1.5°C) | AK26: 2030 | AR26: {=MIN(100, MAX(0, IFERROR(_xlfn.XLOOKUP(AJ26,'Lookup Tables'!$A$2:$A$7,'Lookup Tables'!$B$2:$B$7,0),0) + IF(Z26="Yes", IF(IFERROR(_xlfn.XLOOKUP(AJ26,'Lookup Tables'!$A$2:$A$7,'Lookup Tables'!$B$2:$B$7,0),0)<20, 5, 0), 0) + _xlfn.IFS(AB26="Yes", IF(ISNUMBER(AC26)*AND(AC26<=2030),15,10), AB26="Long-term Only", 5, AB26="No", 0, TRUE, 0) + _xlfn.IFS(AF26="Full",10, AF26="Partial",5, AF26="Scope 2 Only",3, TRUE,0) + _xlfn.IFS(AG26="Yes", IF(ISNUMBER(AH26)*AND(AH26>=5),10,6), AG26="Partial",4, TRUE,0) + _xlfn.IFS(AI26="Yes",5, AI26="Partial (material categories only)",3, TRUE,0) + _xlfn.IFS(AL26="Yes — Detailed",10, AL26="Yes — High Level",5, TRUE,0) + _xlfn.IFS(AM26="Yes — Quantified",15, AM26="Yes — Directional Only",7, TRUE,0) + _xlfn.IFS(AP26="Formal",5, AP26="Referenced",2, TRUE,0) + _xlfn.IFS(AQ26="No Issues Found",5, AQ26="Concern Identified",-5, AQ26="Severe Contradiction",-15, TRUE,0) + _xlfn.IFS(BC26="Reasonable Assurance",5, BC26="Limited Assurance",3, TRUE,0) - IF(AND(Z26="Yes", AI26="No"), 10, 0) - IF(AND(Z26="Yes", AM26="No"), 10, 0) ))} | BE26: {=MIN(100, MAX(0, IFERROR(_xlfn.XLOOKUP(AT26,'Lookup Tables'!$D$2:$D$6,'Lookup Tables'!$E$2:$E$6,0),0) + IFERROR(_xlfn.XLOOKUP(AV26,'Lookup Tables'!$G$2:$G$5,'Lookup Tables'!$H$2:$H$5,0),0) + IFERROR(_xlfn.XLOOKUP(AW26,'Lookup Tables'!$J$2:$J$5,'Lookup Tables'!$K$2:$K$5,0),0) + _xlfn.IFS(AX26="No Issues",10, AX26="Complaint Filed",3, AX26="Confirmed Breach",-15, TRUE,0) + IFERROR(_xlfn.XLOOKUP(AY26,'Lookup Tables'!$M$2:$M$6,'Lookup Tables'!$N$2:$N$6,0),0) + IFERROR(_xlfn.XLOOKUP(AZ26,'Lookup Tables'!$P$2:$P$6,'Lookup Tables'!$Q$2:$Q$6,0),0) + _xlfn.IFS(BA26="Formal Board Committee",5, BA26="Board Oversight Mentioned",2, TRUE,0) + _xlfn.IFS(BB26="Yes — Quantified Targets",5, BB26="Yes — Discretionary Only",2, TRUE,0) + _xlfn.IFS(BC26="Reasonable Assurance",5, BC26="Limited Assurance",3, BC26="Management Review Only",1, TRUE,0) ))} | BS26: {=MIN(100, MAX(0, IFERROR(_xlfn.XLOOKUP(BG26,'Lookup Tables'!$A$11:$A$16,'Lookup Tables'!$B$11:$B$16,0),0) + IFERROR(_xlfn.XLOOKUP(BR26,'Lookup Tables'!$M$11:$M$14,'Lookup Tables'!$N$11:$N$14,0),0) + IFERROR(_xlfn.XLOOKUP(BQ26,'Lookup Tables'!$J$11:$J$15,'Lookup Tables'!$K$11:$K$15,0),0) + IFERROR(_xlfn.XLOOKUP(BH26,'Lookup Tables'!$D$11:$D$15,'Lookup Tables'!$E$11:$E$15,0),0) + IFERROR(_xlfn.XLOOKUP(BJ26,'Lookup Tables'!$G$11:$G$16,'Lookup Tables'!$H$11:$H$16,0),0) + IFERROR(_xlfn.XLOOKUP(BN26,'Lookup Tables'!$P$11:$P$15,'Lookup Tables'!$Q$11:$Q$15,0),0) + _xlfn.IFS(BM26="No Evidence",10, BM26="Unknown",3, BM26="Likely",0, BM26="Confirmed",-10, TRUE,3) + IFERROR(_xlfn.XLOOKUP(BP26,'Lookup Tables'!$J$21:$J$24,'Lookup Tables'!$K$21:$K$24,0),0) ))} | CE26: {=MIN(100, MAX(0, IF(ISNUMBER(BV26)*AND(BV26>0), 10, 0) + _xlfn.IFS(BY26="Independently Verified",25, BY26="Yes",15, TRUE,0) + IFERROR(_xlfn.XLOOKUP(BZ26,'Lookup Tables'!$A$21:$A$24,'Lookup Tables'!$B$21:$B$24,0),0) + IFERROR(_xlfn.XLOOKUP(CA26,'Lookup Tables'!$D$21:$D$24,'Lookup Tables'!$E$21:$E$24,0),0) + _xlfn.IFS(ISNUMBER(CB26)*AND(CB26>=11),15, ISNUMBER(CB26)*AND(CB26>=6),10, ISNUMBER(CB26)*AND(CB26>=1),5, TRUE,0) + IFERROR(_xlfn.XLOOKUP(CC26,'Lookup Tables'!$G$21:$G$25,'Lookup Tables'!$H$21:$H$25,0),0) - IF(ISNUMBER(BW26)*AND(ISNUMBER(BV26))*AND(BW26>BV26), 20, 0) - IF(AND(BY26="Yes", ISNUMBER(BW26), BW26>60), 10, 0) ))} | CG26: Orion has committed to reach net-zero emissions by 2050 | CH26: orion-financial-statement-documents-2025-2.pdf | CI26: 63 | CJ26: PASS | CK26: PASS | CL26: PASS | CM26: PASS | CN26: PASS | CO26: PASS | CP26: PASS | CQ26: PASS | CR26: =COUNTIF(CJ26:CQ26,"FAIL") | CS26: =COUNTIF(CJ26:CQ26,"PARTIAL") | CT26: =COUNTIF(CJ26:CQ26,"MISSING") | CU26: =MIN(100, CR26*15 + CS26*6 + CT26*3 + IFERROR(_xlfn.XLOOKUP(CW26,'Lookup Tables'!$M$21:$M$25,'Lookup Tables'!$N$21:$N$25,0),0) ) | CV26: =IFERROR( CHOOSE( MATCH("FAIL",CJ26:CQ26,0), "1-Specificity","2-Metric","3-Baseline","4-Target", "5-Time Horizon","6-Scope","7-Verification","8-Consistency" ), IFERROR( CHOOSE( MATCH("PARTIAL",CJ26:CQ26,0), "1-Specificity","2-Metric","3-Baseline","4-Target", "5-Time Horizon","6-Scope","7-Verification","8-Consistency" ), "No failures" ) ) | DA26: =IF(OR(CU26>=50,CW26="Material",CW26="Severe",AS26="Material",AS26="Severe",BF26="Material",BF26="Severe — Exclusion Trigger",AND(ISNUMBER(BS26),BS26<30)),"Yes","No") | DB26: =IF(OR(CR26>=6,AW26="Confirmed Violation",AX26="Confirmed Breach"),"Yes — Automatic",IF(CW26="Severe","Yes — Requires Captain Confirmation","No")) | DC26: Orion has committed to reach net-zero emissions by 2050 | DD26: orion-financial-statement-documents-2025-2.pdf | DE26: 63 | DF26: 4 | DG26: 4 | DH26: PENDING | DL26: =IF(OR(IFERROR(VALUE(LEFT(DF26,1)),99)<=2,IFERROR(VALUE(LEFT(DG26,1)),99)<=2),"Flagged","Clear") | DM26: =IF(OR(DA26="Yes",DB26<>"No",DH26="Unverified",DL26="Flagged"),"Yes","No") | DN26: {=MIN(100, IF(ISNUMBER(V26), _xlfn.IFS(V26>=3,25, V26=2,15, V26=1,5, TRUE,0), 0) + IFERROR(_xlfn.IFS(VALUE(LEFT(DF26,1))=5,25, VALUE(LEFT(DF26,1))=4,20, VALUE(LEFT(DF26,1))=3,15, VALUE(LEFT(DF26,1))=2,8, TRUE,0), 15) + IFERROR(_xlfn.IFS(VALUE(LEFT(DG26,1))=5,25, VALUE(LEFT(DG26,1))=4,20, VALUE(LEFT(DG26,1))=3,15, VALUE(LEFT(DG26,1))=2,8, TRUE,0), 15) + _xlfn.IFS(DH26="Fully Verified",25, DH26="Partially Verified",12, TRUE,0) )} | DO26: {=_xlfn.IFS( ISBLANK(AR26), "Insufficient Evidence", AND(AR26>=65, AJ26="Approved"), "Strong", AR26>=65, "Adequate", AR26>=40, "Adequate", AR26>=20, "Weak", TRUE, "Insufficient Evidence" )} | DP26: {=_xlfn.IFS( ISBLANK(BS26), "Insufficient Evidence", BS26>=65, "Strong", BS26>=40, "Adequate", BS26>=20, "Weak", TRUE, "Insufficient Evidence" )} | DQ26: {=_xlfn.IFS( ISBLANK(BE26), "Insufficient Evidence", OR(AW26="Confirmed Violation", AX26="Confirmed Breach"), "Severe — Hard Trigger", BE26>=65, "Strong", BE26>=40, "Adequate", BE26>=20, "Weak", TRUE, "Insufficient Evidence" )} | DR26: {=_xlfn.IFS( ISBLANK(CU26), "Insufficient Evidence", CU26<=20, "Low Risk", CU26<=50, "Moderate Risk", CU26<=75, "High Risk", TRUE, "Very High Risk" )} | DS26: {=_xlfn.IFS( ISBLANK(CE26), "Insufficient Evidence", AND(ISNUMBER(BW26),ISNUMBER(BV26),BW26>BV26), "Overclaiming Risk", CE26>=65, "Strong", CE26>=40, "Adequate", TRUE, "Weak" )} | DT26: =IF(DB26="Yes — Automatic",0,ROUND((IF(ISNUMBER(AR26),AR26,0)*0.3+IF(ISNUMBER(BS26),BS26,0)*0.2+IF(ISNUMBER(BE26),BE26,0)*0.2+IF(ISNUMBER(CE26),CE26,0)*0.15+(100-IF(ISNUMBER(CU26),CU26,50))*0.15)*IF(DN26>=75,1,IF(DN26>=50,0.9,IF(DN26>=25,0.75,0.6))),1)) | DU26: {=_xlfn.IFS( DV26="Upgraded to Clear", "Clear", DV26="Downgraded to Watchlist", "Watchlist", DV26="Downgraded to Exclusion", "Exclusion Risk", DB26="Yes — Automatic", "Exclusion Risk", OR(AW26="Confirmed Violation", AX26="Confirmed Breach"), "Exclusion Risk", OR(V26=0, ISBLANK(V26), DN26<20), "Insufficient Evidence", AND(DT26>=65, DA26="No", DB26="No"), "Clear", OR(DT26>=40, DA26="Yes"), "Watchlist", TRUE, "Exclusion Risk" )} | DW26: {=_xlfn.IFS( DU26="Exclusion Risk", "Exclude — Hard Trigger", DU26="Insufficient Evidence", "Watchlist — Further Evidence Needed", DU26="Watchlist", "Watchlist — Further Evidence Needed", AND(DU26="Clear", DT26>=80), "Include — No Conditions", DU26="Clear", "Include — Monitor", TRUE, "Watchlist — Further Evidence Needed" )} | DX26: Main claim: "Orion has committed to reach net-zero emissions by 2050" (orion-financial-statement-documents-2025-2.pdf, p63). SBTi: Targets set, 1.5°C near-term target (2030). 8-Test: 0 PARTIAL, 0 FAIL, 0 MISSING -> PASS. Source is the CSRD sustainability statement within Orion's financial-statement documents. SBTi-approved 70%-by-2030 target, explicit 2023 baseline, full scope coverage, limited assurance. One MED (assurance level). | EB26: =IF(OR(V26=0, ISBLANK(V26)), "MISSING — No sources reviewed", "") | EC26: =IF(AND(NOT(ISBLANK(DC26)), ISBLANK(DE26)), "PAGE REF MISSING", "")
A27: Balfour Beatty PLC | B27: BIH | C27: =IF(ISBLANK('Universe Tracker'!D23),"",'Universe Tracker'!D23) | F27: =IF(ISBLANK('Universe Tracker'!F23),"",'Universe Tracker'!F23) | G27: =IF(ISBLANK('Universe Tracker'!G23),"",'Universe Tracker'!G23) | J27: =IF(ISBLANK(B27),"",B27&"_"&C27) | Y27: =IF(AND(V27>=2,K27="Yes",L27="Yes"),"Sufficient",IF(AND(V27>=1,OR(K27="Yes",L27="Yes")),"Thin","Insufficient")) | AR27: {=MIN(100, MAX(0, IFERROR(_xlfn.XLOOKUP(AJ27,'Lookup Tables'!$A$2:$A$7,'Lookup Tables'!$B$2:$B$7,0),0) + IF(Z27="Yes", IF(IFERROR(_xlfn.XLOOKUP(AJ27,'Lookup Tables'!$A$2:$A$7,'Lookup Tables'!$B$2:$B$7,0),0)<20, 5, 0), 0) + _xlfn.IFS(AB27="Yes", IF(ISNUMBER(AC27)*AND(AC27<=2030),15,10), AB27="Long-term Only", 5, AB27="No", 0, TRUE, 0) + _xlfn.IFS(AF27="Full",10, AF27="Partial",5, AF27="Scope 2 Only",3, TRUE,0) + _xlfn.IFS(AG27="Yes", IF(ISNUMBER(AH27)*AND(AH27>=5),10,6), AG27="Partial",4, TRUE,0) + _xlfn.IFS(AI27="Yes",5, AI27="Partial (material categories only)",3, TRUE,0) + _xlfn.IFS(AL27="Yes — Detailed",10, AL27="Yes — High Level",5, TRUE,0) + _xlfn.IFS(AM27="Yes — Quantified",15, AM27="Yes — Directional Only",7, TRUE,0) + _xlfn.IFS(AP27="Formal",5, AP27="Referenced",2, TRUE,0) + _xlfn.IFS(AQ27="No Issues Found",5, AQ27="Concern Identified",-5, AQ27="Severe Contradiction",-15, TRUE,0) + _xlfn.IFS(BC27="Reasonable Assurance",5, BC27="Limited Assurance",3, TRUE,0) - IF(AND(Z27="Yes", AI27="No"), 10, 0) - IF(AND(Z27="Yes", AM27="No"), 10, 0) ))} | BE27: {=MIN(100, MAX(0, IFERROR(_xlfn.XLOOKUP(AT27,'Lookup Tables'!$D$2:$D$6,'Lookup Tables'!$E$2:$E$6,0),0) + IFERROR(_xlfn.XLOOKUP(AV27,'Lookup Tables'!$G$2:$G$5,'Lookup Tables'!$H$2:$H$5,0),0) + IFERROR(_xlfn.XLOOKUP(AW27,'Lookup Tables'!$J$2:$J$5,'Lookup Tables'!$K$2:$K$5,0),0) + _xlfn.IFS(AX27="No Issues",10, AX27="Complaint Filed",3, AX27="Confirmed Breach",-15, TRUE,0) + IFERROR(_xlfn.XLOOKUP(AY27,'Lookup Tables'!$M$2:$M$6,'Lookup Tables'!$N$2:$N$6,0),0) + IFERROR(_xlfn.XLOOKUP(AZ27,'Lookup Tables'!$P$2:$P$6,'Lookup Tables'!$Q$2:$Q$6,0),0) + _xlfn.IFS(BA27="Formal Board Committee",5, BA27="Board Oversight Mentioned",2, TRUE,0) + _xlfn.IFS(BB27="Yes — Quantified Targets",5, BB27="Yes — Discretionary Only",2, TRUE,0) + _xlfn.IFS(BC27="Reasonable Assurance",5, BC27="Limited Assurance",3, BC27="Management Review Only",1, TRUE,0) ))} | BS27: {=MIN(100, MAX(0, IFERROR(_xlfn.XLOOKUP(BG27,'Lookup Tables'!$A$11:$A$16,'Lookup Tables'!$B$11:$B$16,0),0) + IFERROR(_xlfn.XLOOKUP(BR27,'Lookup Tables'!$M$11:$M$14,'Lookup Tables'!$N$11:$N$14,0),0) + IFERROR(_xlfn.XLOOKUP(BQ27,'Lookup Tables'!$J$11:$J$15,'Lookup Tables'!$K$11:$K$15,0),0) + IFERROR(_xlfn.XLOOKUP(BH27,'Lookup Tables'!$D$11:$D$15,'Lookup Tables'!$E$11:$E$15,0),0) + IFERROR(_xlfn.XLOOKUP(BJ27,'Lookup Tables'!$G$11:$G$16,'Lookup Tables'!$H$11:$H$16,0),0) + IFERROR(_xlfn.XLOOKUP(BN27,'Lookup Tables'!$P$11:$P$15,'Lookup Tables'!$Q$11:$Q$15,0),0) + _xlfn.IFS(BM27="No Evidence",10, BM27="Unknown",3, BM27="Likely",0, BM27="Confirmed",-10, TRUE,3) + IFERROR(_xlfn.XLOOKUP(BP27,'Lookup Tables'!$J$21:$J$24,'Lookup Tables'!$K$21:$K$24,0),0) ))} | CE27: {=MIN(100, MAX(0, IF(ISNUMBER(BV27)*AND(BV27>0), 10, 0) + _xlfn.IFS(BY27="Independently Verified",25, BY27="Yes",15, TRUE,0) + IFERROR(_xlfn.XLOOKUP(BZ27,'Lookup Tables'!$A$21:$A$24,'Lookup Tables'!$B$21:$B$24,0),0) + IFERROR(_xlfn.XLOOKUP(CA27,'Lookup Tables'!$D$21:$D$24,'Lookup Tables'!$E$21:$E$24,0),0) + _xlfn.IFS(ISNUMBER(CB27)*AND(CB27>=11),15, ISNUMBER(CB27)*AND(CB27>=6),10, ISNUMBER(CB27)*AND(CB27>=1),5, TRUE,0) + IFERROR(_xlfn.XLOOKUP(CC27,'Lookup Tables'!$G$21:$G$25,'Lookup Tables'!$H$21:$H$25,0),0) - IF(ISNUMBER(BW27)*AND(ISNUMBER(BV27))*AND(BW27>BV27), 20, 0) - IF(AND(BY27="Yes", ISNUMBER(BW27), BW27>60), 10, 0) ))} | CR27: =COUNTIF(CJ27:CQ27,"FAIL") | CS27: =COUNTIF(CJ27:CQ27,"PARTIAL") | CT27: =COUNTIF(CJ27:CQ27,"MISSING") | CU27: =MIN(100, CR27*15 + CS27*6 + CT27*3 + IFERROR(_xlfn.XLOOKUP(CW27,'Lookup Tables'!$M$21:$M$25,'Lookup Tables'!$N$21:$N$25,0),0) ) | CV27: =IFERROR( CHOOSE( MATCH("FAIL",CJ27:CQ27,0), "1-Specificity","2-Metric","3-Baseline","4-Target", "5-Time Horizon","6-Scope","7-Verification","8-Consistency" ), IFERROR( CHOOSE( MATCH("PARTIAL",CJ27:CQ27,0), "1-Specificity","2-Metric","3-Baseline","4-Target", "5-Time Horizon","6-Scope","7-Verification","8-Consistency" ), "No failures" ) ) | DA27: =IF(OR(CU27>=50,CW27="Material",CW27="Severe",AS27="Material",AS27="Severe",BF27="Material",BF27="Severe — Exclusion Trigger",AND(ISNUMBER(BS27),BS27<30)),"Yes","No") | DB27: =IF(OR(CR27>=6,AW27="Confirmed Violation",AX27="Confirmed Breach"),"Yes — Automatic",IF(CW27="Severe","Yes — Requires Captain Confirmation","No")) | DL27: =IF(OR(IFERROR(VALUE(LEFT(DF27,1)),99)<=2,IFERROR(VALUE(LEFT(DG27,1)),99)<=2),"Flagged","Clear") | DM27: =IF(OR(DA27="Yes",DB27<>"No",DH27="Unverified",DL27="Flagged"),"Yes","No") | DN27: {=MIN(100, IF(ISNUMBER(V27), _xlfn.IFS(V27>=3,25, V27=2,15, V27=1,5, TRUE,0), 0) + IFERROR(_xlfn.IFS(VALUE(LEFT(DF27,1))=5,25, VALUE(LEFT(DF27,1))=4,20, VALUE(LEFT(DF27,1))=3,15, VALUE(LEFT(DF27,1))=2,8, TRUE,0), 15) + IFERROR(_xlfn.IFS(VALUE(LEFT(DG27,1))=5,25, VALUE(LEFT(DG27,1))=4,20, VALUE(LEFT(DG27,1))=3,15, VALUE(LEFT(DG27,1))=2,8, TRUE,0), 15) + _xlfn.IFS(DH27="Fully Verified",25, DH27="Partially Verified",12, TRUE,0) )} | DO27: {=_xlfn.IFS( ISBLANK(AR27), "Insufficient Evidence", AND(AR27>=65, AJ27="Approved"), "Strong", AR27>=65, "Adequate", AR27>=40, "Adequate", AR27>=20, "Weak", TRUE, "Insufficient Evidence" )} | DP27: {=_xlfn.IFS( ISBLANK(BS27), "Insufficient Evidence", BS27>=65, "Strong", BS27>=40, "Adequate", BS27>=20, "Weak", TRUE, "Insufficient Evidence" )} | DQ27: {=_xlfn.IFS( ISBLANK(BE27), "Insufficient Evidence", OR(AW27="Confirmed Violation", AX27="Confirmed Breach"), "Severe — Hard Trigger", BE27>=65, "Strong", BE27>=40, "Adequate", BE27>=20, "Weak", TRUE, "Insufficient Evidence" )} | DR27: {=_xlfn.IFS( ISBLANK(CU27), "Insufficient Evidence", CU27<=20, "Low Risk", CU27<=50, "Moderate Risk", CU27<=75, "High Risk", TRUE, "Very High Risk" )} | DS27: {=_xlfn.IFS( ISBLANK(CE27), "Insufficient Evidence", AND(ISNUMBER(BW27),ISNUMBER(BV27),BW27>BV27), "Overclaiming Risk", CE27>=65, "Strong", CE27>=40, "Adequate", TRUE, "Weak" )} | DT27: =IF(DB27="Yes — Automatic",0,ROUND((IF(ISNUMBER(AR27),AR27,0)*0.3+IF(ISNUMBER(BS27),BS27,0)*0.2+IF(ISNUMBER(BE27),BE27,0)*0.2+IF(ISNUMBER(CE27),CE27,0)*0.15+(100-IF(ISNUMBER(CU27),CU27,50))*0.15)*IF(DN27>=75,1,IF(DN27>=50,0.9,IF(DN27>=25,0.75,0.6))),1)) | DU27: {=_xlfn.IFS( DV27="Upgraded to Clear", "Clear", DV27="Downgraded to Watchlist", "Watchlist", DV27="Downgraded to Exclusion", "Exclusion Risk", DB27="Yes — Automatic", "Exclusion Risk", OR(AW27="Confirmed Violation", AX27="Confirmed Breach"), "Exclusion Risk", OR(V27=0, ISBLANK(V27), DN27<20), "Insufficient Evidence", AND(DT27>=65, DA27="No", DB27="No"), "Clear", OR(DT27>=40, DA27="Yes"), "Watchlist", TRUE, "Exclusion Risk" )} | DW27: {=_xlfn.IFS( DU27="Exclusion Risk", "Exclude — Hard Trigger", DU27="Insufficient Evidence", "Watchlist — Further Evidence Needed", DU27="Watchlist", "Watchlist — Further Evidence Needed", AND(DU27="Clear", DT27>=80), "Include — No Conditions", DU27="Clear", "Include — Monitor", TRUE, "Watchlist — Further Evidence Needed" )} | EB27: =IF(OR(V27=0, ISBLANK(V27)), "MISSING — No sources reviewed", "") | EC27: =IF(AND(NOT(ISBLANK(DC27)), ISBLANK(DE27)), "PAGE REF MISSING", "")
A28: UCB SA | B28: UNC | C28: BE0003739530 | F28: =IF(ISBLANK('Universe Tracker'!F24),"",'Universe Tracker'!F24) | G28: =IF(ISBLANK('Universe Tracker'!G24),"",'Universe Tracker'!G24) | J28: =IF(ISBLANK(B28),"",B28&"_"&C28) | O28: Yes | P28: Yes | Y28: =IF(AND(V28>=2,K28="Yes",L28="Yes"),"Sufficient",IF(AND(V28>=1,OR(K28="Yes",L28="Yes")),"Thin","Insufficient")) | AJ28: Targets set (1.5°C) | AK28: 2030 | AR28: {=MIN(100, MAX(0, IFERROR(_xlfn.XLOOKUP(AJ28,'Lookup Tables'!$A$2:$A$7,'Lookup Tables'!$B$2:$B$7,0),0) + IF(Z28="Yes", IF(IFERROR(_xlfn.XLOOKUP(AJ28,'Lookup Tables'!$A$2:$A$7,'Lookup Tables'!$B$2:$B$7,0),0)<20, 5, 0), 0) + _xlfn.IFS(AB28="Yes", IF(ISNUMBER(AC28)*AND(AC28<=2030),15,10), AB28="Long-term Only", 5, AB28="No", 0, TRUE, 0) + _xlfn.IFS(AF28="Full",10, AF28="Partial",5, AF28="Scope 2 Only",3, TRUE,0) + _xlfn.IFS(AG28="Yes", IF(ISNUMBER(AH28)*AND(AH28>=5),10,6), AG28="Partial",4, TRUE,0) + _xlfn.IFS(AI28="Yes",5, AI28="Partial (material categories only)",3, TRUE,0) + _xlfn.IFS(AL28="Yes — Detailed",10, AL28="Yes — High Level",5, TRUE,0) + _xlfn.IFS(AM28="Yes — Quantified",15, AM28="Yes — Directional Only",7, TRUE,0) + _xlfn.IFS(AP28="Formal",5, AP28="Referenced",2, TRUE,0) + _xlfn.IFS(AQ28="No Issues Found",5, AQ28="Concern Identified",-5, AQ28="Severe Contradiction",-15, TRUE,0) + _xlfn.IFS(BC28="Reasonable Assurance",5, BC28="Limited Assurance",3, TRUE,0) - IF(AND(Z28="Yes", AI28="No"), 10, 0) - IF(AND(Z28="Yes", AM28="No"), 10, 0) ))} | BE28: {=MIN(100, MAX(0, IFERROR(_xlfn.XLOOKUP(AT28,'Lookup Tables'!$D$2:$D$6,'Lookup Tables'!$E$2:$E$6,0),0) + IFERROR(_xlfn.XLOOKUP(AV28,'Lookup Tables'!$G$2:$G$5,'Lookup Tables'!$H$2:$H$5,0),0) + IFERROR(_xlfn.XLOOKUP(AW28,'Lookup Tables'!$J$2:$J$5,'Lookup Tables'!$K$2:$K$5,0),0) + _xlfn.IFS(AX28="No Issues",10, AX28="Complaint Filed",3, AX28="Confirmed Breach",-15, TRUE,0) + IFERROR(_xlfn.XLOOKUP(AY28,'Lookup Tables'!$M$2:$M$6,'Lookup Tables'!$N$2:$N$6,0),0) + IFERROR(_xlfn.XLOOKUP(AZ28,'Lookup Tables'!$P$2:$P$6,'Lookup Tables'!$Q$2:$Q$6,0),0) + _xlfn.IFS(BA28="Formal Board Committee",5, BA28="Board Oversight Mentioned",2, TRUE,0) + _xlfn.IFS(BB28="Yes — Quantified Targets",5, BB28="Yes — Discretionary Only",2, TRUE,0) + _xlfn.IFS(BC28="Reasonable Assurance",5, BC28="Limited Assurance",3, BC28="Management Review Only",1, TRUE,0) ))} | BS28: {=MIN(100, MAX(0, IFERROR(_xlfn.XLOOKUP(BG28,'Lookup Tables'!$A$11:$A$16,'Lookup Tables'!$B$11:$B$16,0),0) + IFERROR(_xlfn.XLOOKUP(BR28,'Lookup Tables'!$M$11:$M$14,'Lookup Tables'!$N$11:$N$14,0),0) + IFERROR(_xlfn.XLOOKUP(BQ28,'Lookup Tables'!$J$11:$J$15,'Lookup Tables'!$K$11:$K$15,0),0) + IFERROR(_xlfn.XLOOKUP(BH28,'Lookup Tables'!$D$11:$D$15,'Lookup Tables'!$E$11:$E$15,0),0) + IFERROR(_xlfn.XLOOKUP(BJ28,'Lookup Tables'!$G$11:$G$16,'Lookup Tables'!$H$11:$H$16,0),0) + IFERROR(_xlfn.XLOOKUP(BN28,'Lookup Tables'!$P$11:$P$15,'Lookup Tables'!$Q$11:$Q$15,0),0) + _xlfn.IFS(BM28="No Evidence",10, BM28="Unknown",3, BM28="Likely",0, BM28="Confirmed",-10, TRUE,3) + IFERROR(_xlfn.XLOOKUP(BP28,'Lookup Tables'!$J$21:$J$24,'Lookup Tables'!$K$21:$K$24,0),0) ))} | CE28: {=MIN(100, MAX(0, IF(ISNUMBER(BV28)*AND(BV28>0), 10, 0) + _xlfn.IFS(BY28="Independently Verified",25, BY28="Yes",15, TRUE,0) + IFERROR(_xlfn.XLOOKUP(BZ28,'Lookup Tables'!$A$21:$A$24,'Lookup Tables'!$B$21:$B$24,0),0) + IFERROR(_xlfn.XLOOKUP(CA28,'Lookup Tables'!$D$21:$D$24,'Lookup Tables'!$E$21:$E$24,0),0) + _xlfn.IFS(ISNUMBER(CB28)*AND(CB28>=11),15, ISNUMBER(CB28)*AND(CB28>=6),10, ISNUMBER(CB28)*AND(CB28>=1),5, TRUE,0) + IFERROR(_xlfn.XLOOKUP(CC28,'Lookup Tables'!$G$21:$G$25,'Lookup Tables'!$H$21:$H$25,0),0) - IF(ISNUMBER(BW28)*AND(ISNUMBER(BV28))*AND(BW28>BV28), 20, 0) - IF(AND(BY28="Yes", ISNUMBER(BW28), BW28>60), 10, 0) ))} | CG28: UCB is committed to net zero ... SBTi Net-Zero standard | CH28: iar_2025-web.pdf | CI28: 28 | CJ28: PASS | CK28: PASS | CL28: PASS | CM28: PASS | CN28: PASS | CO28: PASS | CP28: PASS | CQ28: PASS | CR28: =COUNTIF(CJ28:CQ28,"FAIL") | CS28: =COUNTIF(CJ28:CQ28,"PARTIAL") | CT28: =COUNTIF(CJ28:CQ28,"MISSING") | CU28: =MIN(100, CR28*15 + CS28*6 + CT28*3 + IFERROR(_xlfn.XLOOKUP(CW28,'Lookup Tables'!$M$21:$M$25,'Lookup Tables'!$N$21:$N$25,0),0) ) | CV28: =IFERROR( CHOOSE( MATCH("FAIL",CJ28:CQ28,0), "1-Specificity","2-Metric","3-Baseline","4-Target", "5-Time Horizon","6-Scope","7-Verification","8-Consistency" ), IFERROR( CHOOSE( MATCH("PARTIAL",CJ28:CQ28,0), "1-Specificity","2-Metric","3-Baseline","4-Target", "5-Time Horizon","6-Scope","7-Verification","8-Consistency" ), "No failures" ) ) | DA28: =IF(OR(CU28>=50,CW28="Material",CW28="Severe",AS28="Material",AS28="Severe",BF28="Material",BF28="Severe — Exclusion Trigger",AND(ISNUMBER(BS28),BS28<30)),"Yes","No") | DB28: =IF(OR(CR28>=6,AW28="Confirmed Violation",AX28="Confirmed Breach"),"Yes — Automatic",IF(CW28="Severe","Yes — Requires Captain Confirmation","No")) | DC28: UCB is committed to net zero ... SBTi Net-Zero standard | DD28: iar_2025-web.pdf | DE28: 28 | DF28: 4 | DG28: 4 | DH28: PENDING | DL28: =IF(OR(IFERROR(VALUE(LEFT(DF28,1)),99)<=2,IFERROR(VALUE(LEFT(DG28,1)),99)<=2),"Flagged","Clear") | DM28: =IF(OR(DA28="Yes",DB28<>"No",DH28="Unverified",DL28="Flagged"),"Yes","No") | DN28: {=MIN(100, IF(ISNUMBER(V28), _xlfn.IFS(V28>=3,25, V28=2,15, V28=1,5, TRUE,0), 0) + IFERROR(_xlfn.IFS(VALUE(LEFT(DF28,1))=5,25, VALUE(LEFT(DF28,1))=4,20, VALUE(LEFT(DF28,1))=3,15, VALUE(LEFT(DF28,1))=2,8, TRUE,0), 15) + IFERROR(_xlfn.IFS(VALUE(LEFT(DG28,1))=5,25, VALUE(LEFT(DG28,1))=4,20, VALUE(LEFT(DG28,1))=3,15, VALUE(LEFT(DG28,1))=2,8, TRUE,0), 15) + _xlfn.IFS(DH28="Fully Verified",25, DH28="Partially Verified",12, TRUE,0) )} | DO28: {=_xlfn.IFS( ISBLANK(AR28), "Insufficient Evidence", AND(AR28>=65, AJ28="Approved"), "Strong", AR28>=65, "Adequate", AR28>=40, "Adequate", AR28>=20, "Weak", TRUE, "Insufficient Evidence" )} | DP28: {=_xlfn.IFS( ISBLANK(BS28), "Insufficient Evidence", BS28>=65, "Strong", BS28>=40, "Adequate", BS28>=20, "Weak", TRUE, "Insufficient Evidence" )} | DQ28: {=_xlfn.IFS( ISBLANK(BE28), "Insufficient Evidence", OR(AW28="Confirmed Violation", AX28="Confirmed Breach"), "Severe — Hard Trigger", BE28>=65, "Strong", BE28>=40, "Adequate", BE28>=20, "Weak", TRUE, "Insufficient Evidence" )} | DR28: {=_xlfn.IFS( ISBLANK(CU28), "Insufficient Evidence", CU28<=20, "Low Risk", CU28<=50, "Moderate Risk", CU28<=75, "High Risk", TRUE, "Very High Risk" )} | DS28: {=_xlfn.IFS( ISBLANK(CE28), "Insufficient Evidence", AND(ISNUMBER(BW28),ISNUMBER(BV28),BW28>BV28), "Overclaiming Risk", CE28>=65, "Strong", CE28>=40, "Adequate", TRUE, "Weak" )} | DT28: =IF(DB28="Yes — Automatic",0,ROUND((IF(ISNUMBER(AR28),AR28,0)*0.3+IF(ISNUMBER(BS28),BS28,0)*0.2+IF(ISNUMBER(BE28),BE28,0)*0.2+IF(ISNUMBER(CE28),CE28,0)*0.15+(100-IF(ISNUMBER(CU28),CU28,50))*0.15)*IF(DN28>=75,1,IF(DN28>=50,0.9,IF(DN28>=25,0.75,0.6))),1)) | DU28: {=_xlfn.IFS( DV28="Upgraded to Clear", "Clear", DV28="Downgraded to Watchlist", "Watchlist", DV28="Downgraded to Exclusion", "Exclusion Risk", DB28="Yes — Automatic", "Exclusion Risk", OR(AW28="Confirmed Violation", AX28="Confirmed Breach"), "Exclusion Risk", OR(V28=0, ISBLANK(V28), DN28<20), "Insufficient Evidence", AND(DT28>=65, DA28="No", DB28="No"), "Clear", OR(DT28>=40, DA28="Yes"), "Watchlist", TRUE, "Exclusion Risk" )} | DW28: {=_xlfn.IFS( DU28="Exclusion Risk", "Exclude — Hard Trigger", DU28="Insufficient Evidence", "Watchlist — Further Evidence Needed", DU28="Watchlist", "Watchlist — Further Evidence Needed", AND(DU28="Clear", DT28>=80), "Include — No Conditions", DU28="Clear", "Include — Monitor", TRUE, "Watchlist — Further Evidence Needed" )} | DX28: Main claim: "UCB is committed to net zero ... SBTi Net-Zero standard" (iar_2025-web.pdf, p28). SBTi: Targets set, 1.5°C near-term target (2030). 8-Test: 0 PARTIAL, 0 FAIL, 0 MISSING -> PASS. Pharma integrated annual report. Strong climate disclosure — SBTi-Net-Zero-standard-aligned targets, 90% absolute reduction vs an explicit 2019 base year, transition plan fully embedded in capital allocation, externally assured. One MED... | EB28: =IF(OR(V28=0, ISBLANK(V28)), "MISSING — No sources reviewed", "") | EC28: =IF(AND(NOT(ISBLANK(DC28)), ISBLANK(DE28)), "PAGE REF MISSING", "")
A29: AstraZeneca PLC | B29: ZEG | C29: GB0009895292 | F29: =IF(ISBLANK('Universe Tracker'!F25),"",'Universe Tracker'!F25) | G29: =IF(ISBLANK('Universe Tracker'!G25),"",'Universe Tracker'!G25) | J29: =IF(ISBLANK(B29),"",B29&"_"&C29) | O29: Yes | P29: Yes | Y29: =IF(AND(V29>=2,K29="Yes",L29="Yes"),"Sufficient",IF(AND(V29>=1,OR(K29="Yes",L29="Yes")),"Thin","Insufficient")) | AJ29: Targets set (1.5°C) | AK29: FY2030 | AR29: {=MIN(100, MAX(0, IFERROR(_xlfn.XLOOKUP(AJ29,'Lookup Tables'!$A$2:$A$7,'Lookup Tables'!$B$2:$B$7,0),0) + IF(Z29="Yes", IF(IFERROR(_xlfn.XLOOKUP(AJ29,'Lookup Tables'!$A$2:$A$7,'Lookup Tables'!$B$2:$B$7,0),0)<20, 5, 0), 0) + _xlfn.IFS(AB29="Yes", IF(ISNUMBER(AC29)*AND(AC29<=2030),15,10), AB29="Long-term Only", 5, AB29="No", 0, TRUE, 0) + _xlfn.IFS(AF29="Full",10, AF29="Partial",5, AF29="Scope 2 Only",3, TRUE,0) + _xlfn.IFS(AG29="Yes", IF(ISNUMBER(AH29)*AND(AH29>=5),10,6), AG29="Partial",4, TRUE,0) + _xlfn.IFS(AI29="Yes",5, AI29="Partial (material categories only)",3, TRUE,0) + _xlfn.IFS(AL29="Yes — Detailed",10, AL29="Yes — High Level",5, TRUE,0) + _xlfn.IFS(AM29="Yes — Quantified",15, AM29="Yes — Directional Only",7, TRUE,0) + _xlfn.IFS(AP29="Formal",5, AP29="Referenced",2, TRUE,0) + _xlfn.IFS(AQ29="No Issues Found",5, AQ29="Concern Identified",-5, AQ29="Severe Contradiction",-15, TRUE,0) + _xlfn.IFS(BC29="Reasonable Assurance",5, BC29="Limited Assurance",3, TRUE,0) - IF(AND(Z29="Yes", AI29="No"), 10, 0) - IF(AND(Z29="Yes", AM29="No"), 10, 0) ))} | BE29: {=MIN(100, MAX(0, IFERROR(_xlfn.XLOOKUP(AT29,'Lookup Tables'!$D$2:$D$6,'Lookup Tables'!$E$2:$E$6,0),0) + IFERROR(_xlfn.XLOOKUP(AV29,'Lookup Tables'!$G$2:$G$5,'Lookup Tables'!$H$2:$H$5,0),0) + IFERROR(_xlfn.XLOOKUP(AW29,'Lookup Tables'!$J$2:$J$5,'Lookup Tables'!$K$2:$K$5,0),0) + _xlfn.IFS(AX29="No Issues",10, AX29="Complaint Filed",3, AX29="Confirmed Breach",-15, TRUE,0) + IFERROR(_xlfn.XLOOKUP(AY29,'Lookup Tables'!$M$2:$M$6,'Lookup Tables'!$N$2:$N$6,0),0) + IFERROR(_xlfn.XLOOKUP(AZ29,'Lookup Tables'!$P$2:$P$6,'Lookup Tables'!$Q$2:$Q$6,0),0) + _xlfn.IFS(BA29="Formal Board Committee",5, BA29="Board Oversight Mentioned",2, TRUE,0) + _xlfn.IFS(BB29="Yes — Quantified Targets",5, BB29="Yes — Discretionary Only",2, TRUE,0) + _xlfn.IFS(BC29="Reasonable Assurance",5, BC29="Limited Assurance",3, BC29="Management Review Only",1, TRUE,0) ))} | BS29: {=MIN(100, MAX(0, IFERROR(_xlfn.XLOOKUP(BG29,'Lookup Tables'!$A$11:$A$16,'Lookup Tables'!$B$11:$B$16,0),0) + IFERROR(_xlfn.XLOOKUP(BR29,'Lookup Tables'!$M$11:$M$14,'Lookup Tables'!$N$11:$N$14,0),0) + IFERROR(_xlfn.XLOOKUP(BQ29,'Lookup Tables'!$J$11:$J$15,'Lookup Tables'!$K$11:$K$15,0),0) + IFERROR(_xlfn.XLOOKUP(BH29,'Lookup Tables'!$D$11:$D$15,'Lookup Tables'!$E$11:$E$15,0),0) + IFERROR(_xlfn.XLOOKUP(BJ29,'Lookup Tables'!$G$11:$G$16,'Lookup Tables'!$H$11:$H$16,0),0) + IFERROR(_xlfn.XLOOKUP(BN29,'Lookup Tables'!$P$11:$P$15,'Lookup Tables'!$Q$11:$Q$15,0),0) + _xlfn.IFS(BM29="No Evidence",10, BM29="Unknown",3, BM29="Likely",0, BM29="Confirmed",-10, TRUE,3) + IFERROR(_xlfn.XLOOKUP(BP29,'Lookup Tables'!$J$21:$J$24,'Lookup Tables'!$K$21:$K$24,0),0) ))} | CE29: {=MIN(100, MAX(0, IF(ISNUMBER(BV29)*AND(BV29>0), 10, 0) + _xlfn.IFS(BY29="Independently Verified",25, BY29="Yes",15, TRUE,0) + IFERROR(_xlfn.XLOOKUP(BZ29,'Lookup Tables'!$A$21:$A$24,'Lookup Tables'!$B$21:$B$24,0),0) + IFERROR(_xlfn.XLOOKUP(CA29,'Lookup Tables'!$D$21:$D$24,'Lookup Tables'!$E$21:$E$24,0),0) + _xlfn.IFS(ISNUMBER(CB29)*AND(CB29>=11),15, ISNUMBER(CB29)*AND(CB29>=6),10, ISNUMBER(CB29)*AND(CB29>=1),5, TRUE,0) + IFERROR(_xlfn.XLOOKUP(CC29,'Lookup Tables'!$G$21:$G$25,'Lookup Tables'!$H$21:$H$25,0),0) - IF(ISNUMBER(BW29)*AND(ISNUMBER(BV29))*AND(BW29>BV29), 20, 0) - IF(AND(BY29="Yes", ISNUMBER(BW29), BW29>60), 10, 0) ))} | CG29: the aim of achieving science-based net zero ... to achieve net zero by 2045 | CH29: AstraZeneca_AR_2025.pdf | CI29: 9 | CJ29: PASS | CK29: PASS | CL29: PASS | CM29: PASS | CN29: PASS | CO29: PASS | CP29: PASS | CQ29: PASS | CR29: =COUNTIF(CJ29:CQ29,"FAIL") | CS29: =COUNTIF(CJ29:CQ29,"PARTIAL") | CT29: =COUNTIF(CJ29:CQ29,"MISSING") | CU29: =MIN(100, CR29*15 + CS29*6 + CT29*3 + IFERROR(_xlfn.XLOOKUP(CW29,'Lookup Tables'!$M$21:$M$25,'Lookup Tables'!$N$21:$N$25,0),0) ) | CV29: =IFERROR( CHOOSE( MATCH("FAIL",CJ29:CQ29,0), "1-Specificity","2-Metric","3-Baseline","4-Target", "5-Time Horizon","6-Scope","7-Verification","8-Consistency" ), IFERROR( CHOOSE( MATCH("PARTIAL",CJ29:CQ29,0), "1-Specificity","2-Metric","3-Baseline","4-Target", "5-Time Horizon","6-Scope","7-Verification","8-Consistency" ), "No failures" ) ) | DA29: =IF(OR(CU29>=50,CW29="Material",CW29="Severe",AS29="Material",AS29="Severe",BF29="Material",BF29="Severe — Exclusion Trigger",AND(ISNUMBER(BS29),BS29<30)),"Yes","No") | DB29: =IF(OR(CR29>=6,AW29="Confirmed Violation",AX29="Confirmed Breach"),"Yes — Automatic",IF(CW29="Severe","Yes — Requires Captain Confirmation","No")) | DC29: the aim of achieving science-based net zero ... to achieve net zero by 2045 | DD29: AstraZeneca_AR_2025.pdf | DE29: 9 | DF29: 4 | DG29: 4 | DH29: PENDING | DL29: =IF(OR(IFERROR(VALUE(LEFT(DF29,1)),99)<=2,IFERROR(VALUE(LEFT(DG29,1)),99)<=2),"Flagged","Clear") | DM29: =IF(OR(DA29="Yes",DB29<>"No",DH29="Unverified",DL29="Flagged"),"Yes","No") | DN29: {=MIN(100, IF(ISNUMBER(V29), _xlfn.IFS(V29>=3,25, V29=2,15, V29=1,5, TRUE,0), 0) + IFERROR(_xlfn.IFS(VALUE(LEFT(DF29,1))=5,25, VALUE(LEFT(DF29,1))=4,20, VALUE(LEFT(DF29,1))=3,15, VALUE(LEFT(DF29,1))=2,8, TRUE,0), 15) + IFERROR(_xlfn.IFS(VALUE(LEFT(DG29,1))=5,25, VALUE(LEFT(DG29,1))=4,20, VALUE(LEFT(DG29,1))=3,15, VALUE(LEFT(DG29,1))=2,8, TRUE,0), 15) + _xlfn.IFS(DH29="Fully Verified",25, DH29="Partially Verified",12, TRUE,0) )} | DO29: {=_xlfn.IFS( ISBLANK(AR29), "Insufficient Evidence", AND(AR29>=65, AJ29="Approved"), "Strong", AR29>=65, "Adequate", AR29>=40, "Adequate", AR29>=20, "Weak", TRUE, "Insufficient Evidence" )} | DP29: {=_xlfn.IFS( ISBLANK(BS29), "Insufficient Evidence", BS29>=65, "Strong", BS29>=40, "Adequate", BS29>=20, "Weak", TRUE, "Insufficient Evidence" )} | DQ29: {=_xlfn.IFS( ISBLANK(BE29), "Insufficient Evidence", OR(AW29="Confirmed Violation", AX29="Confirmed Breach"), "Severe — Hard Trigger", BE29>=65, "Strong", BE29>=40, "Adequate", BE29>=20, "Weak", TRUE, "Insufficient Evidence" )} | DR29: {=_xlfn.IFS( ISBLANK(CU29), "Insufficient Evidence", CU29<=20, "Low Risk", CU29<=50, "Moderate Risk", CU29<=75, "High Risk", TRUE, "Very High Risk" )} | DS29: {=_xlfn.IFS( ISBLANK(CE29), "Insufficient Evidence", AND(ISNUMBER(BW29),ISNUMBER(BV29),BW29>BV29), "Overclaiming Risk", CE29>=65, "Strong", CE29>=40, "Adequate", TRUE, "Weak" )} | DT29: =IF(DB29="Yes — Automatic",0,ROUND((IF(ISNUMBER(AR29),AR29,0)*0.3+IF(ISNUMBER(BS29),BS29,0)*0.2+IF(ISNUMBER(BE29),BE29,0)*0.2+IF(ISNUMBER(CE29),CE29,0)*0.15+(100-IF(ISNUMBER(CU29),CU29,50))*0.15)*IF(DN29>=75,1,IF(DN29>=50,0.9,IF(DN29>=25,0.75,0.6))),1)) | DU29: {=_xlfn.IFS( DV29="Upgraded to Clear", "Clear", DV29="Downgraded to Watchlist", "Watchlist", DV29="Downgraded to Exclusion", "Exclusion Risk", DB29="Yes — Automatic", "Exclusion Risk", OR(AW29="Confirmed Violation", AX29="Confirmed Breach"), "Exclusion Risk", OR(V29=0, ISBLANK(V29), DN29<20), "Insufficient Evidence", AND(DT29>=65, DA29="No", DB29="No"), "Clear", OR(DT29>=40, DA29="Yes"), "Watchlist", TRUE, "Exclusion Risk" )} | DW29: {=_xlfn.IFS( DU29="Exclusion Risk", "Exclude — Hard Trigger", DU29="Insufficient Evidence", "Watchlist — Further Evidence Needed", DU29="Watchlist", "Watchlist — Further Evidence Needed", AND(DU29="Clear", DT29>=80), "Include — No Conditions", DU29="Clear", "Include — Monitor", TRUE, "Watchlist — Further Evidence Needed" )} | DX29: Main claim: "the aim of achieving science-based net zero ... to achieve net zero by 2045" (AstraZeneca_AR_2025.pdf, p9). SBTi: Targets set, 1.5°C near-term target (FY2030). 8-Test: 0 PARTIAL, 0 FAIL, 0 MISSING -> PASS. Pharma annual report. Strong climate disclosure — SBTi-verified Net-Zero-Standard targets, 98% near-term absolute target on a 2015 baseline, independent sustainability assurance. One MED (assurance level). NOTE: a 2025 China legal... | EB29: =IF(OR(V29=0, ISBLANK(V29)), "MISSING — No sources reviewed", "") | EC29: =IF(AND(NOT(ISBLANK(DC29)), ISBLANK(DE29)), "PAGE REF MISSING", "")
A30: Gaztransport Et Technigaz SA | B30: 9TG | C30: =IF(ISBLANK('Universe Tracker'!D26),"",'Universe Tracker'!D26) | F30: =IF(ISBLANK('Universe Tracker'!F26),"",'Universe Tracker'!F26) | G30: =IF(ISBLANK('Universe Tracker'!G26),"",'Universe Tracker'!G26) | J30: =IF(ISBLANK(B30),"",B30&"_"&C30) | Y30: =IF(AND(V30>=2,K30="Yes",L30="Yes"),"Sufficient",IF(AND(V30>=1,OR(K30="Yes",L30="Yes")),"Thin","Insufficient")) | AR30: {=MIN(100, MAX(0, IFERROR(_xlfn.XLOOKUP(AJ30,'Lookup Tables'!$A$2:$A$7,'Lookup Tables'!$B$2:$B$7,0),0) + IF(Z30="Yes", IF(IFERROR(_xlfn.XLOOKUP(AJ30,'Lookup Tables'!$A$2:$A$7,'Lookup Tables'!$B$2:$B$7,0),0)<20, 5, 0), 0) + _xlfn.IFS(AB30="Yes", IF(ISNUMBER(AC30)*AND(AC30<=2030),15,10), AB30="Long-term Only", 5, AB30="No", 0, TRUE, 0) + _xlfn.IFS(AF30="Full",10, AF30="Partial",5, AF30="Scope 2 Only",3, TRUE,0) + _xlfn.IFS(AG30="Yes", IF(ISNUMBER(AH30)*AND(AH30>=5),10,6), AG30="Partial",4, TRUE,0) + _xlfn.IFS(AI30="Yes",5, AI30="Partial (material categories only)",3, TRUE,0) + _xlfn.IFS(AL30="Yes — Detailed",10, AL30="Yes — High Level",5, TRUE,0) + _xlfn.IFS(AM30="Yes — Quantified",15, AM30="Yes — Directional Only",7, TRUE,0) + _xlfn.IFS(AP30="Formal",5, AP30="Referenced",2, TRUE,0) + _xlfn.IFS(AQ30="No Issues Found",5, AQ30="Concern Identified",-5, AQ30="Severe Contradiction",-15, TRUE,0) + _xlfn.IFS(BC30="Reasonable Assurance",5, BC30="Limited Assurance",3, TRUE,0) - IF(AND(Z30="Yes", AI30="No"), 10, 0) - IF(AND(Z30="Yes", AM30="No"), 10, 0) ))} | BE30: {=MIN(100, MAX(0, IFERROR(_xlfn.XLOOKUP(AT30,'Lookup Tables'!$D$2:$D$6,'Lookup Tables'!$E$2:$E$6,0),0) + IFERROR(_xlfn.XLOOKUP(AV30,'Lookup Tables'!$G$2:$G$5,'Lookup Tables'!$H$2:$H$5,0),0) + IFERROR(_xlfn.XLOOKUP(AW30,'Lookup Tables'!$J$2:$J$5,'Lookup Tables'!$K$2:$K$5,0),0) + _xlfn.IFS(AX30="No Issues",10, AX30="Complaint Filed",3, AX30="Confirmed Breach",-15, TRUE,0) + IFERROR(_xlfn.XLOOKUP(AY30,'Lookup Tables'!$M$2:$M$6,'Lookup Tables'!$N$2:$N$6,0),0) + IFERROR(_xlfn.XLOOKUP(AZ30,'Lookup Tables'!$P$2:$P$6,'Lookup Tables'!$Q$2:$Q$6,0),0) + _xlfn.IFS(BA30="Formal Board Committee",5, BA30="Board Oversight Mentioned",2, TRUE,0) + _xlfn.IFS(BB30="Yes — Quantified Targets",5, BB30="Yes — Discretionary Only",2, TRUE,0) + _xlfn.IFS(BC30="Reasonable Assurance",5, BC30="Limited Assurance",3, BC30="Management Review Only",1, TRUE,0) ))} | BS30: {=MIN(100, MAX(0, IFERROR(_xlfn.XLOOKUP(BG30,'Lookup Tables'!$A$11:$A$16,'Lookup Tables'!$B$11:$B$16,0),0) + IFERROR(_xlfn.XLOOKUP(BR30,'Lookup Tables'!$M$11:$M$14,'Lookup Tables'!$N$11:$N$14,0),0) + IFERROR(_xlfn.XLOOKUP(BQ30,'Lookup Tables'!$J$11:$J$15,'Lookup Tables'!$K$11:$K$15,0),0) + IFERROR(_xlfn.XLOOKUP(BH30,'Lookup Tables'!$D$11:$D$15,'Lookup Tables'!$E$11:$E$15,0),0) + IFERROR(_xlfn.XLOOKUP(BJ30,'Lookup Tables'!$G$11:$G$16,'Lookup Tables'!$H$11:$H$16,0),0) + IFERROR(_xlfn.XLOOKUP(BN30,'Lookup Tables'!$P$11:$P$15,'Lookup Tables'!$Q$11:$Q$15,0),0) + _xlfn.IFS(BM30="No Evidence",10, BM30="Unknown",3, BM30="Likely",0, BM30="Confirmed",-10, TRUE,3) + IFERROR(_xlfn.XLOOKUP(BP30,'Lookup Tables'!$J$21:$J$24,'Lookup Tables'!$K$21:$K$24,0),0) ))} | CE30: {=MIN(100, MAX(0, IF(ISNUMBER(BV30)*AND(BV30>0), 10, 0) + _xlfn.IFS(BY30="Independently Verified",25, BY30="Yes",15, TRUE,0) + IFERROR(_xlfn.XLOOKUP(BZ30,'Lookup Tables'!$A$21:$A$24,'Lookup Tables'!$B$21:$B$24,0),0) + IFERROR(_xlfn.XLOOKUP(CA30,'Lookup Tables'!$D$21:$D$24,'Lookup Tables'!$E$21:$E$24,0),0) + _xlfn.IFS(ISNUMBER(CB30)*AND(CB30>=11),15, ISNUMBER(CB30)*AND(CB30>=6),10, ISNUMBER(CB30)*AND(CB30>=1),5, TRUE,0) + IFERROR(_xlfn.XLOOKUP(CC30,'Lookup Tables'!$G$21:$G$25,'Lookup Tables'!$H$21:$H$25,0),0) - IF(ISNUMBER(BW30)*AND(ISNUMBER(BV30))*AND(BW30>BV30), 20, 0) - IF(AND(BY30="Yes", ISNUMBER(BW30), BW30>60), 10, 0) ))} | CR30: =COUNTIF(CJ30:CQ30,"FAIL") | CS30: =COUNTIF(CJ30:CQ30,"PARTIAL") | CT30: =COUNTIF(CJ30:CQ30,"MISSING") | CU30: =MIN(100, CR30*15 + CS30*6 + CT30*3 + IFERROR(_xlfn.XLOOKUP(CW30,'Lookup Tables'!$M$21:$M$25,'Lookup Tables'!$N$21:$N$25,0),0) ) | CV30: =IFERROR( CHOOSE( MATCH("FAIL",CJ30:CQ30,0), "1-Specificity","2-Metric","3-Baseline","4-Target", "5-Time Horizon","6-Scope","7-Verification","8-Consistency" ), IFERROR( CHOOSE( MATCH("PARTIAL",CJ30:CQ30,0), "1-Specificity","2-Metric","3-Baseline","4-Target", "5-Time Horizon","6-Scope","7-Verification","8-Consistency" ), "No failures" ) ) | DA30: =IF(OR(CU30>=50,CW30="Material",CW30="Severe",AS30="Material",AS30="Severe",BF30="Material",BF30="Severe — Exclusion Trigger",AND(ISNUMBER(BS30),BS30<30)),"Yes","No") | DB30: =IF(OR(CR30>=6,AW30="Confirmed Violation",AX30="Confirmed Breach"),"Yes — Automatic",IF(CW30="Severe","Yes — Requires Captain Confirmation","No")) | DL30: =IF(OR(IFERROR(VALUE(LEFT(DF30,1)),99)<=2,IFERROR(VALUE(LEFT(DG30,1)),99)<=2),"Flagged","Clear") | DM30: =IF(OR(DA30="Yes",DB30<>"No",DH30="Unverified",DL30="Flagged"),"Yes","No") | DN30: {=MIN(100, IF(ISNUMBER(V30), _xlfn.IFS(V30>=3,25, V30=2,15, V30=1,5, TRUE,0), 0) + IFERROR(_xlfn.IFS(VALUE(LEFT(DF30,1))=5,25, VALUE(LEFT(DF30,1))=4,20, VALUE(LEFT(DF30,1))=3,15, VALUE(LEFT(DF30,1))=2,8, TRUE,0), 15) + IFERROR(_xlfn.IFS(VALUE(LEFT(DG30,1))=5,25, VALUE(LEFT(DG30,1))=4,20, VALUE(LEFT(DG30,1))=3,15, VALUE(LEFT(DG30,1))=2,8, TRUE,0), 15) + _xlfn.IFS(DH30="Fully Verified",25, DH30="Partially Verified",12, TRUE,0) )} | DO30: {=_xlfn.IFS( ISBLANK(AR30), "Insufficient Evidence", AND(AR30>=65, AJ30="Approved"), "Strong", AR30>=65, "Adequate", AR30>=40, "Adequate", AR30>=20, "Weak", TRUE, "Insufficient Evidence" )} | DP30: {=_xlfn.IFS( ISBLANK(BS30), "Insufficient Evidence", BS30>=65, "Strong", BS30>=40, "Adequate", BS30>=20, "Weak", TRUE, "Insufficient Evidence" )} | DQ30: {=_xlfn.IFS( ISBLANK(BE30), "Insufficient Evidence", OR(AW30="Confirmed Violation", AX30="Confirmed Breach"), "Severe — Hard Trigger", BE30>=65, "Strong", BE30>=40, "Adequate", BE30>=20, "Weak", TRUE, "Insufficient Evidence" )} | DR30: {=_xlfn.IFS( ISBLANK(CU30), "Insufficient Evidence", CU30<=20, "Low Risk", CU30<=50, "Moderate Risk", CU30<=75, "High Risk", TRUE, "Very High Risk" )} | DS30: {=_xlfn.IFS( ISBLANK(CE30), "Insufficient Evidence", AND(ISNUMBER(BW30),ISNUMBER(BV30),BW30>BV30), "Overclaiming Risk", CE30>=65, "Strong", CE30>=40, "Adequate", TRUE, "Weak" )} | DT30: =IF(DB30="Yes — Automatic",0,ROUND((IF(ISNUMBER(AR30),AR30,0)*0.3+IF(ISNUMBER(BS30),BS30,0)*0.2+IF(ISNUMBER(BE30),BE30,0)*0.2+IF(ISNUMBER(CE30),CE30,0)*0.15+(100-IF(ISNUMBER(CU30),CU30,50))*0.15)*IF(DN30>=75,1,IF(DN30>=50,0.9,IF(DN30>=25,0.75,0.6))),1)) | DU30: {=_xlfn.IFS( DV30="Upgraded to Clear", "Clear", DV30="Downgraded to Watchlist", "Watchlist", DV30="Downgraded to Exclusion", "Exclusion Risk", DB30="Yes — Automatic", "Exclusion Risk", OR(AW30="Confirmed Violation", AX30="Confirmed Breach"), "Exclusion Risk", OR(V30=0, ISBLANK(V30), DN30<20), "Insufficient Evidence", AND(DT30>=65, DA30="No", DB30="No"), "Clear", OR(DT30>=40, DA30="Yes"), "Watchlist", TRUE, "Exclusion Risk" )} | DW30: {=_xlfn.IFS( DU30="Exclusion Risk", "Exclude — Hard Trigger", DU30="Insufficient Evidence", "Watchlist — Further Evidence Needed", DU30="Watchlist", "Watchlist — Further Evidence Needed", AND(DU30="Clear", DT30>=80), "Include — No Conditions", DU30="Clear", "Include — Monitor", TRUE, "Watchlist — Further Evidence Needed" )} | EB30: =IF(OR(V30=0, ISBLANK(V30)), "MISSING — No sources reviewed", "") | EC30: =IF(AND(NOT(ISBLANK(DC30)), ISBLANK(DE30)), "PAGE REF MISSING", "")
